Workbook

Sheet Pre-Audit Scoping
A1: PRE-AUDIT SCOPING & FACILITY PROFILE
A2: Complete this tab before beginning the audit. Answers determine which items apply to this facility.
A4: SECTION 1 — FACILITY & AUDIT INFORMATION
B5: Facility / Site Name | D5: Test
B6: Facility Address | D6: 100 Test Way
B7: City, State, ZIP | D7: Test, Test 12345
B8: NAICS Code | D8: 12345
B9: Approximate Headcount (total employees) | D9: 78
B10: Audit Date(s) | D10: July 7-9 2026
B11: Lead Auditor | D11: Sara Wallon
B12: Co-Auditor(s) | D12: Gabriel Wallon
B13: Audit Scope | D13: Full OSHA GI Compliance Audit
B14: Attorney of Record | D14: Conn Maciel Carey LLP
B15: Privilege Contact (Attorney) | D15: Nick Scala
B16: Audit conducted under attorney-client privilege? | D16: Yes
B17: State / Jurisdiction (State Plan) | D17: Maryland (MOSH)
A18: SECTION 2 — PROCESS & EQUIPMENT INVENTORY
B19: Question | D19: Yes / No | E19: Audit Impact
B20: Does this facility have permit-required confined spaces (PRCS)? | D20: Yes | E20: All Confined Space items (CS-1 through CS-24) apply
B21: Does this facility have powered industrial trucks (forklifts, pallet jacks)? | D21: Yes | E21: All Forklifts & Materials items (PIT-1 through PIT-11) apply
B22: Does this facility have overhead cranes, gantry cranes, or hoists? | D22: Yes | E22: All Cranes, Hoists & Rigging items (CR-1 through CR-10) apply
B23: Does this facility have welding, cutting, or brazing operations? | D23: Yes | E23: All Welding & Hot Work items (WC-1 through WC-10) apply
B24: Do any employees have occupational exposure to blood or OPIM (first aid)? | D24: Yes | E24: Bloodborne Pathogens items BP-1 through BP-7 apply
B25: Does this facility have automatic sprinkler systems? | D25: Yes | E25: Fire Protection items FP-5 through FP-8 (sprinklers) apply
B26: Does this facility have standpipe and hose systems? | D26: No | E26: Fire Protection item FP-16 (standpipe systems) applies
B27: Does this facility use LP gas / propane? | D27: Yes | E27: Hazardous Materials items HM-9 through HM-11 (LP gas) apply
B28: Does this facility have abrasive blasting operations? | D28: No | E28: Occupational Health item OH-1 (abrasive blasting ventilation) applies
B29: Does this facility have spray finishing / painting operations? | D29: No | E29: Occupational Health item OH-3 (spray finishing ventilation) applies
B30: Does this facility have mechanical power presses? | D30: No | E30: Machine Guarding items MG-11 and MG-12 (power presses) apply
... B34: Does this facility generate or process combustible dust? | D34: Yes | E34: Hazard Communication item HC-10 (combustible dust) applies
A36: SECTION 3 — ATTORNEY-CLIENT PRIVILEGE CERTIFICATION
B37: This audit was conducted at the direction of legal counsel under the protection of attorney-client privilege. All findings, observations, and recommendations contained in this audit instrument are confidential attorney-client communications prepared in anticipation of litigation. This document shall not be disclosed to any party without prior written authorization from legal counsel.
B38: Lead Auditor Signature / Date

Sheet HSE Dashboard
A1: WLS AUDIT COACH OSHA — HSE AUDIT DASHBOARD
A2: National Gypsum Company | WLS Audit Coach OSHA Pilot | Prepared under attorney-client privilege
A3: SITE: | G3: DATE(S): | L3: AUDITOR(S):
A5: OVERALL COMBINED SCORE | H5: FINDING SUMMARY BY RATING
A6: Combined Score | H6: Rating | J6: Count | L6: Total | T6: ='Confined Space'!B8+PPE!B8+'Walking & Working Surfaces'!B8+Recordkeeping!B8+LOTO!B8+'Egress & Emergency Action'!B8+'Fire Protection & Alarms'!B8+'Machine Guarding'!B8+'Electrical Safety'!B8+'Hand & Power Tools'!B8+'Hazard Communication'!B8+'Forklifts & Materials'!B8+'Cranes, Hoists & Rigging'!B8+'Hazardous Materials'!B8+'Occ. Health & Noise'!B8+'Medical & First Aid'!B8+'Welding & Hot Work'!B8+'BBP & Sanitation'!B8+'State Requirements'!B8 -> 98.6
A7: =T8 -> 0.046465598 | H7: Best Practice | J7: =COUNTIF('Confined Space'!E18:E48,"Best Practice")+COUNTIF(PPE!E18:E51,"Best Practice")+COUNTIF('Walking & Working Surfaces'!E18:E48,"Best Practice")+COUNTIF(Recordkeeping!E18:E59,"Best Practice")+COUNTIF(LOTO!E18:E36,"Best Practice")+COUNTIF('Egress & Emergency Action'!E18:E40,"Best Practice")+COUNTIF('Fire Protection & Alarms'!E18:E40,"Best Practice")+COUNTIF('Machine Guarding'!E18:E32,"Best Practice")+COUNTIF('Electrical Safety'!E18:E38,"Best Practice")+COUNTIF('Hand & Power Tools'!E18:E36,"Best Practice")+COUNTIF('Hazard Communication'!E18:E32,"Best Practice")+COUNTIF('Forklifts & Materials'!E18:E33,"Best Practice")+COUNTIF('Cranes, Hoists & Rigging'!E18:E31,"Best Practice")+COUNTIF('Hazardous Materials'!E18:E31,"Best Practice")+COUNTIF('Occ. Health & Noise'!E18:E29,"Best Practice")+COUNTIF('Medical & First Aid'!E18:E27,"Best Practice")+COUNTIF('Welding & Hot Work'!E18:E30,"Best Practice")+COUNTIF('BBP & Sanitation'!E18:E35,"Best Practice")+COUNTIF('State Requirements'!E19:E118,"Best Practice") -> 3 | L7: =IFERROR(J7/(('Confined Space'!C8-COUNTIF('Confined Space'!E18:E48,"Not Applicable"))+(PPE!C8-COUNTIF(PPE!E18:E51,"Not Applicable"))+('Walking & Working Surfaces'!C8-COUNTIF('Walking & Working Surfaces'!E18:E48,"Not Applicable"))+(Recordkeeping!C8-COUNTIF(Recordkeeping!E18:E59,"Not Applicable"))+(LOTO!C8-COUNTIF(LOTO!E18:E36,"Not Applicable"))+('Egress & Emergency Action'!C8-COUNTIF('Egress & Emergency Action'!E18:E40,"Not Applicable"))+('Fire Protection & Alarms'!C8-COUNTIF('Fire Protection & Alarms'!E18:E40,"Not Applicable"))+('Machine Guarding'!C8-COUNTIF('Machine Guarding'!E18:E32,"Not Applicable"))+('Electrical Safety'!C8-COUNTIF('Electrical Safety'!E18:E38,"Not Applicable"))+('Hand & Power Tools'!C8-COUNTIF('Hand & Power Tools'!E18:E36,"Not Applicable"))+('Hazard Communication'!C8-COUNTIF('Hazard Communication'!E18:E32,"Not Applicable"))+('Forklifts & Materials'!C8-COUNTIF('Forklifts & Materials'!E18:E33,"Not Applicable"))+('Cranes, Hoists & Rigging'!C8-COUNTIF('Cranes, Hoists & Rigging'!E18:E31,"Not Applicable"))+('Hazardous Materials'!C8-COUNTIF('Hazardous Materials'!E18:E31,"Not Applicable"))+('Occ. Health & Noise'!C8-COUNTIF('Occ. Health & Noise'!E18:E29,"Not Applicable"))+('Medical & First Aid'!C8-COUNTIF('Medical & First Aid'!E18:E27,"Not Applicable"))+('Welding & Hot Work'!C8-COUNTIF('Welding & Hot Work'!E18:E30,"Not Applicable"))+('BBP & Sanitation'!C8-COUNTIF('BBP & Sanitation'!E18:E35,"Not Applicable"))+('State Requirements'!C8-COUNTIF('State Requirements'!E19:E118,"Not Applicable"))),"") -> 0.0014164306 | T7: ='Confined Space'!C8+PPE!C8+'Walking & Working Surfaces'!C8+Recordkeeping!C8+LOTO!C8+'Egress & Emergency Action'!C8+'Fire Protection & Alarms'!C8+'Machine Guarding'!C8+'Electrical Safety'!C8+'Hand & Power Tools'!C8+'Hazard Communication'!C8+'Forklifts & Materials'!C8+'Cranes, Hoists & Rigging'!C8+'Hazardous Materials'!C8+'Occ. Health & Noise'!C8+'Medical & First Aid'!C8+'Welding & Hot Work'!C8+'BBP & Sanitation'!C8+'State Requirements'!C8 -> 2122
A8: =T6&" / "&T7 -> 98.6 / 2122 | H8: Verified | J8: =COUNTIF('Confined Space'!E18:E48,"Verified")+COUNTIF(PPE!E18:E51,"Verified")+COUNTIF('Walking & Working Surfaces'!E18:E48,"Verified")+COUNTIF(Recordkeeping!E18:E59,"Verified")+COUNTIF(LOTO!E18:E36,"Verified")+COUNTIF('Egress & Emergency Action'!E18:E40,"Verified")+COUNTIF('Fire Protection & Alarms'!E18:E40,"Verified")+COUNTIF('Machine Guarding'!E18:E32,"Verified")+COUNTIF('Electrical Safety'!E18:E38,"Verified")+COUNTIF('Hand & Power Tools'!E18:E36,"Verified")+COUNTIF('Hazard Communication'!E18:E32,"Verified")+COUNTIF('Forklifts & Materials'!E18:E33,"Verified")+COUNTIF('Cranes, Hoists & Rigging'!E18:E31,"Verified")+COUNTIF('Hazardous Materials'!E18:E31,"Verified")+COUNTIF('Occ. Health & Noise'!E18:E29,"Verified")+COUNTIF('Medical & First Aid'!E18:E27,"Verified")+COUNTIF('Welding & Hot Work'!E18:E30,"Verified")+COUNTIF('BBP & Sanitation'!E18:E35,"Verified")+COUNTIF('State Requirements'!E19:E118,"Verified") -> 3 | L8: =IFERROR(J8/(('Confined Space'!C8-COUNTIF('Confined Space'!E18:E48,"Not Applicable"))+(PPE!C8-COUNTIF(PPE!E18:E51,"Not Applicable"))+('Walking & Working Surfaces'!C8-COUNTIF('Walking & Working Surfaces'!E18:E48,"Not Applicable"))+(Recordkeeping!C8-COUNTIF(Recordkeeping!E18:E59,"Not Applicable"))+(LOTO!C8-COUNTIF(LOTO!E18:E36,"Not Applicable"))+('Egress & Emergency Action'!C8-COUNTIF('Egress & Emergency Action'!E18:E40,"Not Applicable"))+('Fire Protection & Alarms'!C8-COUNTIF('Fire Protection & Alarms'!E18:E40,"Not Applicable"))+('Machine Guarding'!C8-COUNTIF('Machine Guarding'!E18:E32,"Not Applicable"))+('Electrical Safety'!C8-COUNTIF('Electrical Safety'!E18:E38,"Not Applicable"))+('Hand & Power Tools'!C8-COUNTIF('Hand & Power Tools'!E18:E36,"Not Applicable"))+('Hazard Communication'!C8-COUNTIF('Hazard Communication'!E18:E32,"Not Applicable"))+('Forklifts & Materials'!C8-COUNTIF('Forklifts & Materials'!E18:E33,"Not Applicable"))+('Cranes, Hoists & Rigging'!C8-COUNTIF('Cranes, Hoists & Rigging'!E18:E31,"Not Applicable"))+('Hazardous Materials'!C8-COUNTIF('Hazardous Materials'!E18:E31,"Not Applicable"))+('Occ. Health & Noise'!C8-COUNTIF('Occ. Health & Noise'!E18:E29,"Not Applicable"))+('Medical & First Aid'!C8-COUNTIF('Medical & First Aid'!E18:E27,"Not Applicable"))+('Welding & Hot Work'!C8-COUNTIF('Welding & Hot Work'!E18:E30,"Not Applicable"))+('BBP & Sanitation'!C8-COUNTIF('BBP & Sanitation'!E18:E35,"Not Applicable"))+('State Requirements'!C8-COUNTIF('State Requirements'!E19:E118,"Not Applicable"))),"") -> 0.0014164306 | T8: =IF(T7>0,T6/T7,"N/A") -> 0.046465598
A9: Rating Tier | H9: Low | J9: =COUNTIF('Confined Space'!E18:E48,"Low")+COUNTIF(PPE!E18:E51,"Low")+COUNTIF('Walking & Working Surfaces'!E18:E48,"Low")+COUNTIF(Recordkeeping!E18:E59,"Low")+COUNTIF(LOTO!E18:E36,"Low")+COUNTIF('Egress & Emergency Action'!E18:E40,"Low")+COUNTIF('Fire Protection & Alarms'!E18:E40,"Low")+COUNTIF('Machine Guarding'!E18:E32,"Low")+COUNTIF('Electrical Safety'!E18:E38,"Low")+COUNTIF('Hand & Power Tools'!E18:E36,"Low")+COUNTIF('Hazard Communication'!E18:E32,"Low")+COUNTIF('Forklifts & Materials'!E18:E33,"Low")+COUNTIF('Cranes, Hoists & Rigging'!E18:E31,"Low")+COUNTIF('Hazardous Materials'!E18:E31,"Low")+COUNTIF('Occ. Health & Noise'!E18:E29,"Low")+COUNTIF('Medical & First Aid'!E18:E27,"Low")+COUNTIF('Welding & Hot Work'!E18:E30,"Low")+COUNTIF('BBP & Sanitation'!E18:E35,"Low")+COUNTIF('State Requirements'!E19:E118,"Low") -> 4 | L9: =IFERROR(J9/(('Confined Space'!C8-COUNTIF('Confined Space'!E18:E48,"Not Applicable"))+(PPE!C8-COUNTIF(PPE!E18:E51,"Not Applicable"))+('Walking & Working Surfaces'!C8-COUNTIF('Walking & Working Surfaces'!E18:E48,"Not Applicable"))+(Recordkeeping!C8-COUNTIF(Recordkeeping!E18:E59,"Not Applicable"))+(LOTO!C8-COUNTIF(LOTO!E18:E36,"Not Applicable"))+('Egress & Emergency Action'!C8-COUNTIF('Egress & Emergency Action'!E18:E40,"Not Applicable"))+('Fire Protection & Alarms'!C8-COUNTIF('Fire Protection & Alarms'!E18:E40,"Not Applicable"))+('Machine Guarding'!C8-COUNTIF('Machine Guarding'!E18:E32,"Not Applicable"))+('Electrical Safety'!C8-COUNTIF('Electrical Safety'!E18:E38,"Not Applicable"))+('Hand & Power Tools'!C8-COUNTIF('Hand & Power Tools'!E18:E36,"Not Applicable"))+('Hazard Communication'!C8-COUNTIF('Hazard Communication'!E18:E32,"Not Applicable"))+('Forklifts & Materials'!C8-COUNTIF('Forklifts & Materials'!E18:E33,"Not Applicable"))+('Cranes, Hoists & Rigging'!C8-COUNTIF('Cranes, Hoists & Rigging'!E18:E31,"Not Applicable"))+('Hazardous Materials'!C8-COUNTIF('Hazardous Materials'!E18:E31,"Not Applicable"))+('Occ. Health & Noise'!C8-COUNTIF('Occ. Health & Noise'!E18:E29,"Not Applicable"))+('Medical & First Aid'!C8-COUNTIF('Medical & First Aid'!E18:E27,"Not Applicable"))+('Welding & Hot Work'!C8-COUNTIF('Welding & Hot Work'!E18:E30,"Not Applicable"))+('BBP & Sanitation'!C8-COUNTIF('BBP & Sanitation'!E18:E35,"Not Applicable"))+('State Requirements'!C8-COUNTIF('State Requirements'!E19:E118,"Not Applicable"))),"") -> 0.0018885741
A10: =IF(T8="N/A","N/A",IF(T8>=0.99,"Excellence Leader",IF(T8>=0.9,"Gold",IF(T8>=0.8,"Silver",IF(T8>=0.51,"Bronze","Developing"))))) -> Developing | H10: Moderate | J10: =COUNTIF('Confined Space'!E18:E48,"Moderate")+COUNTIF(PPE!E18:E51,"Moderate")+COUNTIF('Walking & Working Surfaces'!E18:E48,"Moderate")+COUNTIF(Recordkeeping!E18:E59,"Moderate")+COUNTIF(LOTO!E18:E36,"Moderate")+COUNTIF('Egress & Emergency Action'!E18:E40,"Moderate")+COUNTIF('Fire Protection & Alarms'!E18:E40,"Moderate")+COUNTIF('Machine Guarding'!E18:E32,"Moderate")+COUNTIF('Electrical Safety'!E18:E38,"Moderate")+COUNTIF('Hand & Power Tools'!E18:E36,"Moderate")+COUNTIF('Hazard Communication'!E18:E32,"Moderate")+COUNTIF('Forklifts & Materials'!E18:E33,"Moderate")+COUNTIF('Cranes, Hoists & Rigging'!E18:E31,"Moderate")+COUNTIF('Hazardous Materials'!E18:E31,"Moderate")+COUNTIF('Occ. Health & Noise'!E18:E29,"Moderate")+COUNTIF('Medical & First Aid'!E18:E27,"Moderate")+COUNTIF('Welding & Hot Work'!E18:E30,"Moderate")+COUNTIF('BBP & Sanitation'!E18:E35,"Moderate")+COUNTIF('State Requirements'!E19:E118,"Moderate") -> 3 | L10: =IFERROR(J10/(('Confined Space'!C8-COUNTIF('Confined Space'!E18:E48,"Not Applicable"))+(PPE!C8-COUNTIF(PPE!E18:E51,"Not Applicable"))+('Walking & Working Surfaces'!C8-COUNTIF('Walking & Working Surfaces'!E18:E48,"Not Applicable"))+(Recordkeeping!C8-COUNTIF(Recordkeeping!E18:E59,"Not Applicable"))+(LOTO!C8-COUNTIF(LOTO!E18:E36,"Not Applicable"))+('Egress & Emergency Action'!C8-COUNTIF('Egress & Emergency Action'!E18:E40,"Not Applicable"))+('Fire Protection & Alarms'!C8-COUNTIF('Fire Protection & Alarms'!E18:E40,"Not Applicable"))+('Machine Guarding'!C8-COUNTIF('Machine Guarding'!E18:E32,"Not Applicable"))+('Electrical Safety'!C8-COUNTIF('Electrical Safety'!E18:E38,"Not Applicable"))+('Hand & Power Tools'!C8-COUNTIF('Hand & Power Tools'!E18:E36,"Not Applicable"))+('Hazard Communication'!C8-COUNTIF('Hazard Communication'!E18:E32,"Not Applicable"))+('Forklifts & Materials'!C8-COUNTIF('Forklifts & Materials'!E18:E33,"Not Applicable"))+('Cranes, Hoists & Rigging'!C8-COUNTIF('Cranes, Hoists & Rigging'!E18:E31,"Not Applicable"))+('Hazardous Materials'!C8-COUNTIF('Hazardous Materials'!E18:E31,"Not Applicable"))+('Occ. Health & Noise'!C8-COUNTIF('Occ. Health & Noise'!E18:E29,"Not Applicable"))+('Medical & First Aid'!C8-COUNTIF('Medical & First Aid'!E18:E27,"Not Applicable"))+('Welding & Hot Work'!C8-COUNTIF('Welding & Hot Work'!E18:E30,"Not Applicable"))+('BBP & Sanitation'!C8-COUNTIF('BBP & Sanitation'!E18:E35,"Not Applicable"))+('State Requirements'!C8-COUNTIF('State Requirements'!E19:E118,"Not Applicable"))),"") -> 0.0014164306
H11: High | J11: =COUNTIF('Confined Space'!E18:E48,"High")+COUNTIF(PPE!E18:E51,"High")+COUNTIF('Walking & Working Surfaces'!E18:E48,"High")+COUNTIF(Recordkeeping!E18:E59,"High")+COUNTIF(LOTO!E18:E36,"High")+COUNTIF('Egress & Emergency Action'!E18:E40,"High")+COUNTIF('Fire Protection & Alarms'!E18:E40,"High")+COUNTIF('Machine Guarding'!E18:E32,"High")+COUNTIF('Electrical Safety'!E18:E38,"High")+COUNTIF('Hand & Power Tools'!E18:E36,"High")+COUNTIF('Hazard Communication'!E18:E32,"High")+COUNTIF('Forklifts & Materials'!E18:E33,"High")+COUNTIF('Cranes, Hoists & Rigging'!E18:E31,"High")+COUNTIF('Hazardous Materials'!E18:E31,"High")+COUNTIF('Occ. Health & Noise'!E18:E29,"High")+COUNTIF('Medical & First Aid'!E18:E27,"High")+COUNTIF('Welding & Hot Work'!E18:E30,"High")+COUNTIF('BBP & Sanitation'!E18:E35,"High")+COUNTIF('State Requirements'!E19:E118,"High") -> 3 | L11: =IFERROR(J11/(('Confined Space'!C8-COUNTIF('Confined Space'!E18:E48,"Not Applicable"))+(PPE!C8-COUNTIF(PPE!E18:E51,"Not Applicable"))+('Walking & Working Surfaces'!C8-COUNTIF('Walking & Working Surfaces'!E18:E48,"Not Applicable"))+(Recordkeeping!C8-COUNTIF(Recordkeeping!E18:E59,"Not Applicable"))+(LOTO!C8-COUNTIF(LOTO!E18:E36,"Not Applicable"))+('Egress & Emergency Action'!C8-COUNTIF('Egress & Emergency Action'!E18:E40,"Not Applicable"))+('Fire Protection & Alarms'!C8-COUNTIF('Fire Protection & Alarms'!E18:E40,"Not Applicable"))+('Machine Guarding'!C8-COUNTIF('Machine Guarding'!E18:E32,"Not Applicable"))+('Electrical Safety'!C8-COUNTIF('Electrical Safety'!E18:E38,"Not Applicable"))+('Hand & Power Tools'!C8-COUNTIF('Hand & Power Tools'!E18:E36,"Not Applicable"))+('Hazard Communication'!C8-COUNTIF('Hazard Communication'!E18:E32,"Not Applicable"))+('Forklifts & Materials'!C8-COUNTIF('Forklifts & Materials'!E18:E33,"Not Applicable"))+('Cranes, Hoists & Rigging'!C8-COUNTIF('Cranes, Hoists & Rigging'!E18:E31,"Not Applicable"))+('Hazardous Materials'!C8-COUNTIF('Hazardous Materials'!E18:E31,"Not Applicable"))+('Occ. Health & Noise'!C8-COUNTIF('Occ. Health & Noise'!E18:E29,"Not Applicable"))+('Medical & First Aid'!C8-COUNTIF('Medical & First Aid'!E18:E27,"Not Applicable"))+('Welding & Hot Work'!C8-COUNTIF('Welding & Hot Work'!E18:E30,"Not Applicable"))+('BBP & Sanitation'!C8-COUNTIF('BBP & Sanitation'!E18:E35,"Not Applicable"))+('State Requirements'!C8-COUNTIF('State Requirements'!E19:E118,"Not Applicable"))),"") -> 0.0014164306
H12: Very High | J12: =COUNTIF('Confined Space'!E18:E48,"Very High")+COUNTIF(PPE!E18:E51,"Very High")+COUNTIF('Walking & Working Surfaces'!E18:E48,"Very High")+COUNTIF(Recordkeeping!E18:E59,"Very High")+COUNTIF(LOTO!E18:E36,"Very High")+COUNTIF('Egress & Emergency Action'!E18:E40,"Very High")+COUNTIF('Fire Protection & Alarms'!E18:E40,"Very High")+COUNTIF('Machine Guarding'!E18:E32,"Very High")+COUNTIF('Electrical Safety'!E18:E38,"Very High")+COUNTIF('Hand & Power Tools'!E18:E36,"Very High")+COUNTIF('Hazard Communication'!E18:E32,"Very High")+COUNTIF('Forklifts & Materials'!E18:E33,"Very High")+COUNTIF('Cranes, Hoists & Rigging'!E18:E31,"Very High")+COUNTIF('Hazardous Materials'!E18:E31,"Very High")+COUNTIF('Occ. Health & Noise'!E18:E29,"Very High")+COUNTIF('Medical & First Aid'!E18:E27,"Very High")+COUNTIF('Welding & Hot Work'!E18:E30,"Very High")+COUNTIF('BBP & Sanitation'!E18:E35,"Very High")+COUNTIF('State Requirements'!E19:E118,"Very High") -> 4 | L12: =IFERROR(J12/(('Confined Space'!C8-COUNTIF('Confined Space'!E18:E48,"Not Applicable"))+(PPE!C8-COUNTIF(PPE!E18:E51,"Not Applicable"))+('Walking & Working Surfaces'!C8-COUNTIF('Walking & Working Surfaces'!E18:E48,"Not Applicable"))+(Recordkeeping!C8-COUNTIF(Recordkeeping!E18:E59,"Not Applicable"))+(LOTO!C8-COUNTIF(LOTO!E18:E36,"Not Applicable"))+('Egress & Emergency Action'!C8-COUNTIF('Egress & Emergency Action'!E18:E40,"Not Applicable"))+('Fire Protection & Alarms'!C8-COUNTIF('Fire Protection & Alarms'!E18:E40,"Not Applicable"))+('Machine Guarding'!C8-COUNTIF('Machine Guarding'!E18:E32,"Not Applicable"))+('Electrical Safety'!C8-COUNTIF('Electrical Safety'!E18:E38,"Not Applicable"))+('Hand & Power Tools'!C8-COUNTIF('Hand & Power Tools'!E18:E36,"Not Applicable"))+('Hazard Communication'!C8-COUNTIF('Hazard Communication'!E18:E32,"Not Applicable"))+('Forklifts & Materials'!C8-COUNTIF('Forklifts & Materials'!E18:E33,"Not Applicable"))+('Cranes, Hoists & Rigging'!C8-COUNTIF('Cranes, Hoists & Rigging'!E18:E31,"Not Applicable"))+('Hazardous Materials'!C8-COUNTIF('Hazardous Materials'!E18:E31,"Not Applicable"))+('Occ. Health & Noise'!C8-COUNTIF('Occ. Health & Noise'!E18:E29,"Not Applicable"))+('Medical & First Aid'!C8-COUNTIF('Medical & First Aid'!E18:E27,"Not Applicable"))+('Welding & Hot Work'!C8-COUNTIF('Welding & Hot Work'!E18:E30,"Not Applicable"))+('BBP & Sanitation'!C8-COUNTIF('BBP & Sanitation'!E18:E35,"Not Applicable"))+('State Requirements'!C8-COUNTIF('State Requirements'!E19:E118,"Not Applicable"))),"") -> 0.0018885741
A13: SECTION SCORES
A14: Conf. Space | C14: PPE | E14: Walk/Work | G14: Recordkeeping | I14: LOTO | K14: Egress | M14: Fire Prot. | O14: Mach. Guard | Q14: Electrical
A15: ='Confined Space'!D8 -> 0.61625 | C15: =PPE!D8 -> 0 | E15: ='Walking & Working Surfaces'!D8 -> 0 | G15: =Recordkeeping!D8 -> 0 | I15: =LOTO!D8 -> 0 | K15: ='Egress & Emergency Action'!D8 -> 0 | M15: ='Fire Protection & Alarms'!D8 -> 0 | O15: ='Machine Guarding'!D8 -> 0 | Q15: ='Electrical Safety'!D8 -> 0
A16: ='Confined Space'!B8&" / "&'Confined Space'!C8 -> 98.6 / 160 | C16: =PPE!B8&" / "&PPE!C8 -> 0 / 193 | E16: ='Walking & Working Surfaces'!B8&" / "&'Walking & Working Surfaces'!C8 -> 0 / 145 | G16: =Recordkeeping!B8&" / "&Recordkeeping!C8 -> 0 / 225 | I16: =LOTO!B8&" / "&LOTO!C8 -> 0 / 142 | K16: ='Egress & Emergency Action'!B8&" / "&'Egress & Emergency Action'!C8 -> 0 / 147 | M16: ='Fire Protection & Alarms'!B8&" / "&'Fire Protection & Alarms'!C8 -> 0 / 124 | O16: ='Machine Guarding'!B8&" / "&'Machine Guarding'!C8 -> 0 / 91 | Q16: ='Electrical Safety'!B8&" / "&'Electrical Safety'!C8 -> 0 / 134
A17: =IF('Confined Space'!D8="N/A","N/A",IF('Confined Space'!D8>=0.99,"Excellence Leader",IF('Confined Space'!D8>=0.9,"Gold",IF('Confined Space'!D8>=0.8,"Silver",IF('Confined Space'!D8>=0.51,"Bronze","Developing"))))) -> Bronze | C17: =IF(PPE!D8="N/A","N/A",IF(PPE!D8>=0.99,"Excellence Leader",IF(PPE!D8>=0.9,"Gold",IF(PPE!D8>=0.8,"Silver",IF(PPE!D8>=0.51,"Bronze","Developing"))))) -> Developing | E17: =IF('Walking & Working Surfaces'!D8="N/A","N/A",IF('Walking & Working Surfaces'!D8>=0.99,"Excellence Leader",IF('Walking & Working Surfaces'!D8>=0.9,"Gold",IF('Walking & Working Surfaces'!D8>=0.8,"Silver",IF('Walking & Working Surfaces'!D8>=0.51,"Bronze","Developing"))))) -> Developing | G17: =IF(Recordkeeping!D8="N/A","N/A",IF(Recordkeeping!D8>=0.99,"Excellence Leader",IF(Recordkeeping!D8>=0.9,"Gold",IF(Recordkeeping!D8>=0.8,"Silver",IF(Recordkeeping!D8>=0.51,"Bronze","Developing"))))) -> Developing | I17: =IF(LOTO!D8="N/A","N/A",IF(LOTO!D8>=0.99,"Excellence Leader",IF(LOTO!D8>=0.9,"Gold",IF(LOTO!D8>=0.8,"Silver",IF(LOTO!D8>=0.51,"Bronze","Developing"))))) -> Developing | K17: =IF('Egress & Emergency Action'!D8="N/A","N/A",IF('Egress & Emergency Action'!D8>=0.99,"Excellence Leader",IF('Egress & Emergency Action'!D8>=0.9,"Gold",IF('Egress & Emergency Action'!D8>=0.8,"Silver",IF('Egress & Emergency Action'!D8>=0.51,"Bronze","Developing"))))) -> Developing | M17: =IF('Fire Protection & Alarms'!D8="N/A","N/A",IF('Fire Protection & Alarms'!D8>=0.99,"Excellence Leader",IF('Fire Protection & Alarms'!D8>=0.9,"Gold",IF('Fire Protection & Alarms'!D8>=0.8,"Silver",IF('Fire Protection & Alarms'!D8>=0.51,"Bronze","Developing"))))) -> Developing | O17: =IF('Machine Guarding'!D8="N/A","N/A",IF('Machine Guarding'!D8>=0.99,"Excellence Leader",IF('Machine Guarding'!D8>=0.9,"Gold",IF('Machine Guarding'!D8>=0.8,"Silver",IF('Machine Guarding'!D8>=0.51,"Bronze","Developing"))))) -> Developing | Q17: =IF('Electrical Safety'!D8="N/A","N/A",IF('Electrical Safety'!D8>=0.99,"Excellence Leader",IF('Electrical Safety'!D8>=0.9,"Gold",IF('Electrical Safety'!D8>=0.8,"Silver",IF('Electrical Safety'!D8>=0.51,"Bronze","Developing"))))) -> Developing
A18: 1910.146 | C18: 1910.132-140 | E18: 1910.22-30 | G18: 1903/1904 | I18: 1910.147 | K18: 1910.36-39 | M18: 1910.157-165 | O18: 1910.212-217 | Q18: 1910.303-335
A20: Tools | C20: HazCom | E20: Forklifts | G20: Cranes | I20: Haz. Mat. | K20: Occ. Health | M20: Medical | O20: Welding | Q20: BBP/Sanit.
A21: ='Hand & Power Tools'!D8 -> 0 | C21: ='Hazard Communication'!D8 -> 0 | E21: ='Forklifts & Materials'!D8 -> 0 | G21: ='Cranes, Hoists & Rigging'!D8 -> 0 | I21: ='Hazardous Materials'!D8 -> 0 | K21: ='Occ. Health & Noise'!D8 -> 0 | M21: ='Medical & First Aid'!D8 -> 0 | O21: ='Welding & Hot Work'!D8 -> 0 | Q21: ='BBP & Sanitation'!D8 -> 0
A22: ='Hand & Power Tools'!B8&" / "&'Hand & Power Tools'!C8 -> 0 / 97 | C22: ='Hazard Communication'!B8&" / "&'Hazard Communication'!C8 -> 0 / 84 | E22: ='Forklifts & Materials'!B8&" / "&'Forklifts & Materials'!C8 -> 0 / 88 | G22: ='Cranes, Hoists & Rigging'!B8&" / "&'Cranes, Hoists & Rigging'!C8 -> 0 / 88 | I22: ='Hazardous Materials'!B8&" / "&'Hazardous Materials'!C8 -> 0 / 84 | K22: ='Occ. Health & Noise'!B8&" / "&'Occ. Health & Noise'!C8 -> 0 / 80 | M22: ='Medical & First Aid'!B8&" / "&'Medical & First Aid'!C8 -> 0 / 68 | O22: ='Welding & Hot Work'!B8&" / "&'Welding & Hot Work'!C8 -> 0 / 76 | Q22: ='BBP & Sanitation'!B8&" / "&'BBP & Sanitation'!C8 -> 0 / 96
A23: =IF('Hand & Power Tools'!D8="N/A","N/A",IF('Hand & Power Tools'!D8>=0.99,"Excellence Leader",IF('Hand & Power Tools'!D8>=0.9,"Gold",IF('Hand & Power Tools'!D8>=0.8,"Silver",IF('Hand & Power Tools'!D8>=0.51,"Bronze","Developing"))))) -> Developing | C23: =IF('Hazard Communication'!D8="N/A","N/A",IF('Hazard Communication'!D8>=0.99,"Excellence Leader",IF('Hazard Communication'!D8>=0.9,"Gold",IF('Hazard Communication'!D8>=0.8,"Silver",IF('Hazard Communication'!D8>=0.51,"Bronze","Developing"))))) -> Developing | E23: =IF('Forklifts & Materials'!D8="N/A","N/A",IF('Forklifts & Materials'!D8>=0.99,"Excellence Leader",IF('Forklifts & Materials'!D8>=0.9,"Gold",IF('Forklifts & Materials'!D8>=0.8,"Silver",IF('Forklifts & Materials'!D8>=0.51,"Bronze","Developing"))))) -> Developing | G23: =IF('Cranes, Hoists & Rigging'!D8="N/A","N/A",IF('Cranes, Hoists & Rigging'!D8>=0.99,"Excellence Leader",IF('Cranes, Hoists & Rigging'!D8>=0.9,"Gold",IF('Cranes, Hoists & Rigging'!D8>=0.8,"Silver",IF('Cranes, Hoists & Rigging'!D8>=0.51,"Bronze","Developing"))))) -> Developing | I23: =IF('Hazardous Materials'!D8="N/A","N/A",IF('Hazardous Materials'!D8>=0.99,"Excellence Leader",IF('Hazardous Materials'!D8>=0.9,"Gold",IF('Hazardous Materials'!D8>=0.8,"Silver",IF('Hazardous Materials'!D8>=0.51,"Bronze","Developing"))))) -> Developing | K23: =IF('Occ. Health & Noise'!D8="N/A","N/A",IF('Occ. Health & Noise'!D8>=0.99,"Excellence Leader",IF('Occ. Health & Noise'!D8>=0.9,"Gold",IF('Occ. Health & Noise'!D8>=0.8,"Silver",IF('Occ. Health & Noise'!D8>=0.51,"Bronze","Developing"))))) -> Developing | M23: =IF('Medical & First Aid'!D8="N/A","N/A",IF('Medical & First Aid'!D8>=0.99,"Excellence Leader",IF('Medical & First Aid'!D8>=0.9,"Gold",IF('Medical & First Aid'!D8>=0.8,"Silver",IF('Medical & First Aid'!D8>=0.51,"Bronze","Developing"))))) -> Developing | O23: =IF('Welding & Hot Work'!D8="N/A","N/A",IF('Welding & Hot Work'!D8>=0.99,"Excellence Leader",IF('Welding & Hot Work'!D8>=0.9,"Gold",IF('Welding & Hot Work'!D8>=0.8,"Silver",IF('Welding & Hot Work'!D8>=0.51,"Bronze","Developing"))))) -> Developing | Q23: =IF('BBP & Sanitation'!D8="N/A","N/A",IF('BBP & Sanitation'!D8>=0.99,"Excellence Leader",IF('BBP & Sanitation'!D8>=0.9,"Gold",IF('BBP & Sanitation'!D8>=0.8,"Silver",IF('BBP & Sanitation'!D8>=0.51,"Bronze","Developing"))))) -> Developing
A24: 1910.241-244 | C24: 1910.1200 | E24: 1910.176,178 | G24: 1910.179-184 | I24: 1910.101,106,110 | K24: 1910.94-95 | M24: 1910.151 | O24: 1910.252-255 | Q24: 1910.1030,141
A26: SCORING TIERS
A27: Excellence Leader ≥99% | D27: Gold 90–98.9% | G27: Silver 80–89.9% | J27: Bronze 51–79.9% | M27: Developing <51%
A28: STATE PLAN SUPPLEMENTAL
A29: State Plan
A30: ='State Requirements'!D8 -> N/A
A31: ='State Requirements'!B8&" / "&'State Requirements'!C8 -> 0 / 0
A32: =IF('State Requirements'!D8="N/A","N/A",IF('State Requirements'!D8>=0.99,"Excellence Leader",IF('State Requirements'!D8>=0.9,"Gold",IF('State Requirements'!D8>=0.8,"Silver",IF('State Requirements'!D8>=0.51,"Bronze","Developing"))))) -> N/A
A33: ='Pre-Audit Scoping'!D17 -> Maryland (MOSH)
A34: State-specific items only

Sheet Audit Report
A1: WLS AUDIT COACH OSHA — AUDIT FINDINGS REPORT
A2: Prepared under attorney-client privilege | Confidential — Not for disclosure without legal counsel authorization
A4: AUDIT INFORMATION
A5: Facility / Site | B5: =IF(ISBLANK('Pre-Audit Scoping'!D5),"[Complete Pre-Audit Scoping tab]",TRIM('Pre-Audit Scoping'!D5)) -> Test
A6: Audit Date(s) | B6: ='Pre-Audit Scoping'!D10 -> July 7-9 2026
A7: Lead Auditor | B7: ='Pre-Audit Scoping'!D11 -> Sara Wallon
A8: Attorney of Record | B8: ='Pre-Audit Scoping'!D14 -> Conn Maciel Carey LLP
A9: Audit Scope | B9: ='Pre-Audit Scoping'!D13 -> Full OSHA GI Compliance Audit
A11: EXECUTIVE SUMMARY
A12: OVERALL SCORE | B12: TIER RATING | C12: SECTIONS AUDITED | D12: TOTAL ITEMS | E12: ITEMS RATED | F12: HIGH / VERY HIGH | G12: SIF-POTENTIAL
A13: =IFERROR(('Confined Space'!B8+PPE!B8+'Walking & Working Surfaces'!B8+Recordkeeping!B8+LOTO!B8+'Egress & Emergency Action'!B8+'Fire Protection & Alarms'!B8+'Machine Guarding'!B8+'Electrical Safety'!B8+'Hand & Power Tools'!B8+'Hazard Communication'!B8+'Forklifts & Materials'!B8+'Cranes, Hoists & Rigging'!B8+'Hazardous Materials'!B8+'Occ. Health & Noise'!B8+'Medical & First Aid'!B8+'Welding & Hot Work'!B8+'BBP & Sanitation'!B8)/('Confined Space'!C8+PPE!C8+'Walking & Working Surfaces'!C8+Recordkeeping!C8+LOTO!C8+'Egress & Emergency Action'!C8+'Fire Protection & Alarms'!C8+'Machine Guarding'!C8+'Electrical Safety'!C8+'Hand & Power Tools'!C8+'Hazard Communication'!C8+'Forklifts & Materials'!C8+'Cranes, Hoists & Rigging'!C8+'Hazardous Materials'!C8+'Occ. Health & Noise'!C8+'Medical & First Aid'!C8+'Welding & Hot Work'!C8+'BBP & Sanitation'!C8),0) -> 0.046465598 | B13: =IF((IFERROR(('Confined Space'!B8+PPE!B8+'Walking & Working Surfaces'!B8+Recordkeeping!B8+LOTO!B8+'Egress & Emergency Action'!B8+'Fire Protection & Alarms'!B8+'Machine Guarding'!B8+'Electrical Safety'!B8+'Hand & Power Tools'!B8+'Hazard Communication'!B8+'Forklifts & Materials'!B8+'Cranes, Hoists & Rigging'!B8+'Hazardous Materials'!B8+'Occ. Health & Noise'!B8+'Medical & First Aid'!B8+'Welding & Hot Work'!B8+'BBP & Sanitation'!B8)/('Confined Space'!C8+PPE!C8+'Walking & Working Surfaces'!C8+Recordkeeping!C8+LOTO!C8+'Egress & Emergency Action'!C8+'Fire Protection & Alarms'!C8+'Machine Guarding'!C8+'Electrical Safety'!C8+'Hand & Power Tools'!C8+'Hazard Communication'!C8+'Forklifts & Materials'!C8+'Cranes, Hoists & Rigging'!C8+'Hazardous Materials'!C8+'Occ. Health & Noise'!C8+'Medical & First Aid'!C8+'Welding & Hot Work'!C8+'BBP & Sanitation'!C8),0))>=0.99,"Excellence Leader",IF((IFERROR(('Confined Space'!B8+PPE!B8+'Walking & Working Surfaces'!B8+Recordkeeping!B8+LOTO!B8+'Egress & Emergency Action'!B8+'Fire Protection & Alarms'!B8+'Machine Guarding'!B8+'Electrical Safety'!B8+'Hand & Power Tools'!B8+'Hazard Communication'!B8+'Forklifts & Materials'!B8+'Cranes, Hoists & Rigging'!B8+'Hazardous Materials'!B8+'Occ. Health & Noise'!B8+'Medical & First Aid'!B8+'Welding & Hot Work'!B8+'BBP & Sanitation'!B8)/('Confined Space'!C8+PPE!C8+'Walking & Working Surfaces'!C8+Recordkeeping!C8+LOTO!C8+'Egress & Emergency Action'!C8+'Fire Protection & Alarms'!C8+'Machine Guarding'!C8+'Electrical Safety'!C8+'Hand & Power Tools'!C8+'Hazard Communication'!C8+'Forklifts & Materials'!C8+'Cranes, Hoists & Rigging'!C8+'Hazardous Materials'!C8+'Occ. Health & Noise'!C8+'Medical & First Aid'!C8+'Welding & Hot Work'!C8+'BBP & Sanitation'!C8),0))>=0.9,"Gold",IF((IFERROR(('Confined Space'!B8+PPE!B8+'Walking & Working Surfaces'!B8+Recordkeeping!B8+LOTO!B8+'Egress & Emergency Action'!B8+'Fire Protection & Alarms'!B8+'Machine Guarding'!B8+'Electrical Safety'!B8+'Hand & Power Tools'!B8+'Hazard Communication'!B8+'Forklifts & Materials'!B8+'Cranes, Hoists & Rigging'!B8+'Hazardous Materials'!B8+'Occ. Health & Noise'!B8+'Medical & First Aid'!B8+'Welding & Hot Work'!B8+'BBP & Sanitation'!B8)/('Confined Space'!C8+PPE!C8+'Walking & Working Surfaces'!C8+Recordkeeping!C8+LOTO!C8+'Egress & Emergency Action'!C8+'Fire Protection & Alarms'!C8+'Machine Guarding'!C8+'Electrical Safety'!C8+'Hand & Power Tools'!C8+'Hazard Communication'!C8+'Forklifts & Materials'!C8+'Cranes, Hoists & Rigging'!C8+'Hazardous Materials'!C8+'Occ. Health & Noise'!C8+'Medical & First Aid'!C8+'Welding & Hot Work'!C8+'BBP & Sanitation'!C8),0))>=0.8,"Silver",IF((IFERROR(('Confined Space'!B8+PPE!B8+'Walking & Working Surfaces'!B8+Recordkeeping!B8+LOTO!B8+'Egress & Emergency Action'!B8+'Fire Protection & Alarms'!B8+'Machine Guarding'!B8+'Electrical Safety'!B8+'Hand & Power Tools'!B8+'Hazard Communication'!B8+'Forklifts & Materials'!B8+'Cranes, Hoists & Rigging'!B8+'Hazardous Materials'!B8+'Occ. Health & Noise'!B8+'Medical & First Aid'!B8+'Welding & Hot Work'!B8+'BBP & Sanitation'!B8)/('Confined Space'!C8+PPE!C8+'Walking & Working Surfaces'!C8+Recordkeeping!C8+LOTO!C8+'Egress & Emergency Action'!C8+'Fire Protection & Alarms'!C8+'Machine Guarding'!C8+'Electrical Safety'!C8+'Hand & Power Tools'!C8+'Hazard Communication'!C8+'Forklifts & Materials'!C8+'Cranes, Hoists & Rigging'!C8+'Hazardous Materials'!C8+'Occ. Health & Noise'!C8+'Medical & First Aid'!C8+'Welding & Hot Work'!C8+'BBP & Sanitation'!C8),0))>=0.51,"Bronze","Developing")))) -> Developing | C13: 18 | D13: =COUNTA(DataPool!E2:E288)-COUNTIF(DataPool!E2:E288,"Select rating") -> 24 | E13: =COUNTA(DataPool!E2:E288)-COUNTIF(DataPool!E2:E288,"Select rating")-COUNTIF(DataPool!E2:E288,"Not Applicable") -> 20 | F13: =COUNTIF(DataPool!E2:E288,"High")+COUNTIF(DataPool!E2:E288,"Very High") -> 7 | G13: =SUMPRODUCT((DataPool!E2:E288="High")+(DataPool!E2:E288="Very High")>0) -> 0
A14: =COUNTIF(DataPool!E2:E288,"Best Practice")&" Best Practice" -> 3 Best Practice | B14: =COUNTIF(DataPool!E2:E288,"Verified")&" Verified" -> 3 Verified | C14: =COUNTIF(DataPool!E2:E288,"Low")&" Low" -> 4 Low | D14: =COUNTIF(DataPool!E2:E288,"Moderate")&" Moderate" -> 3 Moderate | E14: =COUNTIF(DataPool!E2:E288,"High")&" High" -> 3 High | F14: =COUNTIF(DataPool!E2:E288,"Very High")&" Very High" -> 4 Very High | G14: =COUNTIF(DataPool!E2:E288,"Not Applicable")&" Not Applicable" -> 4 Not Applicable
A16: SECTION SCORES
A17: Section | B17: Score | C17: Max | D17: % Score | E17: Tier | F17: Findings | G17: SIF Risk
A18: Confined Space | B18: ='Confined Space'!B8 -> 98.6 | C18: ='Confined Space'!C8 -> 160 | D18: ='Confined Space'!D8 -> 0.61625 | E18: =IF('Confined Space'!D8="N/A","N/A",IF('Confined Space'!D8>=0.99,"Excellence Leader",IF('Confined Space'!D8>=0.9,"Gold",IF('Confined Space'!D8>=0.8,"Silver",IF('Confined Space'!D8>=0.51,"Bronze","Developing"))))) -> Bronze | F18: =COUNTIF('Confined Space'!E19:E48,"Low")+COUNTIF('Confined Space'!E19:E48,"Moderate")+COUNTIF('Confined Space'!E19:E48,"High")+COUNTIF('Confined Space'!E19:E48,"Very High") -> 14
A19: PPE | B19: =PPE!B8 -> 0 | C19: =PPE!C8 -> 193 | D19: =PPE!D8 -> 0 | E19: =IF(PPE!D8="N/A","N/A",IF(PPE!D8>=0.99,"Excellence Leader",IF(PPE!D8>=0.9,"Gold",IF(PPE!D8>=0.8,"Silver",IF(PPE!D8>=0.51,"Bronze","Developing"))))) -> Developing | F19: =COUNTIF(PPE!E19:E51,"Low")+COUNTIF(PPE!E19:E51,"Moderate")+COUNTIF(PPE!E19:E51,"High")+COUNTIF(PPE!E19:E51,"Very High") -> 0
A20: Walk/Work Surfaces | B20: ='Walking & Working Surfaces'!B8 -> 0 | C20: ='Walking & Working Surfaces'!C8 -> 145 | D20: ='Walking & Working Surfaces'!D8 -> 0 | E20: =IF('Walking & Working Surfaces'!D8="N/A","N/A",IF('Walking & Working Surfaces'!D8>=0.99,"Excellence Leader",IF('Walking & Working Surfaces'!D8>=0.9,"Gold",IF('Walking & Working Surfaces'!D8>=0.8,"Silver",IF('Walking & Working Surfaces'!D8>=0.51,"Bronze","Developing"))))) -> Developing | F20: =COUNTIF('Walking & Working Surfaces'!E19:E48,"Low")+COUNTIF('Walking & Working Surfaces'!E19:E48,"Moderate")+COUNTIF('Walking & Working Surfaces'!E19:E48,"High")+COUNTIF('Walking & Working Surfaces'!E19:E48,"Very High") -> 0
A21: Recordkeeping | B21: =Recordkeeping!B8 -> 0 | C21: =Recordkeeping!C8 -> 225 | D21: =Recordkeeping!D8 -> 0 | E21: =IF(Recordkeeping!D8="N/A","N/A",IF(Recordkeeping!D8>=0.99,"Excellence Leader",IF(Recordkeeping!D8>=0.9,"Gold",IF(Recordkeeping!D8>=0.8,"Silver",IF(Recordkeeping!D8>=0.51,"Bronze","Developing"))))) -> Developing | F21: =COUNTIF(Recordkeeping!E19:E59,"Low")+COUNTIF(Recordkeeping!E19:E59,"Moderate")+COUNTIF(Recordkeeping!E19:E59,"High")+COUNTIF(Recordkeeping!E19:E59,"Very High") -> 0
A22: LOTO | B22: =LOTO!B8 -> 0 | C22: =LOTO!C8 -> 142 | D22: =LOTO!D8 -> 0 | E22: =IF(LOTO!D8="N/A","N/A",IF(LOTO!D8>=0.99,"Excellence Leader",IF(LOTO!D8>=0.9,"Gold",IF(LOTO!D8>=0.8,"Silver",IF(LOTO!D8>=0.51,"Bronze","Developing"))))) -> Developing | F22: =COUNTIF(LOTO!E19:E36,"Low")+COUNTIF(LOTO!E19:E36,"Moderate")+COUNTIF(LOTO!E19:E36,"High")+COUNTIF(LOTO!E19:E36,"Very High") -> 0
A23: Egress & Emergency | B23: ='Egress & Emergency Action'!B8 -> 0 | C23: ='Egress & Emergency Action'!C8 -> 147 | D23: ='Egress & Emergency Action'!D8 -> 0 | E23: =IF('Egress & Emergency Action'!D8="N/A","N/A",IF('Egress & Emergency Action'!D8>=0.99,"Excellence Leader",IF('Egress & Emergency Action'!D8>=0.9,"Gold",IF('Egress & Emergency Action'!D8>=0.8,"Silver",IF('Egress & Emergency Action'!D8>=0.51,"Bronze","Developing"))))) -> Developing | F23: =COUNTIF('Egress & Emergency Action'!E19:E40,"Low")+COUNTIF('Egress & Emergency Action'!E19:E40,"Moderate")+COUNTIF('Egress & Emergency Action'!E19:E40,"High")+COUNTIF('Egress & Emergency Action'!E19:E40,"Very High") -> 0
A24: Fire Protection | B24: ='Fire Protection & Alarms'!B8 -> 0 | C24: ='Fire Protection & Alarms'!C8 -> 124 | D24: ='Fire Protection & Alarms'!D8 -> 0 | E24: =IF('Fire Protection & Alarms'!D8="N/A","N/A",IF('Fire Protection & Alarms'!D8>=0.99,"Excellence Leader",IF('Fire Protection & Alarms'!D8>=0.9,"Gold",IF('Fire Protection & Alarms'!D8>=0.8,"Silver",IF('Fire Protection & Alarms'!D8>=0.51,"Bronze","Developing"))))) -> Developing | F24: =COUNTIF('Fire Protection & Alarms'!E19:E40,"Low")+COUNTIF('Fire Protection & Alarms'!E19:E40,"Moderate")+COUNTIF('Fire Protection & Alarms'!E19:E40,"High")+COUNTIF('Fire Protection & Alarms'!E19:E40,"Very High") -> 0
A25: Machine Guarding | B25: ='Machine Guarding'!B8 -> 0 | C25: ='Machine Guarding'!C8 -> 91 | D25: ='Machine Guarding'!D8 -> 0 | E25: =IF('Machine Guarding'!D8="N/A","N/A",IF('Machine Guarding'!D8>=0.99,"Excellence Leader",IF('Machine Guarding'!D8>=0.9,"Gold",IF('Machine Guarding'!D8>=0.8,"Silver",IF('Machine Guarding'!D8>=0.51,"Bronze","Developing"))))) -> Developing | F25: =COUNTIF('Machine Guarding'!E19:E32,"Low")+COUNTIF('Machine Guarding'!E19:E32,"Moderate")+COUNTIF('Machine Guarding'!E19:E32,"High")+COUNTIF('Machine Guarding'!E19:E32,"Very High") -> 0
A26: Electrical Safety | B26: ='Electrical Safety'!B8 -> 0 | C26: ='Electrical Safety'!C8 -> 134 | D26: ='Electrical Safety'!D8 -> 0 | E26: =IF('Electrical Safety'!D8="N/A","N/A",IF('Electrical Safety'!D8>=0.99,"Excellence Leader",IF('Electrical Safety'!D8>=0.9,"Gold",IF('Electrical Safety'!D8>=0.8,"Silver",IF('Electrical Safety'!D8>=0.51,"Bronze","Developing"))))) -> Developing | F26: =COUNTIF('Electrical Safety'!E19:E38,"Low")+COUNTIF('Electrical Safety'!E19:E38,"Moderate")+COUNTIF('Electrical Safety'!E19:E38,"High")+COUNTIF('Electrical Safety'!E19:E38,"Very High") -> 0
A27: Hand & Power Tools | B27: ='Hand & Power Tools'!B8 -> 0 | C27: ='Hand & Power Tools'!C8 -> 97 | D27: ='Hand & Power Tools'!D8 -> 0 | E27: =IF('Hand & Power Tools'!D8="N/A","N/A",IF('Hand & Power Tools'!D8>=0.99,"Excellence Leader",IF('Hand & Power Tools'!D8>=0.9,"Gold",IF('Hand & Power Tools'!D8>=0.8,"Silver",IF('Hand & Power Tools'!D8>=0.51,"Bronze","Developing"))))) -> Developing | F27: =COUNTIF('Hand & Power Tools'!E19:E36,"Low")+COUNTIF('Hand & Power Tools'!E19:E36,"Moderate")+COUNTIF('Hand & Power Tools'!E19:E36,"High")+COUNTIF('Hand & Power Tools'!E19:E36,"Very High") -> 0
A28: Hazard Communication | B28: ='Hazard Communication'!B8 -> 0 | C28: ='Hazard Communication'!C8 -> 84 | D28: ='Hazard Communication'!D8 -> 0 | E28: =IF('Hazard Communication'!D8="N/A","N/A",IF('Hazard Communication'!D8>=0.99,"Excellence Leader",IF('Hazard Communication'!D8>=0.9,"Gold",IF('Hazard Communication'!D8>=0.8,"Silver",IF('Hazard Communication'!D8>=0.51,"Bronze","Developing"))))) -> Developing | F28: =COUNTIF('Hazard Communication'!E19:E32,"Low")+COUNTIF('Hazard Communication'!E19:E32,"Moderate")+COUNTIF('Hazard Communication'!E19:E32,"High")+COUNTIF('Hazard Communication'!E19:E32,"Very High") -> 0
A29: Forklifts | B29: ='Forklifts & Materials'!B8 -> 0 | C29: ='Forklifts & Materials'!C8 -> 88 | D29: ='Forklifts & Materials'!D8 -> 0 | E29: =IF('Forklifts & Materials'!D8="N/A","N/A",IF('Forklifts & Materials'!D8>=0.99,"Excellence Leader",IF('Forklifts & Materials'!D8>=0.9,"Gold",IF('Forklifts & Materials'!D8>=0.8,"Silver",IF('Forklifts & Materials'!D8>=0.51,"Bronze","Developing"))))) -> Developing | F29: =COUNTIF('Forklifts & Materials'!E19:E33,"Low")+COUNTIF('Forklifts & Materials'!E19:E33,"Moderate")+COUNTIF('Forklifts & Materials'!E19:E33,"High")+COUNTIF('Forklifts & Materials'!E19:E33,"Very High") -> 0
A30: Cranes & Rigging | B30: ='Cranes, Hoists & Rigging'!B8 -> 0 | C30: ='Cranes, Hoists & Rigging'!C8 -> 88 | D30: ='Cranes, Hoists & Rigging'!D8 -> 0 | E30: =IF('Cranes, Hoists & Rigging'!D8="N/A","N/A",IF('Cranes, Hoists & Rigging'!D8>=0.99,"Excellence Leader",IF('Cranes, Hoists & Rigging'!D8>=0.9,"Gold",IF('Cranes, Hoists & Rigging'!D8>=0.8,"Silver",IF('Cranes, Hoists & Rigging'!D8>=0.51,"Bronze","Developing"))))) -> Developing | F30: =COUNTIF('Cranes, Hoists & Rigging'!E19:E31,"Low")+COUNTIF('Cranes, Hoists & Rigging'!E19:E31,"Moderate")+COUNTIF('Cranes, Hoists & Rigging'!E19:E31,"High")+COUNTIF('Cranes, Hoists & Rigging'!E19:E31,"Very High") -> 0
A31: Hazardous Materials | B31: ='Hazardous Materials'!B8 -> 0 | C31: ='Hazardous Materials'!C8 -> 84 | D31: ='Hazardous Materials'!D8 -> 0 | E31: =IF('Hazardous Materials'!D8="N/A","N/A",IF('Hazardous Materials'!D8>=0.99,"Excellence Leader",IF('Hazardous Materials'!D8>=0.9,"Gold",IF('Hazardous Materials'!D8>=0.8,"Silver",IF('Hazardous Materials'!D8>=0.51,"Bronze","Developing"))))) -> Developing | F31: =COUNTIF('Hazardous Materials'!E19:E31,"Low")+COUNTIF('Hazardous Materials'!E19:E31,"Moderate")+COUNTIF('Hazardous Materials'!E19:E31,"High")+COUNTIF('Hazardous Materials'!E19:E31,"Very High") -> 0
A32: Occ. Health & Noise | B32: ='Occ. Health & Noise'!B8 -> 0 | C32: ='Occ. Health & Noise'!C8 -> 80 | D32: ='Occ. Health & Noise'!D8 -> 0 | E32: =IF('Occ. Health & Noise'!D8="N/A","N/A",IF('Occ. Health & Noise'!D8>=0.99,"Excellence Leader",IF('Occ. Health & Noise'!D8>=0.9,"Gold",IF('Occ. Health & Noise'!D8>=0.8,"Silver",IF('Occ. Health & Noise'!D8>=0.51,"Bronze","Developing"))))) -> Developing | F32: =COUNTIF('Occ. Health & Noise'!E19:E29,"Low")+COUNTIF('Occ. Health & Noise'!E19:E29,"Moderate")+COUNTIF('Occ. Health & Noise'!E19:E29,"High")+COUNTIF('Occ. Health & Noise'!E19:E29,"Very High") -> 0
A33: Medical & First Aid | B33: ='Medical & First Aid'!B8 -> 0 | C33: ='Medical & First Aid'!C8 -> 68 | D33: ='Medical & First Aid'!D8 -> 0 | E33: =IF('Medical & First Aid'!D8="N/A","N/A",IF('Medical & First Aid'!D8>=0.99,"Excellence Leader",IF('Medical & First Aid'!D8>=0.9,"Gold",IF('Medical & First Aid'!D8>=0.8,"Silver",IF('Medical & First Aid'!D8>=0.51,"Bronze","Developing"))))) -> Developing | F33: =COUNTIF('Medical & First Aid'!E19:E27,"Low")+COUNTIF('Medical & First Aid'!E19:E27,"Moderate")+COUNTIF('Medical & First Aid'!E19:E27,"High")+COUNTIF('Medical & First Aid'!E19:E27,"Very High") -> 0
A34: Welding & Hot Work | B34: ='Welding & Hot Work'!B8 -> 0 | C34: ='Welding & Hot Work'!C8 -> 76 | D34: ='Welding & Hot Work'!D8 -> 0 | E34: =IF('Welding & Hot Work'!D8="N/A","N/A",IF('Welding & Hot Work'!D8>=0.99,"Excellence Leader",IF('Welding & Hot Work'!D8>=0.9,"Gold",IF('Welding & Hot Work'!D8>=0.8,"Silver",IF('Welding & Hot Work'!D8>=0.51,"Bronze","Developing"))))) -> Developing | F34: =COUNTIF('Welding & Hot Work'!E19:E30,"Low")+COUNTIF('Welding & Hot Work'!E19:E30,"Moderate")+COUNTIF('Welding & Hot Work'!E19:E30,"High")+COUNTIF('Welding & Hot Work'!E19:E30,"Very High") -> 0
A35: BBP & Sanitation | B35: ='BBP & Sanitation'!B8 -> 0 | C35: ='BBP & Sanitation'!C8 -> 96 | D35: ='BBP & Sanitation'!D8 -> 0 | E35: =IF('BBP & Sanitation'!D8="N/A","N/A",IF('BBP & Sanitation'!D8>=0.99,"Excellence Leader",IF('BBP & Sanitation'!D8>=0.9,"Gold",IF('BBP & Sanitation'!D8>=0.8,"Silver",IF('BBP & Sanitation'!D8>=0.51,"Bronze","Developing"))))) -> Developing | F35: =COUNTIF('BBP & Sanitation'!E19:E35,"Low")+COUNTIF('BBP & Sanitation'!E19:E35,"Moderate")+COUNTIF('BBP & Sanitation'!E19:E35,"High")+COUNTIF('BBP & Sanitation'!E19:E35,"Very High") -> 0
A37: DETAILED FINDINGS — All items rated Low or above, sorted by severity
A38: ⚠ Items marked with SIF = Serious Injury or Fatality potential. These should be prioritized for immediate corrective action regardless of overall score.
A39: Section | B39: Item # | C39: SIF | D39: Requirement (Summary) | E39: Observations | F39: Recommendations | G39: Citation
A40: No reportable findings — all items Verified or Not Applicable

Sheet CA Tracker
A1: WLS AUDIT COACH OSHA — CORRECTIVE ACTION TRACKER
A2: Auto-populated from audit findings | Prepared under attorney-client privilege | Findings sorted: Very High → Low
A3: ⚑ Columns A–G are auto-populated from audit results and will update as findings are entered. Enter tracking data in columns H–L. Use Item # (col B) as the key if re-alignment is needed between audits.
A5: Section / Tab | B5: Item # | C5: Finding Rating | D5: Requirement | E5: Observations | F5: Recommendations | G5: Citation | H5: Auditor Notes | I5: Assigned To | J5: Due Date | K5: Status | L5: Verified By | M5: Close Date
A6: No findings requiring corrective action

Sheet Confined Space
A1: CONFINED SPACE (PRCS) COMPLIANCE AUDIT | M1: Rating | N1: Pct
A2: 29 CFR 1910.146 — Permit-Required Confined Spaces. Prepared under attorney-client privilege. | M2: Best Practice | N2: 100
M3: Verified | N3: 100
A4: SITE: | B4: ='Pre-Audit Scoping'!D5 -> Test | D4: DATE(S): | E4: ='Pre-Audit Scoping'!D10 -> July 7-9 2026 | G4: AUDITOR(S): | H4: =TRIM('Pre-Audit Scoping'!D11)&IF(TRIM('Pre-Audit Scoping'!D12)<>"",", "&TRIM('Pre-Audit Scoping'!D12),"") -> Sara Wallon, Gabriel Wallon | M4: Low | N4: 85
M5: Moderate | N5: 70
A6: SCORING SUMMARY | M6: High | N6: 30
A7: Category | B7: Score | C7: Max | D7: Percentage % | F7: Finding Rating | G7: Count | M7: Very High | N7: 0
A8: TOTAL | B8: =SUM(F18:F48) -> 98.6 | C8: =SUM(O18:O48) -> 160 | D8: =IF(C8<>0,B8/C8,"N/A") -> 0.61625 | F8: Best Practice | G8: =COUNTIF(E18:E48,"Best Practice") -> 3 | M8: Not Applicable | N8: 0
F9: Verified | G9: =COUNTIF(E18:E48,"Verified") -> 3
F10: Low | G10: =COUNTIF(E18:E48,"Low") -> 4
F11: Moderate | G11: =COUNTIF(E18:E48,"Moderate") -> 3
F12: High | G12: =COUNTIF(E18:E48,"High") -> 3
F13: Very High | G13: =COUNTIF(E18:E48,"Very High") -> 4
F14: Not Applicable | G14: =COUNTIF(E18:E48,"Not Applicable") -> 4
A15: OVERALL SCORE | D15: =D8 -> 0.61625 | F15: Rating Tier: | G15: =IF(D8="N/A","N/A",IF(D8>=0.99,"Excellence Leader",IF(D8>=0.9,"Gold",IF(D8>=0.8,"Silver",IF(D8>=0.51,"Bronze","Developing"))))) -> Bronze
A17: Item # | B17: Subsection | C17: Requirement | D17: Evidence to Look For | E17: Finding Rating | F17: Score | G17: Max | H17: Observations | I17: Recommendations | J17: Citation | K17: Auditor Notes | O17: Eff. Max
A18: GENERAL REQUIREMENTS
A19: CS-1 | B19: General Requirements | C19: The employer must evaluate the workplace to determine if any spaces qualify as permit-required confined spaces (PRCS). A permit-required confined space is a space that: (1) is large enough and configured so an employee can bodily enter and perform assigned work; (2) has limited or restricted means for entry or exit; AND (3) is not designed for continuous employee occupancy; AND meets one or more of: contains or has the potential to contain a serious atmospheric hazard; contains a material with potential for engulfment; has an internal configuration that could trap or asphyxiate an entrant; contains any other recognized serious safety or health hazard. | D19: Request the written confined space inventory/survey document. Walk 10% of the facility (minimum 3 representative areas — processing areas, utility rooms, below-grade areas, material handling areas) and confirm the inventory captures all spaces meeting the PRCS definition. Look for commonly missed spaces: dust collector hoppers, conveyor pits, below-grade sumps, enclosed ductwork, storage bins, silos, and large tanks. Confirm the inventory is signed, dated, and updated when the facility layout changes. | E19: Not Applicable | F19: =IFERROR(ROUND(G19*VLOOKUP(E19,$M$2:$N$8,2,FALSE())/100,1),0) -> 0 | G19: 10 | H19: Test | I19: Test Method 123 | J19: 29 CFR 1910.146(c)(1),(c)(6) | O19: =IF(E19="Not Applicable",0,G19) -> 0
A20: CS-2 | B20: General Requirements | C20: Each identified permit-required confined space must be identified by posting a warning sign at or near the entry point. Signs must include wording such as: 'DANGER — PERMIT-REQUIRED CONFINED SPACE — AUTHORIZED ENTRANTS ONLY' (or equivalent language that conveys the hazard). If signage is not practical, another equally effective means of informing employees must be used. | D20: Walk to 100% of identified PRCS locations and confirm warning signs are posted at or near each entry point. Signs must be visible before an employee could inadvertently enter the space. Document any identified PRCS that lacks a sign or where the sign is obscured, illegible, or outdated. | E20: Low | F20: =IFERROR(ROUND(G20*VLOOKUP(E20,$M$2:$N$8,2,FALSE())/100,1),0) -> 6.8 | G20: 8 | H20: Testing is cool | I20: testing is the best | J20: 29 CFR 1910.146(c)(2) | O20: =IF(E20="Not Applicable",0,G20) -> 8
A21: CS-3 | B21: General Requirements | C21: If the employer decides employees will not enter any confined space, the employer must take effective measures to prevent employee entry — not just post a sign. Effective measures include: welding or bolting covers shut, installing padlocked barriers, or other physical means that prevent unauthorized access. | D21: Confirm whether any spaces on the inventory are designated no-entry. If yes, physically inspect 100% of no-entry spaces and confirm physical prevention measures are in place (not just a sign or verbal instruction). Verify employees and contractors know the no-entry designation and understand they may not enter under any circumstances without a program revision. | E21: Very High | F21: =IFERROR(ROUND(G21*VLOOKUP(E21,$M$2:$N$8,2,FALSE())/100,1),0) -> 0 | G21: 6 | H21: trial and tribulation | I21: test | J21: 29 CFR 1910.146(c)(3) | O21: =IF(E21="Not Applicable",0,G21) -> 6
A22: CONTRACTORS
A23: CS-4 | B23: Contractors | C23: When contractors perform work at this facility, the host employer must: (1) Inform the contractor that the workplace contains permit-required confined spaces. (2) Inform the contractor of the spaces' locations and the hazards present. (3) Inform the contractor of the employer's experience with the spaces. (4) Inform the contractor of any precautions or procedures implemented for protection. (5) Coordinate entry operations if both employer and contractor will be working in or near a PRCS simultaneously. (6) Debrief the contractor after entry operations to identify any hazards discovered. | D23: Request documentation of contractor coordination for 10% of contractor jobs involving PRCS work at this facility in the past year (minimum 1 job). Confirm: the host shared the space inventory and known hazards before work began; there is a record of the pre-entry information exchange (sign-in sheet, pre-job meeting notes, or contractor safety form); and if both host and contractor worked in or near the same space simultaneously, a coordination protocol is documented. | E23: Not Applicable | F23: =IFERROR(ROUND(G23*VLOOKUP(E23,$M$2:$N$8,2,FALSE())/100,1),0) -> 0 | G23: 8 | J23: 29 CFR 1910.146(c)(8),(c)(9) | O23: =IF(E23="Not Applicable",0,G23) -> 0
A24: PERMIT-REQUIRED CONFINED SPACE PROGRAM
A25: CS-5 | B25: Permit-Required Confined Space Program | C25: An employer whose employees enter permit spaces must develop and implement a written PRCS entry program. The program must be made available for inspection by employees and their authorized representatives. | D25: Request the written PRCS program. Confirm: (1) it is site-specific, not a generic template; (2) it references the specific spaces at this facility; (3) it includes a current revision date; (4) it is physically accessible to employees and authorized employee representatives — not solely in a manager's office or a locked file. A printed copy posted near the entry or maintained in the work area meets this requirement. | E25: Low | F25: =IFERROR(ROUND(G25*VLOOKUP(E25,$M$2:$N$8,2,FALSE())/100,1),0) -> 8.5 | G25: 10 | J25: 29 CFR 1910.146(c)(4),(d)(1)-(d)(2),(l) | O25: =IF(E25="Not Applicable",0,G25) -> 10
A26: CS-6 | B26: Permit-Required Confined Space Program | C26: The written PRCS program must include ALL 14 required elements per 29 CFR 1910.146(d)(3)-(d)(14). Missing any element is a citable deficiency. See the Evidence column checklist. | D26: CHECKLIST — review the written PRCS program against each element. Mark each: Verified (complete), Partial (exists but incomplete), or Absent (not addressed at all). □ (1) Measures to prevent unauthorized entry □ (2) Identification and evaluation of hazards before entry □ (3) Safe entry procedures: acceptable entry conditions; isolation from energy/material sources; condition verification throughout entry; purging/inerting/flushing/ventilation to control atmospheric hazards; pedestrian/vehicle barriers □ (4) Equipment at no cost: testing instruments, ventilation, communications, PPE, lighting, ingress/egress, rescue gear □ (5) Atmospheric testing and monitoring before and during entry □ (6) At least one dedicated attendant stationed outside for the full duration of every authorized entry □ (7) Multi-space attendant protocol if one attendant monitors simultaneous entries □ (8) Designated roles with responsibilities: authorized entrants, attendants, entry supervisors, rescuers □ (9) Rescue and emergency services — on-site trained team or identified external service □ (10) Permit system: preparation, issuance, use, and cancellation □ (11) Multi-employer coordination when >1 employer works in or near the space simultaneously □ (12) Entry conclusion and permit cancellation procedures □ (13) Pre-entry hazard re-evaluation when conditions may have changed □ (14) Annual program review using canceled permits as input Elements (6), (9), and (14) are most frequently missing — verify these first. | E26: High | F26: =IFERROR(ROUND(G26*VLOOKUP(E26,$M$2:$N$8,2,FALSE())/100,1),0) -> 3 | G26: 10 | J26: 29 CFR 1910.146(d)(3),(d)(6)-(d)(14) | O26: =IF(E26="Not Applicable",0,G26) -> 10
A27: CS-7 | B27: Permit-Required Confined Space Program | C27: The employer must provide and maintain all equipment necessary for safe PRCS entry at no cost to the employee. Required equipment includes: (1) Testing and monitoring equipment for atmospheric hazards (calibrated multi-gas meter for O2, LEL, CO, and H2S at minimum); (2) Ventilating equipment sufficient to obtain acceptable entry conditions; (3) Communications equipment; (4) Personal protective equipment; (5) Lighting equipment to enable employees to see well enough to work safely and exit quickly in an emergency; (6) Barriers and shields; (7) Equipment for safe ingress and egress; (8) Rescue and emergency equipment. | D27: Physically inspect the confined space entry equipment station. Verify: (1) Multi-gas meter is present, powered on, and the calibration date on the tag or in the log is current (most meters require bump testing before each use and full calibration per manufacturer schedule — typically every 6 months); (2) Ventilation blower is present and functional; (3) Communications device (radio or phone) is present and working; (4) Rescue retrieval equipment (tripod, winch, or davit) is present and in serviceable condition; (5) Full-body harness and retrieval lifeline are present; (6) Lighting is available. Sample 10% of confined space entry equipment kits at this facility (minimum 1 full kit inspection). | E27: Moderate | F27: =IFERROR(ROUND(G27*VLOOKUP(E27,$M$2:$N$8,2,FALSE())/100,1),0) -> 7 | G27: 10 | J27: 29 CFR 1910.146(d)(4) | O27: =IF(E27="Not Applicable",0,G27) -> 10
A28: CS-8 | B28: Permit-Required Confined Space Program | C28: Atmospheric monitoring must be conducted: (1) Before entry authorization is granted — to test for the presence of atmospheric hazards. (2) As needed during entry — to ensure acceptable entry conditions are maintained for the duration of the entry. Testing must be conducted by or under the direction of a qualified person using properly calibrated instruments. The atmosphere must be tested for: oxygen content (acceptable range: 19.5% to 23.5%); flammable gases and vapors (must be less than 10% of LFL); potential toxic air contaminants (below applicable PEL). | D28: Pull 10% of canceled entry permits from the past 12 months (minimum 5 permits). For each permit: confirm pre-entry atmospheric test results are recorded with the actual readings (not just a checkmark), the name of the person who performed the test, and the instrument used. Confirm readings were within acceptable ranges before entry was authorized. Confirm that any permit where continuous monitoring was required shows monitoring notes during the entry. Any permit with blank atmospheric test fields is a deficiency. | E28: Very High | F28: =IFERROR(ROUND(G28*VLOOKUP(E28,$M$2:$N$8,2,FALSE())/100,1),0) -> 0 | G28: 10 | J28: 29 CFR 1910.146(d)(5) | O28: =IF(E28="Not Applicable",0,G28) -> 10
A29: CS-9 | B29: Permit-Required Confined Space Program | C29: An employer may use an alternate procedure (continuous forced-air ventilation without a full permit) ONLY when ALL of the following conditions are met: (1) The only hazard in the space is an actual or potential hazardous atmosphere; (2) The hazardous atmosphere can be controlled by continuous forced-air ventilation alone; (3) The employer can demonstrate that entry can be made safely; (4) The written program describes the means, procedures, and practices used; (5) The atmosphere is tested before any employee enters to confirm the ventilation has worked; (6) Atmospheric testing continues as necessary. | D29: For any spaces designated as alternate-entry (non-permit entry with ventilation), confirm the written program documents specifically that: (1) the space has been evaluated and the ONLY hazard is atmospheric; (2) ventilation controls the hazard; (3) pre-entry and continuous atmospheric monitoring is performed. Walk 10% of alternate-entry spaces (minimum 1) and confirm ventilation equipment is in place and functional. Any space with an engulfment hazard, converging walls, or uncontrolled energy cannot qualify for alternate entry. | E29: Best Practice | F29: =IFERROR(ROUND(G29*VLOOKUP(E29,$M$2:$N$8,2,FALSE())/100,1),0) -> 6 | G29: 6 | J29: 29 CFR 1910.146(c)(5) | O29: =IF(E29="Not Applicable",0,G29) -> 6
A30: CS-10 | B30: Permit-Required Confined Space Program | C30: When an alternate entry procedure is used, the employer must: (1) Test the atmosphere within the space before any employee enters to demonstrate the ventilation has worked. (2) Continue atmospheric testing as often as necessary to ensure acceptable conditions exist throughout the entry. (3) If a hazardous atmosphere is detected during entry, have each employee leave the space immediately and investigate, evaluate, and remedy the hazardous atmosphere before re-entering. | D30: Review 10% of alternate-entry records (minimum 2). Confirm: pre-entry atmospheric readings are recorded with the actual values; continuous monitoring requirements are documented; and there is a documented procedure (or training record showing employees know) to evacuate immediately if conditions change. | E30: Verified | F30: =IFERROR(ROUND(G30*VLOOKUP(E30,$M$2:$N$8,2,FALSE())/100,1),0) -> 6 | G30: 6 | J30: 29 CFR 1910.146(c)(5)(ii) | O30: =IF(E30="Not Applicable",0,G30) -> 6
A31: CS-11 | B31: Permit-Required Confined Space Program | C31: A permit-required confined space may be reclassified as a non-permit-required confined space ONLY when: (1) the space contains no actual or potential serious safety or health hazards; AND (2) the employer documents that the hazardous characteristics have been permanently eliminated (not just controlled). The documentation must be certified and made available to employees. | D31: If any spaces have been reclassified from PRCS to non-permit status, request the written reclassification documentation for 100% of reclassified spaces. Confirm: the certification specifically states how hazards were eliminated (not merely controlled); it is signed by a qualified person; and it identifies the space by location. Re-entry into a reclassified space that later shows a hazardous atmosphere requires the space to be immediately evacuated and re-evaluated. | E31: Low | F31: =IFERROR(ROUND(G31*VLOOKUP(E31,$M$2:$N$8,2,FALSE())/100,1),0) -> 5.1 | G31: 6 | J31: 29 CFR 1910.146(c)(7) | O31: =IF(E31="Not Applicable",0,G31) -> 6
A32: ENTRY PERMITS
A33: CS-12 | B33: Entry Permits | C33: Before entry is authorized, the employer must prepare and issue an entry permit containing ALL 15 required components per 29 CFR 1910.146(f). A permit missing any required component is deficient. See Evidence column checklist. | D33: CHECKLIST — for each permit sampled (10% of canceled permits, minimum 5), verify every component is present and completed (not blank). □ (1) The permit space to be entered (identified by location) □ (2) Purpose of the entry □ (3) Date and authorized duration of the entry permit □ (4) Authorized entrants — by name or a means (roster/badge system) to identify all entrants quickly □ (5) Current attendant(s) — by name □ (6) Entry supervisor — identified with signature or initials BEFORE entry □ (7) Hazards of the permit space □ (8) Measures to isolate the space and eliminate or control hazards □ (9) Acceptable entry conditions (specific ranges: O2 19.5-23.5%, LEL <10%, CO <35 ppm, etc.) □ (10) Results of initial and periodic atmospheric tests — actual readings, tester name, instrument used □ (11) Rescue and emergency services — specific contact information (phone number, not just 'call 911') □ (12) Communication procedures between entrants and attendant □ (13) Required equipment: PPE, testing equipment, communications, alarm, rescue equipment, lighting □ (14) Any other information necessary to ensure employee safety □ (15) Any additional permits (e.g., hot work permit) for work in the space Document the % of sampled permits with all 15 components complete. | E33: Moderate | F33: =IFERROR(ROUND(G33*VLOOKUP(E33,$M$2:$N$8,2,FALSE())/100,1),0) -> 7 | G33: 10 | J33: 29 CFR 1910.146(f) | O33: =IF(E33="Not Applicable",0,G33) -> 10
A34: CS-13 | B34: Entry Permits | C34: The permit must be properly used before and during entry: (1) Signed by the entry supervisor who verifies that all required entries on the permit have been made; (2) Made available to authorized entrants through posting at the permit space entrance or another equally effective means; (3) Actively used by the attendant to track authorized entrants; (4) Retained after operations are completed and the permit is canceled. | D34: For 10% of the most recent entries (minimum 3), confirm: the permit bears the entry supervisor's initials or signature from before entry began; permits were posted at the entry point (ask whether this is standard practice or review a photo/checklist confirming it); the attendant's duty to maintain a count of entrants is reflected on or with the permit. Ask the entry supervisor to walk through how they authorize an entry — not after-the-fact signature. | E34: High | F34: =IFERROR(ROUND(G34*VLOOKUP(E34,$M$2:$N$8,2,FALSE())/100,1),0) -> 2.4 | G34: 8 | J34: 29 CFR 1910.146(e)(1)-(e)(4) | O34: =IF(E34="Not Applicable",0,G34) -> 8
A35: CS-14 | B35: Entry Permits | C35: Entry must be terminated and the permit canceled under two conditions: (1) When the work covered by the permit has been completed; OR (2) When a prohibited condition arises — any condition not allowed by the permit, including an atmospheric reading outside acceptable parameters, an equipment failure, or an unexpected hazard. All authorized entrants must immediately evacuate when entry is terminated due to a prohibited condition. | D35: Confirm 100% of retained permits are marked as canceled/completed. Ask the entry supervisor: 'If you discovered during entry that the O2 level dropped to 18% — what would you do?' The correct answer is immediate evacuation, termination of the permit, and re-evaluation before re-entry. Confirm this is reflected in the written program. | E35: Very High | F35: =IFERROR(ROUND(G35*VLOOKUP(E35,$M$2:$N$8,2,FALSE())/100,1),0) -> 0 | G35: 6 | J35: 29 CFR 1910.146(e)(5) | O35: =IF(E35="Not Applicable",0,G35) -> 6
A36: CS-15 | B36: Entry Permits | C36: Canceled entry permits must be retained for at least 1 year following each entry. Within 1 year of each entry, the employer must review the canceled permits for that entry and use them to revise the permit program as needed to ensure that employees are protected from permit space hazards. | D36: Confirm canceled permits are filed and accessible for the past 12 months (100% of the prior year's permits should be on file). Ask when the most recent annual program review was completed and request the documentation. Confirm the review references specific findings from prior permits. | E36: Not Applicable | F36: =IFERROR(ROUND(G36*VLOOKUP(E36,$M$2:$N$8,2,FALSE())/100,1),0) -> 0 | G36: 6 | J36: 29 CFR 1910.146(e)(6) | O36: =IF(E36="Not Applicable",0,G36) -> 0
A37: TRAINING AND ROLE DUTIES
A38: CS-16 | B38: Training and Role Duties | C38: Training must be provided to each employee whose work is regulated by the PRCS standard. Training must be provided: (1) Before the employee is first assigned duties under the standard; (2) Before there is a change in assigned duties; (3) Whenever there is a change in permit space operations that presents a hazard that employees have not been trained for; (4) Whenever the employer has reason to believe employees do not have the required understanding, knowledge, or skills. Training must establish employee proficiency in duties assigned and must be specific to the role (authorized entrant, attendant, entry supervisor, rescue). | D38: Request training records for 100% of currently designated authorized entrants, attendants, and entry supervisors. Confirm: initial training was completed before first assignment; training is role-specific (separate content for entrants vs. attendants vs. supervisors); and the training record documents the specific spaces and hazards covered. Note whether training is refreshed when new spaces are added or hazard profiles change. | E38: Best Practice | F38: =IFERROR(ROUND(G38*VLOOKUP(E38,$M$2:$N$8,2,FALSE())/100,1),0) -> 10 | G38: 10 | J38: 29 CFR 1910.146(g) | O38: =IF(E38="Not Applicable",0,G38) -> 10
A39: CS-17 | B39: Training and Role Duties | C39: Authorized entrants must be able to: (1) Know the hazards that may be faced during entry, including information on the mode, signs or symptoms, and consequences of the exposure; (2) Properly use equipment; (3) Communicate with the attendant as necessary; (4) Alert the attendant whenever the entrant recognizes any warning sign or symptom of exposure or a prohibited condition; (5) Exit from the permit space as quickly as possible whenever ordered by the attendant or entry supervisor, an evacuation alarm is activated, or they recognize a warning sign, symptom, or prohibited condition. | D39: Interview 10% of authorized entrants (minimum 3). Ask each entrant: 'What hazards are you exposed to in the confined spaces you enter at this facility?' 'What atmospheric conditions would cause you to leave immediately?' 'What are three ways you communicate with the attendant?' 'If the attendant said leave — what do you do?' Grade responses against the five required knowledge areas above. | E39: Verified | F39: =IFERROR(ROUND(G39*VLOOKUP(E39,$M$2:$N$8,2,FALSE())/100,1),0) -> 8 | G39: 8 | J39: 29 CFR 1910.146(h) | O39: =IF(E39="Not Applicable",0,G39) -> 8
A40: CS-18 | B40: Training and Role Duties | C40: Attendants must be able to: (1) Know the hazards that may be faced during entry; (2) Know the behavioral effects of hazard exposure; (3) Continuously maintain an accurate count of authorized entrants in the permit space; (4) Remain outside the permit space during entry operations and NOT enter the space under any circumstances unless a relieving attendant has taken over; (5) Communicate with entrants as necessary; (6) Monitor activities inside and outside the space to determine whether it is safe for entrants to remain; (7) Order evacuation when a prohibited condition occurs, an entrant shows behavioral effects, an emergency arises, or the attendant cannot perform duties; (8) Summon rescue services without entering the space; (9) Prevent unauthorized entry; (10) Perform non-entry rescues per the rescue procedure. | D40: Interview 10% of designated attendants (minimum 3). Ask: 'Can you ever enter the space yourself?' (Answer: NO, unless formally relieved by another attendant) 'What do you do if you lose communication with an entrant?' 'How do you summon rescue?' 'Can you leave your post to help someone?' (Answer: NO — they must call for relief). Pay particular attention to whether attendants understand the prohibition on entry and the distinction between their role and an authorized entrant's role. | E40: Low | F40: =IFERROR(ROUND(G40*VLOOKUP(E40,$M$2:$N$8,2,FALSE())/100,1),0) -> 6.8 | G40: 8 | J40: 29 CFR 1910.146(i) | O40: =IF(E40="Not Applicable",0,G40) -> 8
A41: CS-19 | B41: Training and Role Duties | C41: Entry supervisors must be able to: (1) Know the hazards that may be faced; (2) Verify by checking all entries on the permit that all tests, procedures, and equipment are in place before endorsing and authorizing entry; (3) Terminate entry and cancel the permit when required; (4) Verify that rescue services are available; (5) Remove unauthorized individuals; (6) Determine whenever responsibility for a permit space entry operation is transferred to a new supervisor, and when conditions change, whether it is still safe to enter. | D41: Interview 10% of entry supervisors (minimum 2). Ask: 'Walk me through what you check before you authorize an entry.' Confirm they verify atmospheric readings, equipment availability, team assignments, and rescue contacts — not just sign the permit. Ask: 'If an entrant called you from inside the space and said they smelled something unusual — what is your immediate action?' (Expected: order immediate evacuation, terminate the permit, investigate). | E41: Moderate | F41: =IFERROR(ROUND(G41*VLOOKUP(E41,$M$2:$N$8,2,FALSE())/100,1),0) -> 5.6 | G41: 8 | J41: 29 CFR 1910.146(j) | O41: =IF(E41="Not Applicable",0,G41) -> 8
A42: RESCUE OPERATIONS AND EQUIPMENT
A43: CS-20 | B43: Rescue Operations and Equipment | C43: The employer must select a rescue service capable of responding to a rescue summons in a timely manner, considering the hazards identified and the type of permit space operations at this facility. If an off-site emergency responder (fire department) is used, the employer must: (1) Inform the responder of the hazards; (2) Provide the responder with access to the facility for pre-entry rescue planning; (3) Evaluate the service's ability to respond effectively. | D43: Ask whether rescue services are internal (on-site trained team) or external (fire department or contract rescue). For external rescue: request documentation that the service was informed of the specific hazards present (copies of SDSs, hazard descriptions, space configurations shared with the responder); confirm the service has visited the facility for pre-planning (emergency plan pre-entry briefing, drill, or site walk); and confirm the estimated response time is acceptable for the hazard level in each PRCS. | E43: High | F43: =IFERROR(ROUND(G43*VLOOKUP(E43,$M$2:$N$8,2,FALSE())/100,1),0) -> 2.4 | G43: 8 | J43: 29 CFR 1910.146(k)(1) | O43: =IF(E43="Not Applicable",0,G43) -> 8
A44: CS-21 | B44: Rescue Operations and Equipment | C44: If the employer uses on-site employees for rescue, those rescue employees must: (1) Be provided with and trained in the use of PPE and rescue equipment required for the space, at no cost to the employee; (2) Be trained to perform assigned rescue duties, including first aid and CPR; (3) Practice making permit space rescues at least once every 12 months, using a representative permit space (actual space or mockup with similar hazards and entry/exit conditions). | D44: If an internal rescue team is used: request the training records for 100% of designated rescue team members. Confirm: PPE and rescue equipment training is documented; current CPR and first aid certification is on file for each member; and an annual rescue practice drill using an actual or representative space was conducted within the past 12 months — with documentation of the drill (date, participants, space used, lessons learned). | E44: Very High | F44: =IFERROR(ROUND(G44*VLOOKUP(E44,$M$2:$N$8,2,FALSE())/100,1),0) -> 0 | G44: 8 | J44: 29 CFR 1910.146(k)(2) | O44: =IF(E44="Not Applicable",0,G44) -> 8
A45: CS-22 | B45: Rescue Operations and Equipment | C45: Retrieval equipment must be used whenever an authorized entrant enters a permit space, unless the retrieval equipment would increase the overall risk of entry or would not contribute to the rescue. Retrieval systems must include: (1) Each authorized entrant uses a chest or full body harness with a retrieval line attached to the center ring or wrist straps; (2) The other end of the retrieval line is attached to a mechanical device or fixed point outside the space; (3) A mechanical device capable of retrieving the entrant from vertical entry spaces more than 5 feet deep. | D45: Physically inspect the retrieval system used for permit space entries at this facility. Confirm: full-body harnesses are present and sized for the workforce; retrieval lines are connected to a mechanical retrieval device (tripod and winch) positioned outside the space; the attendant can operate the system from their station without entering the space; the device is rated for the load. If retrieval equipment is not used for certain spaces, confirm written documentation justifying the exception (e.g., the configuration of the space makes retrieval equipment more hazardous than beneficial). | E45: Not Applicable | F45: =IFERROR(ROUND(G45*VLOOKUP(E45,$M$2:$N$8,2,FALSE())/100,1),0) -> 0 | G45: 8 | J45: 29 CFR 1910.146(k)(3) | O45: =IF(E45="Not Applicable",0,G45) -> 0
A46: CS-23 | B46: Rescue Operations and Equipment | C46: Pertinent safety data sheets (SDSs) or other written information regarding the hazards of chemicals in the permit space must be made available to the medical facility treating exposed entrants at the time of emergency response. | D46: Confirm that a packet of SDSs or a chemical hazard summary is kept with or near the entry equipment kit so it can be sent with any injured entrant to the hospital. Ask the entry supervisor: 'If an entrant needed to be transported to the ER after a chemical exposure in one of your permit spaces — how would the hospital know what they were exposed to?' The process should not require someone to search for SDSs after an emergency has begun. | E46: Best Practice | F46: =IFERROR(ROUND(G46*VLOOKUP(E46,$M$2:$N$8,2,FALSE())/100,1),0) -> 6 | G46: 6 | J46: 29 CFR 1910.146(k)(4) | O46: =IF(E46="Not Applicable",0,G46) -> 6
A47: PROGRAM REVIEW
A48: CS-24 | B48: Program Review | C48: The PRCS program must be reviewed within 1 year after each entry and whenever the employer has reason to believe the measures in the program may not protect employees adequately. The review must use canceled entry permits as input. If deficiencies are identified, the program must be revised before employees next enter the permit space. | D48: Request the most recent annual PRCS program review document. Confirm: it was completed within 12 months of the most recent entries; it references specific findings from the canceled permits reviewed (e.g., atmospheric readings that were close to limits, equipment issues, permit completion rate); and any identified deficiencies resulted in documented program revisions. If no annual review documentation exists, this is a significant finding. | E48: Verified | F48: =IFERROR(ROUND(G48*VLOOKUP(E48,$M$2:$N$8,2,FALSE())/100,1),0) -> 8 | G48: 8 | J48: 29 CFR 1910.146(d)(13)-(d)(14) | O48: =IF(E48="Not Applicable",0,G48) -> 8

Sheet PPE
A1: PERSONAL PROTECTIVE EQUIPMENT (PPE) COMPLIANCE AUDIT | M1: Rating | N1: Pct
A2: 29 CFR 1910.132–140 — Personal Protective Equipment. Prepared under attorney-client privilege. | M2: Best Practice | N2: 100
M3: Verified | N3: 100
A4: SITE: | B4: ='Pre-Audit Scoping'!D5 -> Test | D4: DATE(S): | E4: ='Pre-Audit Scoping'!D10 -> July 7-9 2026 | G4: AUDITOR(S): | H4: =TRIM('Pre-Audit Scoping'!D11)&IF(TRIM('Pre-Audit Scoping'!D12)<>"",", "&TRIM('Pre-Audit Scoping'!D12),"") -> Sara Wallon, Gabriel Wallon | M4: Low | N4: 85
M5: Moderate | N5: 70
A6: SCORING SUMMARY | M6: High | N6: 30
A7: Category | B7: Score | C7: Max | D7: Percentage % | F7: Finding Rating | G7: Count | M7: Very High | N7: 0
A8: TOTAL | B8: =SUM(F18:F51) -> 0 | C8: =SUM(O18:O51) -> 193 | D8: =IF(C8<>0,B8/C8,"N/A") -> 0 | F8: Best Practice | G8: =COUNTIF(E18:E51,"Best Practice") -> 0 | M8: Not Applicable | N8: 0
F9: Verified | G9: =COUNTIF(E18:E51,"Verified") -> 0
F10: Low | G10: =COUNTIF(E18:E51,"Low") -> 0
F11: Moderate | G11: =COUNTIF(E18:E51,"Moderate") -> 0
F12: High | G12: =COUNTIF(E18:E51,"High") -> 0
F13: Very High | G13: =COUNTIF(E18:E51,"Very High") -> 0
F14: Not Applicable | G14: =COUNTIF(E18:E51,"Not Applicable") -> 0
A15: OVERALL SCORE | D15: =D8 -> 0 | F15: Rating Tier: | G15: =IF(D8="N/A","N/A",IF(D8>=0.99,"Excellence Leader",IF(D8>=0.9,"Gold",IF(D8>=0.8,"Silver",IF(D8>=0.51,"Bronze","Developing"))))) -> Developing
A17: Item # | B17: Subsection | C17: Requirement | D17: Evidence to Look For | E17: Finding Rating | F17: Score | G17: Max | H17: Observations | I17: Recommendations | J17: Citation | K17: Auditor Notes | O17: Eff. Max
A18: GENERAL PPE REQUIREMENTS
A19: PP-1 | B19: General PPE Requirements | C19: The employer must assess the workplace to determine if hazards are present that necessitate PPE. Where required, PPE must be provided, maintained in a safe and reliable condition, and used by employees. PPE must not be defective or damaged. | D19: Walk all work areas (minimum 5 representative areas including production floor, maintenance, and shipping). Observe employees performing tasks requiring PPE. For each area, confirm: appropriate PPE is in use and matches the hazard level; PPE is in serviceable condition — no cracked safety glasses, torn gloves, or hard hats with cracks or deep gouges; and a replacement process exists for damaged PPE. | E19: Select rating | F19: =IFERROR(ROUND(G19*VLOOKUP(E19,$M$2:$N$8,2,FALSE())/100,1),0) -> 0 | G19: 10 | J19: 29 CFR 1910.132(a),(c),(e) | O19: =IF(E19="Not Applicable",0,G19) -> 10
A20: PP-2 | B20: General PPE Requirements | C20: The employer must pay for required PPE — with the following exceptions where employees may be required to provide their own: (1) non-specialty safety-toe footwear (if worn off the job), (2) non-specialty prescription safety eyewear (if worn off the job), (3) logging boots, (4) ordinary clothing, skin creams, or other items used solely for protection from weather. | D20: Confirm the employer provides all required PPE at no cost. Interview 10% of employees in PPE-required areas (minimum 5). Ask whether they have ever been asked to purchase their own safety glasses, hard hats, gloves, or other required PPE. | E20: Select rating | F20: =IFERROR(ROUND(G20*VLOOKUP(E20,$M$2:$N$8,2,FALSE())/100,1),0) -> 0 | G20: 6 | J20: 29 CFR 1910.132(h) | O20: =IF(E20="Not Applicable",0,G20) -> 6
A21: PP-3 | B21: General PPE Requirements | C21: Where employees provide their own PPE, the employer must ensure the equipment is adequate to protect the employee. The employer must be responsible for the adequacy of such equipment, including maintenance and sanitation. | D21: If any employees use personal PPE (e.g., prescription safety glasses or personal steel-toed boots), confirm the employer has a documented approval process to verify the equipment meets the required protection standard. Confirm the employer's responsibility for adequacy is addressed in the written PPE program. | E21: Select rating | F21: =IFERROR(ROUND(G21*VLOOKUP(E21,$M$2:$N$8,2,FALSE())/100,1),0) -> 0 | G21: 4 | J21: 29 CFR 1910.132(b) | O21: =IF(E21="Not Applicable",0,G21) -> 4
A22: PP-4 | B22: General PPE Requirements | C22: The employer must assess the workplace to determine PPE needs and certify that the assessment was performed. The written hazard assessment certification must identify: (1) the workplace evaluated; (2) the name of the person certifying the evaluation was performed; (3) the date of the hazard assessment; and (4) a statement that the document identifies it as a certification of hazard assessment. | D22: Request the written PPE hazard assessment/certification. Confirm all four required elements are present. Review the assessment content: confirm it covers all significant tasks performed at this facility (not just production — include maintenance, housekeeping, shipping/receiving, and lab if applicable) and that PPE selections are matched to specific hazards identified for each task or area. Confirm the assessment was reviewed following any significant process change in the past 12 months. | E22: Select rating | F22: =IFERROR(ROUND(G22*VLOOKUP(E22,$M$2:$N$8,2,FALSE())/100,1),0) -> 0 | G22: 10 | J22: 29 CFR 1910.132(d) | O22: =IF(E22="Not Applicable",0,G22) -> 10
A23: PP-5 | B23: General PPE Requirements | C23: The employer must provide training to each employee required to use PPE. Training must cover: (1) when PPE is necessary; (2) what PPE is necessary; (3) how to properly don (put on), doff (remove), adjust, and wear PPE; (4) limitations of PPE; (5) proper care, maintenance, useful life, and disposal of PPE. Employees who demonstrate inadequate understanding must be retrained. | D23: Request PPE training records for 10% of employees in PPE-required roles (minimum 10 employees). Confirm training covers all five content areas above. Interview 10% of employees using PPE (minimum 3). Ask: 'How do you inspect your safety glasses before putting them on?' 'When would you replace your hard hat?' 'What does your PPE not protect you from?' Grade answers against the required training content. | E23: Select rating | F23: =IFERROR(ROUND(G23*VLOOKUP(E23,$M$2:$N$8,2,FALSE())/100,1),0) -> 0 | G23: 10 | J23: 29 CFR 1910.132(f) | O23: =IF(E23="Not Applicable",0,G23) -> 10
A24: EYE AND FACE PROTECTION
A25: PP-6 | B25: Eye and Face Protection | C25: Each affected employee must use appropriate eye or face protection when exposed to eye or face hazards. Hazard types requiring protection include: (1) flying particles — safety glasses with side shields or goggles; (2) molten metal — goggles or face shield; (3) liquid chemicals — chemical splash goggles; (4) acid/caustic liquids — splash goggles with face shield; (5) chemical gases/vapors — chemical splash goggles; (6) injurious light radiation — filter lenses with appropriate shade number; (7) lasers — laser safety eyewear. Employees who wear prescription lenses must wear either prescription safety eyewear or safety eyewear designed to fit over their corrective lenses. | D25: Walk work areas where eye hazards exist (minimum 5 areas). Confirm: the correct protection type is matched to the specific hazard; side shields are present on safety glasses used where flying particle hazards exist; chemical splash goggles are used for chemical handling (not just safety glasses, which do not seal against liquid splash); face shields are used in conjunction with goggles (not as a replacement) for splash hazards. Note whether prescription-lens employees have appropriate safety eyewear. | E25: Select rating | F25: =IFERROR(ROUND(G25*VLOOKUP(E25,$M$2:$N$8,2,FALSE())/100,1),0) -> 0 | G25: 8 | J25: 29 CFR 1910.133(a) | O25: =IF(E25="Not Applicable",0,G25) -> 8
A26: PP-7 | B26: Eye and Face Protection | C26: Protective eye and face devices must meet the requirements of ANSI/ISEA Z87.1 — American National Standard Practice for Occupational and Educational Eye and Face Protection. All eye and face protection devices must be marked by the manufacturer with the appropriate ANSI designation. | D26: Review issued safety glasses, goggles, and face shields in use. Confirm each device is marked 'Z87' or 'Z87+' (the '+' designation indicates high-impact protection). Reject any unmarked or consumer-grade eyewear used in industrial tasks. | E26: Select rating | F26: =IFERROR(ROUND(G26*VLOOKUP(E26,$M$2:$N$8,2,FALSE())/100,1),0) -> 0 | G26: 6 | J26: 29 CFR 1910.133(b) | O26: =IF(E26="Not Applicable",0,G26) -> 6
A27: PP-8 | B27: Eye and Face Protection | C27: Filter lenses and plates must meet ANSI requirements. For protection against radiant energy (welding, brazing, cutting), lenses must have a shade number appropriate for the specific process. Shade number guidance: Shielded metal arc welding (SMAW) at 10-500 amps = Shade 10-14; MIG/MAG welding = Shade 10-13; gas welding/brazing = Shade 4-8; oxygen cutting = Shade 3-6; plasma arc welding = Shade 6-14. | D27: If welding, cutting, or brazing occurs at this facility: identify the specific processes and confirm the shade number of filter lenses in use for each process. Use the shade number guide above. If shades are inadequate (too low), document as a deficiency. Confirm auto-darkening helmets used in welding applications are ANSI Z87.1 rated. | E27: Select rating | F27: =IFERROR(ROUND(G27*VLOOKUP(E27,$M$2:$N$8,2,FALSE())/100,1),0) -> 0 | G27: 6 | J27: 29 CFR 1910.133(a)(5) | O27: =IF(E27="Not Applicable",0,G27) -> 6
A28: HEAD PROTECTION
A29: PP-9 | B29: Head Protection | C29: Each affected employee must wear a protective helmet when working in areas posing a risk of head injury from: (1) falling or flying objects; (2) bumping the head against fixed objects (low clearance, protruding equipment); (3) electrical shock/burns. Hard hats must be worn with the bill facing forward unless the manufacturer specifically certifies the helmet for reverse use while maintaining the required protection class. | D29: Walk 10% of work areas identified in the PPE hazard assessment as requiring head protection (minimum 5 areas). Confirm: hard hats are worn by all employees, visitors, and contractors in required areas; no hard hats are worn backwards unless the manufacturer's certification for reverse use is confirmed; and hard hats are not suspended from equipment or stored in direct sunlight for extended periods (UV degrades the shell). | E29: Select rating | F29: =IFERROR(ROUND(G29*VLOOKUP(E29,$M$2:$N$8,2,FALSE())/100,1),0) -> 0 | G29: 8 | J29: 29 CFR 1910.135(a)(1)-(a)(2) | O29: =IF(E29="Not Applicable",0,G29) -> 8
A30: PP-10 | B30: Head Protection | C30: Head protection must meet ANSI/ISEA Z89.1 criteria. Hard hats are classified by type and class: Type I protects the top of the head; Type II protects the top and sides. Classes: Class E (electrical, rated to 20,000 volts); Class G (general, rated to 2,200 volts); Class C (conductive, no electrical protection). Facilities with electrical hazards must use Class E helmets in electrical work areas. | D30: Inspect 10% of hard hats in use (minimum 10 hard hats). Check the inside of each shell for: ANSI Z89.1 marking; the protection class (E, G, or C); the manufacture date (most manufacturers recommend retirement at 2-5 years from manufacture date and 2-5 years from first use, whichever comes first). Confirm the class used in electrical work areas is Class E, not Class G or C. | E30: Select rating | F30: =IFERROR(ROUND(G30*VLOOKUP(E30,$M$2:$N$8,2,FALSE())/100,1),0) -> 0 | G30: 6 | J30: 29 CFR 1910.135(b) | O30: =IF(E30="Not Applicable",0,G30) -> 6
A31: FOOT PROTECTION
A32: PP-11 | B32: Foot Protection | C32: Protective footwear must be worn by employees working in areas where there is a danger of: (1) foot injuries from falling or rolling objects; (2) foot injuries from objects piercing the sole; (3) foot injuries from electrical hazards. Safety footwear selection must match the hazard type (impact, compression, metatarsal, electrical hazard, puncture resistance). | D32: Walk 10% of work areas requiring safety footwear (minimum 5 areas). Confirm all employees, visitors, and contractors in those areas are wearing safety-toe footwear. Ask 10% of employees (minimum 5): 'How do you know your boots provide the right protection for the hazards here?' Confirm the PPE hazard assessment specifies the protection requirements by area. | E32: Select rating | F32: =IFERROR(ROUND(G32*VLOOKUP(E32,$M$2:$N$8,2,FALSE())/100,1),0) -> 0 | G32: 8 | J32: 29 CFR 1910.136(a) | O32: =IF(E32="Not Applicable",0,G32) -> 8
A33: PP-12 | B33: Foot Protection | C33: Protective footwear must meet ASTM F2412 (test methods) and ASTM F2413 (performance requirements), or the previous ANSI Z41 standard for footwear procured before the ASTM standard's adoption. Required markings on the label: ASTM designation; protection class (I/75 for impact, C/75 for compression, EH for electrical hazard, PR for puncture resistant, MT/75 for metatarsal). | D33: Inspect footwear of 10% of employees in required areas (minimum 5 employees). Ask employees to check the label inside their boot for the ASTM F2413 designation and confirm the protection class matches the hazard requirements in the PPE hazard assessment. Consumer-grade work boots without ASTM markings do not meet the standard. | E33: Select rating | F33: =IFERROR(ROUND(G33*VLOOKUP(E33,$M$2:$N$8,2,FALSE())/100,1),0) -> 0 | G33: 5 | J33: 29 CFR 1910.136(b) | O33: =IF(E33="Not Applicable",0,G33) -> 5
A34: ELECTRICAL PROTECTIVE EQUIPMENT
A35: PP-13 | B35: Electrical Protective Equipment | C35: Insulating blankets, matting, covers, line hoses, gloves, and sleeves made of rubber must meet ASTM design requirements. Each piece must be marked with the voltage class for which it provides protection. Classes: 00 (max use voltage 500V AC), 0 (1000V), 1 (7,500V), 2 (17,000V), 3 (26,500V), 4 (36,000V). Other types of electrical protective equipment must also meet applicable ASTM standards. | D35: If electrically rated rubber PPE is in use at this facility: inspect 10% of rubber insulating gloves, blankets, and sleeves (minimum 3 pieces). Confirm: voltage class markings are present and match the voltage of equipment worked on; no visible damage (cracks, cuts, punctures, swelling) is present; and gloves are stored rolled (not folded) in their protective bags. | E35: Select rating | F35: =IFERROR(ROUND(G35*VLOOKUP(E35,$M$2:$N$8,2,FALSE())/100,1),0) -> 0 | G35: 6 | J35: 29 CFR 1910.137(a)(1),(b) | O35: =IF(E35="Not Applicable",0,G35) -> 6
A36: PP-14 | B36: Electrical Protective Equipment | C36: Electrical protective equipment must be maintained in a safe, reliable condition. Rubber insulating equipment must be inspected before each day's use and immediately following an incident that may have caused damage. Rubber insulating equipment must be tested at regular intervals as follows: gloves and sleeves — every 6 months; blankets, covers, and line hoses — every 12 months. Equipment that fails inspection or testing must be immediately removed from service. | D36: Request the electrical PPE test log for 100% of rubber insulating PPE currently in service. Confirm: test dates are within the required intervals (gloves/sleeves within 6 months; blankets/covers/line hoses within 12 months); equipment with expired tests has been removed from service; and the log identifies each piece of equipment individually. Pull out a set of gloves — check the date stamp on the test tag inside the bag. | E36: Select rating | F36: =IFERROR(ROUND(G36*VLOOKUP(E36,$M$2:$N$8,2,FALSE())/100,1),0) -> 0 | G36: 8 | J36: 29 CFR 1910.137(b)(1)-(b)(2)(iii),(c) | O36: =IF(E36="Not Applicable",0,G36) -> 8
A37: HAND PROTECTION
A38: PP-15 | B38: Hand Protection | C38: Employers must select and require employees to use appropriate hand protection when hands are exposed to: (1) skin absorption of harmful substances; (2) severe cuts or lacerations; (3) severe abrasions; (4) punctures; (5) chemical burns; (6) thermal burns; (7) harmful temperature extremes. Glove selection must be based on the specific chemical or physical hazard — a single glove material does not protect against all chemicals. | D38: Review the PPE hazard assessment for glove requirements. Walk 10% of chemical handling, sharp material, and heat work areas (minimum 5 areas). For each chemical task: confirm the glove material is appropriate for the specific chemical (consult the SDS glove recommendation in Section 8); nitrile gloves do not protect against all solvents; latex gloves do not protect against all acids; thin surgical-style gloves do not protect against cuts. Interview 10% of employees using gloves (minimum 5): ask what hazard their gloves protect against and whether they have ever experienced a skin exposure while wearing gloves (which may indicate wrong glove type). | E38: Select rating | F38: =IFERROR(ROUND(G38*VLOOKUP(E38,$M$2:$N$8,2,FALSE())/100,1),0) -> 0 | G38: 8 | J38: 29 CFR 1910.138 | O38: =IF(E38="Not Applicable",0,G38) -> 8
A39: RESPIRATORY PROTECTION
A40: PP-16 | B40: Respiratory Protection | C40: Where respirators are necessary or required, a written respiratory protection program must be implemented containing ALL 9 required elements per 29 CFR 1910.134(c)(1). See Evidence column checklist. | D40: CHECKLIST — review the written respiratory protection program against each required element. Mark each: Verified, Partial, or Absent. □ (1) Procedures for selecting respirators for use in the workplace □ (2) Medical evaluations of employees required to use respirators □ (3) Fit testing procedures for tight-fitting respirators □ (4) Procedures for proper use in routine and reasonably foreseeable emergency situations □ (5) Procedures and schedules for cleaning, disinfecting, storing, inspecting, repairing, discarding, and maintaining respirators □ (6) Procedures to ensure adequate air quality, quantity, and flow for atmosphere-supplying respirators □ (7) Training on the respiratory hazards to which employees may be exposed (routine and emergency) □ (8) Training on proper use, limitations, donning/doffing, and maintenance of respirators □ (9) Procedures for regularly evaluating the effectiveness of the program Also confirm: program administrator is identified by name and has documented qualifications. If no respirator use occurs, confirm that a written evaluation exists determining no respirator is required. | E40: Select rating | F40: =IFERROR(ROUND(G40*VLOOKUP(E40,$M$2:$N$8,2,FALSE())/100,1),0) -> 0 | G40: 10 | J40: 29 CFR 1910.134(a)(2),(c)(1),(c)(3) | O40: =IF(E40="Not Applicable",0,G40) -> 10
A41: PP-17 | B41: Respiratory Protection | C41: Respirators, training, and medical evaluations must be provided at no cost to employees required to use them. | D41: Confirm the employer provides respirators, training, and medical evaluations at no cost. Interview 10% of respirator-using employees (minimum 3): ask whether they were charged for any respirator-related cost (medical exam, fit test, or equipment). | E41: Select rating | F41: =IFERROR(ROUND(G41*VLOOKUP(E41,$M$2:$N$8,2,FALSE())/100,1),0) -> 0 | G41: 5 | J41: 29 CFR 1910.134(c)(4) | O41: =IF(E41="Not Applicable",0,G41) -> 5
A42: PP-18 | B42: Respiratory Protection | C42: A medical evaluation must be completed before an employee is required to use a respirator, and before fit testing. The physician or licensed health care professional (PLHCP) must determine whether the employee is medically able to use the respirator. The medical questionnaire must be administered confidentially and results must not be shared with the employer without the employee's permission. Additional evaluations must be provided if: employee reports signs or symptoms related to respirator use; PLHCP, supervisor, or program administrator recommends it; information from the respirator program indicates a need; or fit testing shows difficulty using the respirator. | D42: Request medical evaluation records for 10% of respirator-using employees (minimum 5). Confirm: (1) initial evaluation was completed before first use — not concurrently with or after fit testing; (2) medical questionnaires were sent directly to the PLHCP (not reviewed by the supervisor or HR before submission); (3) the PLHCP issued a written recommendation letter confirming fitness for respirator use; and (4) employees who reported symptoms or experienced difficulty during fit testing received follow-up evaluations. | E42: Select rating | F42: =IFERROR(ROUND(G42*VLOOKUP(E42,$M$2:$N$8,2,FALSE())/100,1),0) -> 0 | G42: 10 | J42: 29 CFR 1910.134(e)(1)-(e)(7) | O42: =IF(E42="Not Applicable",0,G42) -> 10
A43: PP-19 | B43: Respiratory Protection | C43: Before using a tight-fitting facepiece respirator, employees must pass a fit test with the same make, model, style, and size of respirator to be used on the job. Fit testing must be repeated: annually; when employees report changes in physical condition that could affect fit (significant weight gain/loss, dental work, facial scarring); and when the employer issues a different respirator facepiece. Both qualitative (QLFT) and quantitative (QNFT) fit test methods are acceptable for most respirators; QNFT is required for certain high-hazard respirator classes. | D43: Request fit test records for 10% of tight-fitting respirator users (minimum 5). Confirm: (1) fit test was completed before first use — not during training or orientation; (2) the respirator model recorded on the fit test record matches exactly the model currently issued to the employee; (3) fit test was repeated within the past 12 months; (4) the fit test method used (QLFT or QNFT) is appropriate for the respirator class. Cross-check a sample of fit test records against the current respirator inventory to confirm the employee is using the same model tested. | E43: Select rating | F43: =IFERROR(ROUND(G43*VLOOKUP(E43,$M$2:$N$8,2,FALSE())/100,1),0) -> 0 | G43: 10 | J43: 29 CFR 1910.134(f)(1)-(f)(8) | O43: =IF(E43="Not Applicable",0,G43) -> 10
A44: PP-20 | B44: Respiratory Protection | C44: Procedures must be established and implemented to prevent facepiece seal leakage. Specifically: (1) No tight-fitting respirator shall be worn by employees who have facial hair that comes between the sealing surface of the facepiece and the face, or that interferes with valve function. (2) No tight-fitting respirator shall be worn by employees with any other condition that prevents a good face seal. (3) Each employee who wears a tight-fitting respirator must perform a user seal check immediately before each use using the positive and/or negative pressure check method. | D44: Walk 10% of areas where tight-fitting respirators are used (minimum 3 areas). Observe whether any employees wearing tight-fitting respirators have beards, goatees, or stubble in the sealing zone. Ask the safety manager how the no-facial-hair rule is enforced and communicated. Ask a respirator-wearing employee to demonstrate their user seal check before donning — confirm they use both the positive and negative pressure method or the manufacturer's recommended method. | E44: Select rating | F44: =IFERROR(ROUND(G44*VLOOKUP(E44,$M$2:$N$8,2,FALSE())/100,1),0) -> 0 | G44: 8 | J44: 29 CFR 1910.134(g)(1) | O44: =IF(E44="Not Applicable",0,G44) -> 8
A45: PP-21 | B45: Respiratory Protection | C45: Respirators must be properly maintained: (1) Cleaned and disinfected as often as necessary to be maintained in a sanitary condition, and before being worn by a different person; (2) Stored in a clean, sanitary location to protect from damage, contamination, dust, sunlight, extreme temperature, excessive moisture, and damaging chemicals; (3) Inspected before each use and during cleaning, including checking respirator function, facepiece, head straps, valves, connecting tube, cartridges, canisters or filters, and any other applicable component with reference to the manufacturer's recommendations; (4) Defective respirators removed from service and discarded or repaired. | D45: Inspect 10% of respirators currently in storage or in use (minimum 5 respirators). For each: confirm the facepiece is clean and free of cracking or discoloration; straps are intact; exhalation valve is not damaged; cartridges/filters are within their service life (confirm the change schedule is documented and followed). Inspect storage conditions — respirators should be individually bagged and stored away from chemicals, heat, and UV light. Ask whether a respirator discovered to be defective during a pre-use inspection has ever been taken out of service and how that was documented. | E45: Select rating | F45: =IFERROR(ROUND(G45*VLOOKUP(E45,$M$2:$N$8,2,FALSE())/100,1),0) -> 0 | G45: 8 | J45: 29 CFR 1910.134(h)(1)-(h)(4) | O45: =IF(E45="Not Applicable",0,G45) -> 8
A46: PP-22 | B46: Respiratory Protection | C46: Training must be provided to each employee required to use a respirator. Training must occur before use and annually thereafter (or more frequently if warranted). Training must be understandable to the employee and must cover: (1) why the respirator is necessary and how improper fit, use, or maintenance can compromise protection; (2) limitations and capabilities of the respirator; (3) effective use in emergency situations; (4) how to inspect, put on, remove, and check the seals; (5) maintenance and storage procedures; (6) medical signs and symptoms that may limit or prevent effective use. | D46: Request respirator training records for 10% of current respirator users (minimum 5). Confirm initial training before first use and annual retraining on file. Confirm training records show completion of all six content areas above (or confirm the training curriculum covers them). Interview 10% of respirator users (minimum 3): ask what hazard the respirator protects them from, when they would not use a respirator even if one were available (e.g., immediately dangerous to life and health atmosphere — should evacuate, not use a filter respirator), and how they store their respirator at end of shift. | E46: Select rating | F46: =IFERROR(ROUND(G46*VLOOKUP(E46,$M$2:$N$8,2,FALSE())/100,1),0) -> 0 | G46: 8 | J46: 29 CFR 1910.134(k) | O46: =IF(E46="Not Applicable",0,G46) -> 8
A47: PP-23 | B47: Respiratory Protection | C47: The program administrator must conduct periodic workplace evaluations to ensure the program is being properly implemented and to consult with employees to identify problems. Evaluations must include: (1) conducting workplace and respirator use observations; (2) reviewing employee reports of problems; (3) identifying program deficiencies; and (4) correcting deficiencies before they affect employee health. | D47: Request the most recent respiratory protection program evaluation records. Confirm: observations were conducted in the work area (not just a review of paperwork); employee feedback was solicited; and any identified deficiencies were addressed. Ask the program administrator when they last walked the areas where respirators are used and what they observed. | E47: Select rating | F47: =IFERROR(ROUND(G47*VLOOKUP(E47,$M$2:$N$8,2,FALSE())/100,1),0) -> 0 | G47: 6 | J47: 29 CFR 1910.134(l) | O47: =IF(E47="Not Applicable",0,G47) -> 6
A48: PERSONAL FALL PROTECTION SYSTEMS
A49: PP-24 | B49: Personal Fall Protection Systems | C49: All personal fall protection systems must meet general requirements: (1) Be designed, constructed, and installed per the applicable ANSI/ASSE standard; (2) Have connectors (snap hooks, carabiners, D-rings) that are corrosion-resistant and load-rated; (3) Have locking-type snap hooks to prevent rollout; (4) Self-retracting lifelines must meet ANSI/ASSE Z359.14; (5) Full-body harnesses must meet ANSI/ASSE Z359.11; (6) Equipment must be inspected before each use and removed from service if defective; (7) Equipment must be retired after a fall arrest event. | D49: Inspect 10% of fall protection equipment in inventory (minimum 5 harnesses and 5 lanyards/SRLs). For each harness: confirm ANSI Z359.11 marking; check the inspection date in the annual inspection log; look for cuts, tears, fraying, worn stitching, deformed D-rings, or cracked hardware. For SRLs: confirm ANSI Z359.14 marking; pull the lifeline out 12 inches and confirm it retracts under tension. Ask whether any harness or SRL has been involved in a fall arrest event — those must be removed from service immediately. | E49: Select rating | F49: =IFERROR(ROUND(G49*VLOOKUP(E49,$M$2:$N$8,2,FALSE())/100,1),0) -> 0 | G49: 8 | J49: 29 CFR 1910.140(c) | O49: =IF(E49="Not Applicable",0,G49) -> 8
A50: PP-25 | B50: Personal Fall Protection Systems | C50: Personal fall arrest systems must: (1) Limit maximum arresting force on the employee to 1,800 lbs when used with a body harness; (2) Be rigged such that the employee can fall no more than 6 feet, nor contact any lower level; (3) Bring an employee to a complete stop and limit maximum deceleration distance to 3.5 feet; (4) Have sufficient strength to withstand twice the potential impact load or at least 5,000 lbs per attached employee. | D50: For areas where fall arrest systems are in use (elevated platforms, roof access, elevated maintenance areas): confirm the fall clearance calculation has been performed for each anchor point (total fall clearance = free fall + deceleration distance + worker height + safety factor — must not contact the lower level). Confirm anchor points or certified anchorage connectors are rated to 5,000 lbs per employee. Sample 10% of fall arrest anchor points in use (minimum 3). | E50: Select rating | F50: =IFERROR(ROUND(G50*VLOOKUP(E50,$M$2:$N$8,2,FALSE())/100,1),0) -> 0 | G50: 6 | J50: 29 CFR 1910.140(d) | O50: =IF(E50="Not Applicable",0,G50) -> 6
A51: PP-26 | B51: Personal Fall Protection Systems | C51: Positioning systems must be rigged such that an employee cannot free-fall more than 2 feet. Positioning systems must be secured to an anchorage capable of supporting at least twice the potential impact load or at least 3,000 lbs, whichever is greater. | D51: If positioning systems (body belts with positioning lanyards) are used for work positioning on structures, poles, or elevated work surfaces: confirm the lanyard length limits free fall to 2 feet and the anchor meets the 3,000-lb minimum. Note that body belts are only permitted for positioning — not for fall arrest. | E51: Select rating | F51: =IFERROR(ROUND(G51*VLOOKUP(E51,$M$2:$N$8,2,FALSE())/100,1),0) -> 0 | G51: 5 | J51: 29 CFR 1910.140(e) | O51: =IF(E51="Not Applicable",0,G51) -> 5

Sheet Walking & Working Surfaces
A1: WALKING & WORKING SURFACES COMPLIANCE AUDIT | M1: Rating | N1: Pct
A2: 29 CFR 1910.22–30 — Walking and Working Surfaces. Prepared under attorney-client privilege. | M2: Best Practice | N2: 100
M3: Verified | N3: 100
A4: SITE: | B4: ='Pre-Audit Scoping'!D5 -> Test | D4: DATE(S): | E4: ='Pre-Audit Scoping'!D10 -> July 7-9 2026 | G4: AUDITOR(S): | H4: =TRIM('Pre-Audit Scoping'!D11)&IF(TRIM('Pre-Audit Scoping'!D12)<>"",", "&TRIM('Pre-Audit Scoping'!D12),"") -> Sara Wallon, Gabriel Wallon | M4: Low | N4: 85
M5: Moderate | N5: 70
A6: SCORING SUMMARY | M6: High | N6: 30
A7: Category | B7: Score | C7: Max | D7: Percentage % | F7: Finding Rating | G7: Count | M7: Very High | N7: 0
A8: TOTAL | B8: =SUM(F18:F48) -> 0 | C8: =SUM(O18:O48) -> 145 | D8: =IF(C8<>0,B8/C8,"N/A") -> 0 | F8: Best Practice | G8: =COUNTIF(E18:E48,"Best Practice") -> 0 | M8: Not Applicable | N8: 0
F9: Verified | G9: =COUNTIF(E18:E48,"Verified") -> 0
F10: Low | G10: =COUNTIF(E18:E48,"Low") -> 0
F11: Moderate | G11: =COUNTIF(E18:E48,"Moderate") -> 0
F12: High | G12: =COUNTIF(E18:E48,"High") -> 0
F13: Very High | G13: =COUNTIF(E18:E48,"Very High") -> 0
F14: Not Applicable | G14: =COUNTIF(E18:E48,"Not Applicable") -> 0
A15: OVERALL SCORE | D15: =D8 -> 0 | F15: Rating Tier: | G15: =IF(D8="N/A","N/A",IF(D8>=0.99,"Excellence Leader",IF(D8>=0.9,"Gold",IF(D8>=0.8,"Silver",IF(D8>=0.51,"Bronze","Developing"))))) -> Developing
A17: Item # | B17: Subsection | C17: Requirement | D17: Evidence to Look For | E17: Finding Rating | F17: Score | G17: Max | H17: Observations | I17: Recommendations | J17: Citation | K17: Auditor Notes | O17: Eff. Max
A18: GENERAL WALKING-WORKING SURFACE REQUIREMENTS
A19: WW-1 | B19: General Walking-Working Surface Requirements | C19: All places of employment, passageways, storerooms, and service rooms must be kept in a clean, orderly, and sanitary condition. Floor surfaces must be kept clean and as dry as possible. Drainage must be maintained for wet process areas, and false floors, platforms, mats, or other dry-standing places must be provided where workers stand in wet conditions. | D19: Walk 10% of the facility floor area (minimum 5 representative areas including production, maintenance, storage, and restroom/locker areas). Document: (1) any accumulations of debris, scrap, or product residue on walking surfaces; (2) wet areas without adequate drainage or dry-standing places; (3) oil or liquid spills not cleaned up; (4) any areas where material is stored in passageways or emergency egress paths. Compare findings to housekeeping inspection records to assess whether the inspection program is catching these conditions. | E19: Select rating | F19: =IFERROR(ROUND(G19*VLOOKUP(E19,$M$2:$N$8,2,FALSE())/100,1),0) -> 0 | G19: 8 | J19: 29 CFR 1910.22(a) | O19: =IF(E19="Not Applicable",0,G19) -> 8
A20: WW-2 | B20: General Walking-Working Surface Requirements | C20: Each walking-working surface must be able to support the maximum intended load placed upon it. Loads must not exceed the surface's design load capacity. | D20: Walk 10% of elevated platforms, mezzanines, catwalks, and storage areas (minimum 3 locations). Confirm: posted load capacity signs are present where maximum loads could be approached or exceeded; ask whether any process or storage configuration changes since the last inspection could affect load distribution. If any elevated surface shows visible signs of deflection, cracking, or corrosion, document for immediate engineering review. | E20: Select rating | F20: =IFERROR(ROUND(G20*VLOOKUP(E20,$M$2:$N$8,2,FALSE())/100,1),0) -> 0 | G20: 6 | J20: 29 CFR 1910.22(b) | O20: =IF(E20="Not Applicable",0,G20) -> 6
A21: WW-3 | B21: General Walking-Working Surface Requirements | C21: The employer must provide safe means of access and egress to and from each elevated walking-working surface, and must ensure that employees use those means. | D21: Walk to 10% of elevated work areas (minimum 5). Confirm: a proper access means (fixed ladder, stair, ramp) is present and accessible; no improvised climbing methods are in use (stacked pallets, barrels, equipment used as steps). Ask employees how they access elevated equipment for routine maintenance — confirm the intended access route is practical and actually being used. | E21: Select rating | F21: =IFERROR(ROUND(G21*VLOOKUP(E21,$M$2:$N$8,2,FALSE())/100,1),0) -> 0 | G21: 8 | J21: 29 CFR 1910.22(c) | O21: =IF(E21="Not Applicable",0,G21) -> 8
A22: WW-4 | B22: General Walking-Working Surface Requirements | C22: Walking-working surfaces must be inspected on a regular basis and as necessary, and must be maintained in a safe condition. Any surface with a hazardous condition must be taken out of service and either guarded to prevent employee use or corrected/repaired before employees use it again. When structural repairs are involved, a qualified person must perform or supervise the repair. | D22: Request the walking-working surface inspection logs for the most recent quarter. Confirm: inspections occur at documented intervals; identified hazards are tracked to corrective action closure; any surface removed from service is physically barricaded (not just flagged on a log). Sample 10% of corrective actions from inspection logs (minimum 3) and trace each to a closed work order or documented repair. | E22: Select rating | F22: =IFERROR(ROUND(G22*VLOOKUP(E22,$M$2:$N$8,2,FALSE())/100,1),0) -> 0 | G22: 8 | J22: 29 CFR 1910.22(d) | O22: =IF(E22="Not Applicable",0,G22) -> 8
A23: LADDERS
A24: WW-5 | B24: Ladders | C24: All ladders must meet the following general construction and use requirements: (1) Rungs, steps, and cleats must be parallel, level, and uniformly spaced 10-14 inches apart (center-to-center); (2) Minimum clear width of 11.5 inches for portable ladders, 16 inches for fixed ladders; (3) Ladder surfaces must be free of puncture and laceration hazards; (4) Ladders must be inspected before each shift and defective ladders must be immediately tagged 'Dangerous: Do Not Use' and removed from service; (5) Employees must face the ladder when climbing or descending; (6) At least one hand must grasp the ladder at all times; (7) No objects or loads carried that could cause loss of balance. | D24: Inspect 10% of ladders at the facility (minimum 5 ladders — include a mix of portable, fixed, and rolling). For each: (1) confirm the inspection date on the tag is current; (2) check rung spacing with a tape measure on 1-2 rungs; (3) check the minimum clear width; (4) look for cracked or broken rungs, bent side rails, missing feet or shoes, corrosion on metal ladders, and cracks or checks in wooden ladders; (5) observe whether ladders in storage are labeled correctly; (6) ask employees to demonstrate the correct climbing technique. | E24: Select rating | F24: =IFERROR(ROUND(G24*VLOOKUP(E24,$M$2:$N$8,2,FALSE())/100,1),0) -> 0 | G24: 8 | J24: 29 CFR 1910.23(b) | O24: =IF(E24="Not Applicable",0,G24) -> 8
A25: WW-6 | B25: Ladders | C25: Portable ladders must additionally meet these requirements: (1) Not loaded beyond maximum intended load; (2) Used only on stable and level surfaces, or secured to prevent displacement; (3) Secured or guarded with barriers when placed in doorways, passageways, or driveways; (4) Not moved or extended while an employee is on the ladder; (5) No single-rail portable ladders in use; (6) When used for access to an upper landing surface, side rails must extend at least 3 feet above the upper landing; (7) Not placed on boxes, barrels, or other unstable bases to gain height; (8) Not tied or fastened together to provide added length unless designed for such use. | D25: Observe portable ladder use at 10% of locations where they are deployed (minimum 3 locations). Confirm: the 3-foot extension above upper landing surfaces where access is being made; no ladders placed on unstable bases; no single-rail ladders in use anywhere. Ask employees to demonstrate how they secure a ladder placed in a doorway or near a path of travel. | E25: Select rating | F25: =IFERROR(ROUND(G25*VLOOKUP(E25,$M$2:$N$8,2,FALSE())/100,1),0) -> 0 | G25: 8 | J25: 29 CFR 1910.23(c) | O25: =IF(E25="Not Applicable",0,G25) -> 8
A26: WW-7 | B26: Ladders | C26: Fixed ladders must meet: (1) Minimum perpendicular clearance of 7 inches from centerline of rungs to nearest permanent object behind the ladder; (2) Side rails extend at least 42 inches above the top access level; (3) For through-ladders, extensions omit the rungs and flare the side rails 24-30 inches apart; (4) Pitch not greater than 90 degrees from horizontal; (5) Clear width of at least 15 inches on each side of the centerline; (6) Fixed ladders extending more than 24 feet above a lower level must have a ladder safety system (preferred) or cage/well. | D26: Walk to 10% of fixed ladders at the facility (minimum 5 fixed ladders). For ladders over 24 feet: confirm a ladder safety system (self-retracting lifeline system) or cage/well is installed. For all fixed ladders: confirm 42-inch side rail extension above the landing; check clearance behind rungs by estimating or measuring the space behind the rung centerline. Look for clogged cages or deteriorated ladder safety system components. | E26: Select rating | F26: =IFERROR(ROUND(G26*VLOOKUP(E26,$M$2:$N$8,2,FALSE())/100,1),0) -> 0 | G26: 6 | J26: 29 CFR 1910.23(d) | O26: =IF(E26="Not Applicable",0,G26) -> 6
A27: WW-8 | B27: Ladders | C27: Mobile ladder stands and platforms must meet: (1) Step width of at least 16 inches; (2) Slip-resistant step and platform surfaces; (3) Load capacity of at least 4 times the maximum intended load; (4) Wheels/casters capable of supporting proportional share of 4 times the maximum intended load; (5) Handrails with vertical height 29.5-37 inches on units with top step height of 4 feet or more; (6) Maximum work-surface height must not exceed 4 times the shortest base dimension (unless stabilized); (7) A system to prevent horizontal movement when an employee is on the unit. | D27: Inspect 10% of mobile ladder stands and platforms in use (minimum 3 units). Confirm: the wheel lock or brake system functions; the top step height does not exceed 4 times the shortest base dimension (tip-over hazard); handrails are present on units with top steps at or above 4 feet; load capacity marking is visible. Ask employees to demonstrate locking the wheels before climbing. | E27: Select rating | F27: =IFERROR(ROUND(G27*VLOOKUP(E27,$M$2:$N$8,2,FALSE())/100,1),0) -> 0 | G27: 5 | J27: 29 CFR 1910.23(e)(1) | O27: =IF(E27="Not Applicable",0,G27) -> 5
A28: STEP BOLTS AND MANHOLE STEPS
A29: WW-9 | B29: Step Bolts and Manhole Steps | C29: Step bolts used for climbing structures must meet requirements for dimensions (minimum 4.5-inch tread depth, minimum 8-inch spacing, minimum 4.5-inch width), slip resistance, and load capacity (minimum 250 lbs). Manhole steps must be corrosion-resistant (plastic-encapsulated steel or non-corrosive material) and capable of supporting 250 lbs minimum. | D29: If the facility has utility vaults, manholes, or structures with step bolts (common in outdoor utility or process areas): inspect 10% of step bolt installations and manhole step locations (minimum 2 locations). Confirm: no steps are missing, corroded through, or loose; spacing is sufficient to allow safe use; and the steps are labeled or included in the facility's walking-working surface inspection program. | E29: Select rating | F29: =IFERROR(ROUND(G29*VLOOKUP(E29,$M$2:$N$8,2,FALSE())/100,1),0) -> 0 | G29: 4 | J29: 29 CFR 1910.24(a)-(b) | O29: =IF(E29="Not Applicable",0,G29) -> 4
A30: STAIRWAYS
A31: WW-10 | B31: Stairways | C31: Standard stairways must meet: (1) Width of at least 22 inches; (2) Rise height (riser) of 6.5 to 9.5 inches (uniform throughout the flight, with maximum variation of 3/8 inch); (3) Tread depth of at least 9.5 inches (uniform throughout the flight, with maximum variation of 3/8 inch); (4) Non-slip surfaces on stair treads; (5) Stairway angle between 30 and 50 degrees from horizontal. | D31: Walk to 10% of stairways at the facility (minimum 5 stairways). For each: (1) observe whether tread surfaces are in good condition and non-slip (rubber nosing or abrasive strips present and not worn through); (2) check for any broken, cracked, or missing treads; (3) check riser height uniformity (a single uneven step is a significant trip hazard — measure the first and last riser height if uniformity appears compromised); (4) confirm adequate width for the level of use. | E31: Select rating | F31: =IFERROR(ROUND(G31*VLOOKUP(E31,$M$2:$N$8,2,FALSE())/100,1),0) -> 0 | G31: 6 | J31: 29 CFR 1910.25(b)-(c) | O31: =IF(E31="Not Applicable",0,G31) -> 6
A32: WW-11 | B32: Stairways | C32: Spiral, ship, and alternating-tread stairs may only be used where it is not practical to install a standard stairway. Each type has specific design requirements. Spiral stairs: minimum 26-inch inside diameter, 7.5-inch minimum tread depth. Ship stairs: 50-70 degree angle, 8-inch minimum tread depth. Alternating-tread stairs: 50-70 degree angle, 8.5-inch minimum tread depth. | D32: If any non-standard stair types are present: confirm they are used only in locations where a standard stair is not practical (document the reason for selection). Confirm each type meets its specific design requirements. Confirm handrails are installed on alternating-tread stairs and ship stairs. | E32: Select rating | F32: =IFERROR(ROUND(G32*VLOOKUP(E32,$M$2:$N$8,2,FALSE())/100,1),0) -> 0 | G32: 4 | J32: 29 CFR 1910.25(d)-(f) | O32: =IF(E32="Not Applicable",0,G32) -> 4
A33: DOCKBOARDS
A34: WW-12 | B34: Dockboards | C34: Dockboards (bridge plates) must be: (1) Strong enough to carry the load imposed upon them; (2) Secured in position (to the dock or vehicle) by anchors or equivalent means before use to prevent accidental movement; (3) Marked with the rated load capacity; (4) Not loaded beyond their rated load capacity. | D34: Inspect 10% of dockboards in use at the facility (minimum 3 dockboards). Confirm: load capacity markings are visible; the securing mechanism (anchor hooks, lip hooks, or chains) is present and used; ask a dock employee to demonstrate how they secure the dockboard before allowing forklift traffic across it. Look for bent, cracked, or corroded dockboards that may be structurally compromised. | E34: Select rating | F34: =IFERROR(ROUND(G34*VLOOKUP(E34,$M$2:$N$8,2,FALSE())/100,1),0) -> 0 | G34: 4 | J34: 29 CFR 1910.26 | O34: =IF(E34="Not Applicable",0,G34) -> 4
A35: SCAFFOLDS AND ROPE DESCENT SYSTEMS
A36: WW-13 | B36: Scaffolds and Rope Descent Systems | C36: Scaffolds used at this facility must meet the same requirements as those found in OSHA's Construction standards at 29 CFR 1926 Subpart L, including: (1) Load rating and capacity markings; (2) Planking or decking of proper grade and condition; (3) Guardrails, mid-rails, and toe boards on all open sides and ends; (4) Erected, moved, dismantled, or altered only under the supervision of a competent person; (5) Inspected by a competent person before each work shift and after any occurrence that could affect structural integrity. | D36: If scaffolding is used for maintenance or construction work at this facility: walk 10% of erected scaffolds (minimum 2 structures). Confirm: a tagged inspection has been completed for the current work shift; guardrails are present on all open sides; toe boards are in place to prevent tools from falling; the scaffold tag or log identifies the competent person who performed the inspection. If scaffolding appears structurally unstable or shows damaged components, document immediately. | E36: Select rating | F36: =IFERROR(ROUND(G36*VLOOKUP(E36,$M$2:$N$8,2,FALSE())/100,1),0) -> 0 | G36: 6 | J36: 29 CFR 1910.27 | O36: =IF(E36="Not Applicable",0,G36) -> 6
A37: WW-14 | B37: Scaffolds and Rope Descent Systems | C37: Rope descent systems must have anchorages certified by a qualified person to support at least 5,000 lbs per worker. Before each use, the rope, descent controller, carabiner, harness, and anchor must be inspected. Ropes must not be used if defective. | D37: If rope descent systems are used for exterior maintenance or window washing activities: confirm the anchorage certification documentation (qualified engineer certification) is on file and current. Confirm users are trained and that a pre-use inspection checklist is completed before each descent. | E37: Select rating | F37: =IFERROR(ROUND(G37*VLOOKUP(E37,$M$2:$N$8,2,FALSE())/100,1),0) -> 0 | G37: 4 | J37: 29 CFR 1910.27(b)(1)-(b)(2) | O37: =IF(E37="Not Applicable",0,G37) -> 4
A38: FALL PROTECTION REQUIREMENTS
A39: WW-15 | B39: Fall Protection Requirements | C39: The employer must ensure that each employee exposed to a fall hazard of 4 feet or more to a lower level is protected by a guardrail system, safety net system, or personal fall protection system. Additionally, fall protection is required at: (1) unprotected sides and edges; (2) hoist areas (guardrail or gate required); (3) holes in walking surfaces (cover or guardrail); (4) ramps, runways, and walkways; (5) walking surfaces above dangerous equipment; (6) wall and floor openings; (7) fixed ladders over 24 feet; (8) stairways with unprotected sides or edges; (9) scaffolds; (10) low-slope roofs. | D39: Walk 10% of all elevated areas, elevated platforms, mezzanines, open floor holes, and areas adjacent to floor openings (minimum 10 locations). For each location: confirm the appropriate fall protection system is in place; measure or estimate the fall height; check guardrail integrity (shake each rail — it must withstand 200 lbs of outward force); confirm all floor/wall openings have either guardrails or covers. Document every unguarded edge, missing guardrail section, or uncovered opening found. | E39: Select rating | F39: =IFERROR(ROUND(G39*VLOOKUP(E39,$M$2:$N$8,2,FALSE())/100,1),0) -> 0 | G39: 10 | J39: 29 CFR 1910.28(b)(1)-(b)(15),(c) | O39: =IF(E39="Not Applicable",0,G39) -> 10
A40: WW-16 | B40: Fall Protection Requirements | C40: Employees must be protected from falling objects through toeboards, screens, guardrail systems, canopies, or barricades whenever work is performed above other employees or in areas where overhead work creates a dropped-object hazard. | D40: Walk 10% of areas where elevated work occurs (maintenance catwalks, mezzanine edges, overhead crane work) to 10% of locations with overhead work (minimum 5 locations). Confirm: toeboards (minimum 3.5 inches in height) are present on all elevated platforms with guardrails where objects could fall; or a barricade prevents employees from working below; or debris netting is installed. Dropped-object incidents are among the most preventable serious injuries — document any overhead work area without protection. | E40: Select rating | F40: =IFERROR(ROUND(G40*VLOOKUP(E40,$M$2:$N$8,2,FALSE())/100,1),0) -> 0 | G40: 8 | J40: 29 CFR 1910.28(c) | O40: =IF(E40="Not Applicable",0,G40) -> 8
A41: FALL PROTECTION SYSTEMS — CRITERIA AND PRACTICES
A42: WW-17 | B42: Fall Protection Systems — Criteria and Practices | C42: Guardrail systems must: (1) Be between 39 and 45 inches in height (measured from the walking-working surface to the top of the top rail); (2) Withstand a force of 200 lbs applied in any outward or downward direction within 2 inches of the top edge; (3) Include a mid-rail (at approximately mid-height between the top rail and walking surface) or equivalent; (4) Have no openings large enough for an employee to fall through; (5) If made of wire rope, have rope capable of withstanding 200 lbs; (6) Not have any horizontal members acting as a ladder between the top rail and the walking surface. | D42: Evalute guardrail height and guardrailed locations (minimum 10). Height must be 39-45 inches. Physically attempt to push or pull the top rail — it should be rigid. Confirm mid-rails or equivalent are present. Look for damaged or missing mid-rail sections, guardrail posts that are loose, or gaps in the system wide enough for a person to fall through. | E42: Select rating | F42: =IFERROR(ROUND(G42*VLOOKUP(E42,$M$2:$N$8,2,FALSE())/100,1),0) -> 0 | G42: 8 | J42: 29 CFR 1910.29(b) | O42: =IF(E42="Not Applicable",0,G42) -> 8
A43: WW-18 | B43: Fall Protection Systems — Criteria and Practices | C43: Covers for holes in floors, roofs, and platforms must: (1) Be capable of supporting at least twice the weight of employees, equipment, and materials that may be imposed on the cover at any one time; (2) Be secured to prevent accidental displacement — not just set in place; (3) Be color-coded or marked 'HOLE' or 'COVER' to provide warning. | D43: Walk to 10% of hole cover locations (minimum 5 covers). For each: attempt to displace the cover — it must require a deliberate action to remove (cleat, chain, bolt, or other securing mechanism); confirm the cover is marked 'HOLE' or 'COVER' or color-coded in a warning color; check the cover for structural adequacy (no cracks, no excessive deflection under load). Document any unsecured or unmarked hole covers. | E43: Select rating | F43: =IFERROR(ROUND(G43*VLOOKUP(E43,$M$2:$N$8,2,FALSE())/100,1),0) -> 0 | G43: 8 | J43: 29 CFR 1910.29(e) | O43: =IF(E43="Not Applicable",0,G43) -> 8
A44: WW-19 | B44: Fall Protection Systems — Criteria and Practices | C44: Handrails and stair rail systems must: (1) Handrail top surface height: 30-38 inches above stair nosing; (2) Stair rail system top edge height: 36-42 inches above stair nosing; (3) Capable of withstanding a force of 200 lbs applied in any downward or outward direction at any point along the top edge; (4) Smooth surfaces to prevent lacerations; (5) Continuous the full length of the stair flight (from top riser to bottom riser) with no gaps that could catch a sleeve or fall restraint. | D44: Walk to 10% of stairways and measure handrail heights at the top and bottom of each stair (minimum 5 stairways). Compare to the 30-38 inch handrail requirement. Test stability: apply downward and outward force by hand. Check for continuity — no missing sections between top and bottom landings. Look for any handrails with sharp edges, splinters, or protrusions that could cause lacerations. | E44: Select rating | F44: =IFERROR(ROUND(G44*VLOOKUP(E44,$M$2:$N$8,2,FALSE())/100,1),0) -> 0 | G44: 6 | J44: 29 CFR 1910.29(f) | O44: =IF(E44="Not Applicable",0,G44) -> 6
A45: WW-20 | B45: Fall Protection Systems — Criteria and Practices | C45: Fixed ladders over 24 feet above a lower level must be equipped with a ladder safety system or a personal fall arrest system. Cages and wells are permitted only for ladders installed before November 19, 2018 (and must be replaced with a ladder safety system or PFAS by November 18, 2036). Ladder safety systems and personal fall arrest systems used on ladders must allow the employee to climb and descend without continually having to adjust the system. | D45: Identify 100% of fixed ladders at the facility that extend more than 24 feet above a lower level. For each: confirm a ladder safety system (self-retracting lifeline or climb assist device) or personal fall arrest system is installed. If a legacy cage or well is still in use (installed before November 19, 2018), note the compliant replacement deadline of November 18, 2036 and confirm the cage meets dimensional requirements in the interim. | E45: Select rating | F45: =IFERROR(ROUND(G45*VLOOKUP(E45,$M$2:$N$8,2,FALSE())/100,1),0) -> 0 | G45: 6 | J45: 29 CFR 1910.29(g),(i) | O45: =IF(E45="Not Applicable",0,G45) -> 6
A46: WW-21 | B46: Fall Protection Systems — Criteria and Practices | C46: Personal fall arrest systems (PFAS) used to protect against falls from walking-working surfaces must: (1) Limit maximum arresting force to 1,800 lbs; (2) Be rigged to minimize free-fall distance to 6 feet; (3) Bring the employee to a complete stop with a deceleration distance no greater than 3.5 feet; (4) Not allow the employee to contact a lower level or obstruction; (5) Have anchorage capable of supporting 5,000 lbs per attached employee; (6) Be used with a full-body harness (not a body belt for fall arrest). | D46: For 10% of locations where employees use PFAS for work at heights beyond guardrail protection (minimum 3 locations): confirm the total fall clearance (free fall + deceleration + harness height + safety factor) clears the lower level or obstruction. Confirm anchorage points are rated at 5,000 lbs (anchor certification or structural engineer confirmation). Confirm full-body harnesses — not body belts — are used for fall arrest. | E46: Select rating | F46: =IFERROR(ROUND(G46*VLOOKUP(E46,$M$2:$N$8,2,FALSE())/100,1),0) -> 0 | G46: 6 | J46: 29 CFR 1910.29(j) | O46: =IF(E46="Not Applicable",0,G46) -> 6
A47: FALL PROTECTION TRAINING
A48: WW-22 | B48: Fall Protection Training | C48: Before being exposed to a fall hazard, each employee must be trained by a qualified person in: (1) The nature of fall hazards in the work area; (2) The correct procedures for installing, inspecting, operating, maintaining, and disassembling the personal fall protection systems to be used; (3) The use and operation of the walking-working surfaces, guardrail systems, and personal fall protection systems; (4) The correct procedures for equipment and materials handling in work area; (5) The maximum intended load-carrying capacities of the equipment to be used. Retraining is required when the employer has reason to believe an employee lacks the required understanding or when equipment or surfaces change. | D48: Request fall protection training records for 10% of employees who work in areas requiring fall protection (minimum 10 employees). Confirm initial training was completed before first exposure to fall hazards. Interview 10% of employees working at heights (minimum 5). Ask: 'How do you inspect your harness before use?' 'What would you do if you found a fall while using a harness?' 'Who is responsible for anchoring points on this job?' Document gaps between training content and actual equipment/work conditions. | E48: Select rating | F48: =IFERROR(ROUND(G48*VLOOKUP(E48,$M$2:$N$8,2,FALSE())/100,1),0) -> 0 | G48: 8 | J48: 29 CFR 1910.30(a)-(d) | O48: =IF(E48="Not Applicable",0,G48) -> 8

Sheet Recordkeeping
A1: RECORDKEEPING COMPLIANCE AUDIT | M1: Rating | N1: Pct
A2: 29 CFR 1903/1904 — Recordkeeping and Posting Requirements. Prepared under attorney-client privilege. | M2: Best Practice | N2: 100
M3: Verified | N3: 100
A4: SITE: | B4: ='Pre-Audit Scoping'!D5 -> Test | D4: DATE(S): | E4: ='Pre-Audit Scoping'!D10 -> July 7-9 2026 | G4: AUDITOR(S): | H4: =TRIM('Pre-Audit Scoping'!D11)&IF(TRIM('Pre-Audit Scoping'!D12)<>"",", "&TRIM('Pre-Audit Scoping'!D12),"") -> Sara Wallon, Gabriel Wallon | M4: Low | N4: 85
M5: Moderate | N5: 70
A6: SCORING SUMMARY | M6: High | N6: 30
A7: Category | B7: Score | C7: Max | D7: Percentage % | F7: Finding Rating | G7: Count | M7: Very High | N7: 0
A8: TOTAL | B8: =SUM(F18:F59) -> 0 | C8: =SUM(O18:O59) -> 225 | D8: =IF(C8<>0,B8/C8,"N/A") -> 0 | F8: Best Practice | G8: =COUNTIF(E18:E59,"Best Practice") -> 0 | M8: Not Applicable | N8: 0
F9: Verified | G9: =COUNTIF(E18:E59,"Verified") -> 0
F10: Low | G10: =COUNTIF(E18:E59,"Low") -> 0
F11: Moderate | G11: =COUNTIF(E18:E59,"Moderate") -> 0
F12: High | G12: =COUNTIF(E18:E59,"High") -> 0
F13: Very High | G13: =COUNTIF(E18:E59,"Very High") -> 0
F14: Not Applicable | G14: =COUNTIF(E18:E59,"Not Applicable") -> 0
A15: OVERALL SCORE | D15: =D8 -> 0 | F15: Rating Tier: | G15: =IF(D8="N/A","N/A",IF(D8>=0.99,"Excellence Leader",IF(D8>=0.9,"Gold",IF(D8>=0.8,"Silver",IF(D8>=0.51,"Bronze","Developing"))))) -> Developing
A17: Item # | B17: Subsection | C17: Requirement | D17: Evidence to Look For | E17: Finding Rating | F17: Score | G17: Max | H17: Observations | I17: Recommendations | J17: Citation | K17: Auditor Notes | O17: Eff. Max
A18: RECORDKEEPING REQUIREMENTS
A19: RK-1 | B19: Recordkeeping Requirements | C19: Employer records work-related fatalities, injuries, and illnesses on the OSHA 300 Log. | D19: Pull the OSHA 300 Log for the current calendar year. Cross-reference against the incident/case management system or first aid log. Sample 10% of all reported injuries and illnesses from the audit period (minimum 3 cases) — confirm each recordable case appears on the 300 Log and that non-recordable cases are appropriately excluded. | E19: Select rating | F19: =IFERROR(ROUND(G19*VLOOKUP(E19,$M$2:$N$8,2,FALSE())/100,1),0) -> 0 | G19: 10 | J19: 29 CFR 1904.4(a) | O19: =IF(E19="Not Applicable",0,G19) -> 10
A20: RK-2 | B20: Recordkeeping Requirements | C20: Employer uses the correct OSHA forms: OSHA 300 Log of Work-Related Injuries and Illnesses, OSHA 300-A Summary of Work-Related Injuries and Illnesses, and OSHA 301 Injury and Illness Incident Report (or an approved equivalent). | D20: Request the three required forms. Confirm they are the current OSHA versions (or an approved equivalent). If an alternative to the OSHA 301 is used, confirm it is readable, understandable, and completed using the same instructions as the OSHA form it replaces. If computer-based, verify the system can produce equivalent forms on demand. | E20: Select rating | F20: =IFERROR(ROUND(G20*VLOOKUP(E20,$M$2:$N$8,2,FALSE())/100,1),0) -> 0 | G20: 8 | J20: 29 CFR 1904.29(a),(b)(4) | O20: =IF(E20="Not Applicable",0,G20) -> 8
A21: RK-3 | B21: Recordkeeping Requirements | C21: Each recordable injury/illness is entered on the OSHA 300 Log within 7 calendar days of the employer receiving information that a recordable case has occurred. | D21: From your case sample (10% of recordable cases, minimum 3), compare the date the employer received information about the injury/illness to the date it was entered on the OSHA 300 Log. The entry must appear within 7 calendar days of that notification date — not 7 days from the injury date. | E21: Select rating | F21: =IFERROR(ROUND(G21*VLOOKUP(E21,$M$2:$N$8,2,FALSE())/100,1),0) -> 0 | G21: 10 | J21: 29 CFR 1904.29(b)(3) | O21: =IF(E21="Not Applicable",0,G21) -> 10
A22: RK-4 | B22: Recordkeeping Requirements | C22: Computer-based recordkeeping systems are acceptable only if they can produce the equivalent OSHA 300, 300-A, and 301 forms when needed. | D22: If the site uses electronic recordkeeping (e.g., EHS software), ask the site to generate each form on-screen or print it during the audit. The forms must be producible by the end of the next business day for employee requests and within 4 business hours for government representative requests. | E22: Select rating | F22: =IFERROR(ROUND(G22*VLOOKUP(E22,$M$2:$N$8,2,FALSE())/100,1),0) -> 0 | G22: 5 | J22: 29 CFR 1904.29(b)(5) | O22: =IF(E22="Not Applicable",0,G22) -> 5
A23: RK-5 | B23: Recordkeeping Requirements | C23: Employee names must not be entered on the OSHA 300 Log for privacy concern cases. Privacy concern cases include: injuries/illnesses affecting an intimate body part or the reproductive system; resulting from sexual assault; mental illness; HIV, hepatitis, or tuberculosis; needlestick or sharps injuries; or any illness voluntarily designated as private by the employee. | D23: Review 10% of 300 Log entries (minimum 3) that appear to involve privacy-sensitive conditions. Confirm the employee's name is replaced with 'Privacy Case' on the log. Verify no personally identifiable information in the description column could identify the employee. | E23: Select rating | F23: =IFERROR(ROUND(G23*VLOOKUP(E23,$M$2:$N$8,2,FALSE())/100,1),0) -> 0 | G23: 8 | J23: 29 CFR 1904.29(b)(7),(9),(10) | O23: =IF(E23="Not Applicable",0,G23) -> 8
A24: RK-6 | B24: Recordkeeping Requirements | C24: A separate, confidential list linking each privacy case number to the employee's name must be maintained and stored separately from the OSHA 300 Log. | D24: Request the confidential privacy case list. Confirm it is stored in a restricted location (not filed with the 300 Log). Verify each privacy case logged on the 300 Log appears on the confidential list. The list should not be accessible to general management. | E24: Select rating | F24: =IFERROR(ROUND(G24*VLOOKUP(E24,$M$2:$N$8,2,FALSE())/100,1),0) -> 0 | G24: 8 | J24: 29 CFR 1904.29(b)(6) | O24: =IF(E24="Not Applicable",0,G24) -> 8
A25: RK-7 | B25: Recordkeeping Requirements | C25: If the employer has multiple business establishments, a separate OSHA 300 Log must be maintained for each establishment expected to be in operation for one year or longer. | D25: If this employer operates multiple sites, confirm a site-specific 300 Log exists for this establishment — not a combined log shared across locations. If logs are maintained centrally, confirm the site can produce its own log by end of next business day. | E25: Select rating | F25: =IFERROR(ROUND(G25*VLOOKUP(E25,$M$2:$N$8,2,FALSE())/100,1),0) -> 0 | G25: 6 | J25: 29 CFR 1904.30(a),(b)(1) | O25: =IF(E25="Not Applicable",0,G25) -> 6
A26: RK-8 | B26: Recordkeeping Requirements | C26: For short-term establishments (operating less than one year), injuries/illnesses must be recorded either on an establishment-specific log, one log covering all short-term establishments, or logs organized by division or region. | D26: If the employer has any temporary or short-term field locations, confirm which of the three allowable methods is used to capture recordable cases for those locations. Verify that no cases fall through the cracks between the host and field establishment. | E26: Select rating | F26: =IFERROR(ROUND(G26*VLOOKUP(E26,$M$2:$N$8,2,FALSE())/100,1),0) -> 0 | G26: 4 | J26: 29 CFR 1904.30(b)(1)-(2) | O26: =IF(E26="Not Applicable",0,G26) -> 4
A27: RK-9 | B27: Recordkeeping Requirements | C27: Employees who work at multiple locations or at no fixed location must be linked to one business establishment for recordkeeping. Injuries at another employer's establishment are recorded on that establishment's log; injuries elsewhere are recorded on the employee's home establishment log. | D27: If this site has employees who regularly work at other employer locations or in the field, confirm the site has a defined rule for which log captures their recordable cases. Ask for one example and trace where the case was recorded. | E27: Select rating | F27: =IFERROR(ROUND(G27*VLOOKUP(E27,$M$2:$N$8,2,FALSE())/100,1),0) -> 0 | G27: 4 | J27: 29 CFR 1904.30(b)(3)-(4) | O27: =IF(E27="Not Applicable",0,G27) -> 4
A28: RK-10 | B28: Recordkeeping Requirements | C28: The employer must record recordable injuries/illnesses for all employees under day-to-day supervision, regardless of employment type — including labor, executive, hourly, salaried, part-time, seasonal, migrant, and temporary/staffing agency workers the site supervises. | D28: Confirm with HR or the safety manager how many temporary or contract workers are on site under day-to-day supervision. Review the 300 Log to confirm any recordable cases involving those workers appear. Check the staffing agency contract for language on recordkeeping responsibility. | E28: Select rating | F28: =IFERROR(ROUND(G28*VLOOKUP(E28,$M$2:$N$8,2,FALSE())/100,1),0) -> 0 | G28: 10 | J28: 29 CFR 1904.31(a)-(b) | O28: =IF(E28="Not Applicable",0,G28) -> 10
A29: RK-11 | B29: Recordkeeping Requirements | C29: At year-end, the OSHA 300 Log must be reviewed, the 300-A Annual Summary created and certified by a company executive, and the 300-A posted February 1 through April 30 per 29 CFR 1904.32. The 300-A must contain 8 required data elements. See Evidence column checklist. | D29: Review the most recent OSHA 300-A Annual Summary. Verify all 8 required elements are present and completed: □ (1) Totals in each column from the OSHA 300 Log (enter zeros if no recordable cases — do not leave blank) □ (2) Calendar year covered □ (3) Company name □ (4) Establishment name □ (5) Establishment address □ (6) Annual average number of employees covered by the 300 Log (frequently left blank — this is a deficiency) □ (7) Total hours worked by all employees covered by the 300 Log (frequently left blank — this is a deficiency) □ (8) Certification: signature, printed name, title, and date — by a company executive (owner, officer, highest-ranking official at the establishment, or that person's immediate supervisor) Also confirm: request posting evidence (date-stamped photo, posting log, or supervisor attestation) that the 300-A was displayed in a conspicuous location from February 1 through April 30. | E29: Select rating | F29: =IFERROR(ROUND(G29*VLOOKUP(E29,$M$2:$N$8,2,FALSE())/100,1),0) -> 0 | G29: 10 | J29: 29 CFR 1904.32(a),(b)(2)-(6) | O29: =IF(E29="Not Applicable",0,G29) -> 10
A30: RK-12 | B30: Recordkeeping Requirements | C30: The employer must retain OSHA 300 Logs, 300-A Annual Summaries, 301 Incident Report Forms, and the privacy case list for 5 years following the end of the calendar year covered. | D30: Request 300 Logs and 300-A summaries for the 5 prior calendar years. Confirm all are present and have not been destroyed. If electronic, confirm the system retains records with appropriate date stamps. | E30: Select rating | F30: =IFERROR(ROUND(G30*VLOOKUP(E30,$M$2:$N$8,2,FALSE())/100,1),0) -> 0 | G30: 8 | J30: 29 CFR 1904.33(a) | O30: =IF(E30="Not Applicable",0,G30) -> 8
... A37: RK-19 | B37: Recordkeeping Requirements | C37: If the Bureau of Labor Statistics (BLS) notifies the employer that it has been selected to participate in the annual Survey of Occupational Injuries and Illnesses, the employer must complete and return the survey form by the deadline specified on the form. | D37: Ask whether the site has received a BLS survey notification in the past two years. If yes, request evidence of timely response (completed form or submission confirmation). Note: even employers otherwise exempt from recordkeeping must respond to BLS surveys. | E37: Select rating | F37: =IFERROR(ROUND(G37*VLOOKUP(E37,$M$2:$N$8,2,FALSE())/100,1),0) -> 0 | G37: 4 | J37: 29 CFR 1904.42 | O37: =IF(E37="Not Applicable",0,G37) -> 4
A38: RECORDING CRITERIA
A39: RK-20 | B39: Recording Criteria | C39: A recordable case is one that is work-related, is a new case, AND meets one or more general recording criteria: (1) death; (2) days away from work; (3) restricted work or job transfer; (4) medical treatment beyond first aid; (5) loss of consciousness; (6) significant injury or illness diagnosed by a physician or PLHCP (including cancer, chronic irreversible disease, fractured or cracked bone, or punctured eardrum). | D39: Sample 10% of all cases from the audit period (minimum 5 cases, including both recorded and excluded cases). For each case: (1) independently determine work-relatedness; (2) determine if it is a new case; (3) identify whether any general recording criterion applies. Compare your determination to the site's classification on the 300 Log. Document any cases where your determination differs from the site's. | E39: Select rating | F39: =IFERROR(ROUND(G39*VLOOKUP(E39,$M$2:$N$8,2,FALSE())/100,1),0) -> 0 | G39: 10 | J39: 29 CFR 1904.7 | O39: =IF(E39="Not Applicable",0,G39) -> 10
A40: RK-21 | B40: Recording Criteria | C40: All injuries and illnesses that arise in the work environment are presumed work-related. Exceptions (not recordable): employee was present as a member of the general public; signs/symptoms result solely from a non-work event; voluntary participation in a wellness program; eating/drinking personal food; personal tasks outside assigned work hours; personal grooming or self-medication; motor vehicle accident on a company parking lot while commuting; the common cold or flu; mental illness (unless a licensed professional states it is work-related). | D40: From your case sample (10%, minimum 5), review any cases the site excluded as non-recordable. Confirm the exclusion falls within one of the eight defined exceptions. Be alert for common misapplications — particularly personal grooming exclusions applied broadly, or 'commuting' exclusions applied to employees who were performing work tasks during travel. | E40: Select rating | F40: =IFERROR(ROUND(G40*VLOOKUP(E40,$M$2:$N$8,2,FALSE())/100,1),0) -> 0 | G40: 8 | J40: 29 CFR 1904.5(b)(1)-(7) | O40: =IF(E40="Not Applicable",0,G40) -> 8
A41: RK-22 | B41: Recording Criteria | C41: A new case must be recorded if: (1) the employee has not previously experienced a recorded injury/illness of the same type affecting the same part of the body, OR (2) the employee previously had such a case but had completely recovered and a new work event caused symptoms to reappear. | D41: From your case sample, identify any cases involving a body part or condition the employee had a prior recorded case for. Confirm the site applied the new-case test — fully recovered + new workplace event = new case. Chronic conditions (occupational cancer, asbestosis, silicosis) should be recorded once, not re-recorded each time symptoms recur. | E41: Select rating | F41: =IFERROR(ROUND(G41*VLOOKUP(E41,$M$2:$N$8,2,FALSE())/100,1),0) -> 0 | G41: 6 | J41: 29 CFR 1904.6 | O41: =IF(E41="Not Applicable",0,G41) -> 6
A42: RK-23 | B42: Recording Criteria | C42: Needlestick and sharps injuries involving another person's blood or other potentially infectious materials (OPIM) must be recorded on the OSHA 300 Log as an injury. The employee's name must be withheld (privacy case). If the employee is later diagnosed with a bloodborne disease as a result, the record must be updated from injury to illness. | D42: If the site has any exposure to bloodborne pathogens (maintenance on medical waste equipment, first aid providers, health services): ask whether any sharps exposure incidents have occurred in the audit period. If yes, confirm they appear on the 300 Log as privacy cases and that any resulting diagnoses were used to update the record. | E42: Select rating | F42: =IFERROR(ROUND(G42*VLOOKUP(E42,$M$2:$N$8,2,FALSE())/100,1),0) -> 0 | G42: 6 | J42: 29 CFR 1904.8 | O42: =IF(E42="Not Applicable",0,G42) -> 6
A43: RK-24 | B43: Recording Criteria | C43: If an employee is removed from a job due to an OSHA medical removal standard (e.g., lead standard 1910.1025, cadmium standard 1910.1027, hexavalent chromium 1910.1026, noise-induced hearing loss under 1910.95), that removal must be recorded as days away from work or restricted work activity, as applicable. Chemical exposure removals must be identified as poisoning on the 300 Log. | D43: Identify whether any OSHA standards with medical removal provisions apply at this facility (confirm with the safety manager). Sample 10% of MRP-triggered removals from the audit period (minimum 1) and verify they are recorded correctly on the 300 Log. | E43: Select rating | F43: =IFERROR(ROUND(G43*VLOOKUP(E43,$M$2:$N$8,2,FALSE())/100,1),0) -> 0 | G43: 4 | J43: 29 CFR 1904.9(b)(1)-(3) | O43: =IF(E43="Not Applicable",0,G43) -> 4
A44: RK-25 | B44: Recording Criteria | C44: Work-related hearing loss is recordable when: (1) the employee has experienced a Standard Threshold Shift (STS) — an average change in hearing threshold of 10 dB or more at 2000, 3000, and 4000 Hz in one or both ears — AND (2) the employee's total hearing level is 25 dB or more above audiometric zero (averaged at 2000, 3000, and 4000 Hz) in the same ear(s). Age adjustment is permitted for the STS but not the 25 dB level. | D44: Request the audiometric testing program results for the audit period. Confirm the audiologist or program administrator has flagged any STS cases and applied both the STS test and the 25 dB level test. Sample 10% of STS cases flagged in the past year (minimum 2) and verify the recordability determination and 300 Log entry. Confirm STS cases are identified in the hearing loss column of the 300 Log. | E44: Select rating | F44: =IFERROR(ROUND(G44*VLOOKUP(E44,$M$2:$N$8,2,FALSE())/100,1),0) -> 0 | G44: 6 | J44: 29 CFR 1904.10 | O44: =IF(E44="Not Applicable",0,G44) -> 6
A45: RK-26 | B45: Recording Criteria | C45: A work-related tuberculosis (TB) infection is recordable when: (1) the employee was occupationally exposed to a known case of active TB, AND (2) the employee subsequently develops a TB infection as evidenced by a positive skin test or diagnosis by a PLHCP. | D45: Ask whether this facility has any potential TB exposure (healthcare adjacency, corrections, homeless shelter proximity). If yes, confirm a TB surveillance protocol is in place and that any positive skin test conversions following known occupational exposure are evaluated for recordability. If TB exposure is not present, mark Not Applicable. | E45: Select rating | F45: =IFERROR(ROUND(G45*VLOOKUP(E45,$M$2:$N$8,2,FALSE())/100,1),0) -> 0 | G45: 4 | J45: 29 CFR 1904.11 | O45: =IF(E45="Not Applicable",0,G45) -> 4
A46: LIMITED RECORDKEEPING EXEMPTIONS
A47: RK-27 | B47: Limited Recordkeeping Exemptions | C47: Employers with 10 or fewer employees at all times during the entire calendar year are partially exempt from routine OSHA recordkeeping. However, even exempt employers must: (1) report fatalities, hospitalizations, amputations, and eye losses to OSHA; and (2) maintain records and respond to BLS surveys if selected. | D47: Confirm site headcount at all times during the calendar year. If the site ever exceeded 10 employees — even temporarily (seasonal peak, temp workers, project-based hiring) — the exemption does not apply for that year. Manufacturing facilities the size of NGC typically do not qualify. | E47: Select rating | F47: =IFERROR(ROUND(G47*VLOOKUP(E47,$M$2:$N$8,2,FALSE())/100,1),0) -> 0 | G47: 4 | J47: 29 CFR 1904.1(a)(1) | O47: =IF(E47="Not Applicable",0,G47) -> 4
A48: RK-28 | B48: Limited Recordkeeping Exemptions | C48: Establishments classified in a low-hazard industry listed in 29 CFR 1904 Subpart B Appendix A are partially exempt from routine OSHA recordkeeping. Low-hazard industries include retail, finance, insurance, real estate, and specific service industries. Gypsum manufacturing is NOT on the exempt list. | D48: Confirm this establishment's primary NAICS code with the site manager. Verify the NAICS code is not on the partially-exempt low-hazard industry list (Appendix A to 29 CFR 1904 Subpart B). Manufacturing operations like gypsum production are not exempt and must maintain full records. | E48: Select rating | F48: =IFERROR(ROUND(G48*VLOOKUP(E48,$M$2:$N$8,2,FALSE())/100,1),0) -> 0 | G48: 4 | J48: 29 CFR 1904.2(a)(1); 1904.42 | O48: =IF(E48="Not Applicable",0,G48) -> 4
A49: POSTING REQUIREMENTS
A50: RK-29 | B50: Posting Requirements | C50: The OSHA 'Job Safety and Health: It's the Law' poster (or the applicable State Plan equivalent) must be posted in a conspicuous place where notices to employees are customarily posted. The poster must not be defaced, destroyed, or covered. Reproductions and facsimiles are acceptable if at least 8.5 x 14 inches with 10-point print. | D50: Walk to the main employee bulletin board, break room, time clock area, and any other locations where notices are posted. Confirm the current federal or State Plan OSHA poster is displayed and legible. Note if it is an outdated version (compare the revision date). Free current copies are available at osha.gov. | E50: Select rating | F50: =IFERROR(ROUND(G50*VLOOKUP(E50,$M$2:$N$8,2,FALSE())/100,1),0) -> 0 | G50: 5 | J50: 29 CFR 1903.2(a)(1)-(3) | O50: =IF(E50="Not Applicable",0,G50) -> 5
A51: RK-30 | B51: Posting Requirements | C51: If an employer obtains copies of OSHA regulations or applicable standards, those copies must be made available for inspection and copying by any employee or authorized representative at the establishment where the employee is employed, on the same day a request is made. | D51: Ask the safety manager how an employee would access the applicable OSHA standards if they requested them today. Confirm a mechanism exists — whether a binder in the safety office, an intranet link, or printed copies — and that it is accessible to all employees without management approval. | E51: Select rating | F51: =IFERROR(ROUND(G51*VLOOKUP(E51,$M$2:$N$8,2,FALSE())/100,1),0) -> 0 | G51: 3 | J51: 29 CFR 1903.2(c) | O51: =IF(E51="Not Applicable",0,G51) -> 3
A52: POSTING OF CITATIONS & ABATEMENT
A53: RK-31 | B53: Posting of Citations & Abatement | C53: Immediately upon receipt of any OSHA citation, the employer must post an unedited copy of the citation at or near each place where the alleged violation occurred. The citation must remain posted until the violation has been abated OR for 3 working days — whichever is longer. The citation must remain posted even while being contested. | D53: Ask whether any OSHA citations have been received in the past 3 years. If yes, confirm the site has documentation of posting (a log entry, photo, or supervisor attestation). Confirm the citation was not altered, defaced, or covered. If citations are currently open, confirm they are posted today. | E53: Select rating | F53: =IFERROR(ROUND(G53*VLOOKUP(E53,$M$2:$N$8,2,FALSE())/100,1),0) -> 0 | G53: 4 | J53: 29 CFR 1903.16 | O53: =IF(E53="Not Applicable",0,G53) -> 4
A54: RK-32 | B54: Posting of Citations & Abatement | C54: For serious, repeat, and willful violations involving movable equipment, the employer must attach a warning tag (or a copy of the citation) to the operating controls or cited component before the equipment moves within or between worksites. The tag must identify the nature of the violation and the location of the citation. | D54: If any citations involving movable equipment (forklifts, cranes, mobile equipment) have been received, confirm the tagging process was followed before the equipment was moved. If no movable equipment citations, mark Not Applicable. | E54: Select rating | F54: =IFERROR(ROUND(G54*VLOOKUP(E54,$M$2:$N$8,2,FALSE())/100,1),0) -> 0 | G54: 4 | J54: 29 CFR 1903.19(i) | O54: =IF(E54="Not Applicable",0,G54) -> 4
A55: RK-33 | B55: Posting of Citations & Abatement | C55: Cited violations must be abated by the date set in the citation or as extended by OSHA. Within 10 calendar days after the abatement date, the employer must certify to OSHA in writing that each cited violation has been abated. For willful/repeat violations and serious violations requiring abatement documentation, the employer must also submit supporting evidence (photos, receipts, records). | D55: Request the abatement certification letters or submissions for any citations received. Confirm they were submitted within 10 calendar days of the abatement date. For any serious citations requiring documentation, confirm supporting evidence was included. | E55: Select rating | F55: =IFERROR(ROUND(G55*VLOOKUP(E55,$M$2:$N$8,2,FALSE())/100,1),0) -> 0 | G55: 6 | J55: 29 CFR 1903.19(c)-(f) | O55: =IF(E55="Not Applicable",0,G55) -> 6
A56: RK-34 | B56: Posting of Citations & Abatement | C56: All required abatement submissions to OSHA must include: (1) employer name and address; (2) inspection number; (3) citation and item numbers; (4) a statement that the information is accurate; and (5) the employer's signature and authorized representative's signature. | D56: Review a sample abatement submission and confirm all five required elements are present. A submission missing any element is deficient and may result in a failure to abate finding. | E56: Select rating | F56: =IFERROR(ROUND(G56*VLOOKUP(E56,$M$2:$N$8,2,FALSE())/100,1),0) -> 0 | G56: 4 | J56: 29 CFR 1903.19(h) | O56: =IF(E56="Not Applicable",0,G56) -> 4
A57: RK-35 | B57: Posting of Citations & Abatement | C57: The employer must inform affected employees and their representatives about all abatement activities by posting a copy (or summary) of each submission near the violation location for at least 3 working days. Employees must also be informed of their right to examine and copy abatement documents. | D57: Confirm that employee notification was completed for any cited violations. Ask the safety manager how employees were informed. Check for posting of abatement documents or meeting minutes referencing communication to affected employees. | E57: Select rating | F57: =IFERROR(ROUND(G57*VLOOKUP(E57,$M$2:$N$8,2,FALSE())/100,1),0) -> 0 | G57: 4 | J57: 29 CFR 1903.19(g) | O57: =IF(E57="Not Applicable",0,G57) -> 4
A58: STATE & LOCAL REQUIREMENTS
A59: RK-36 | B59: State & Local Requirements | C59: Some states require employers to establish a written Injury and Illness Prevention Program (IIPP), maintain a safety committee, or meet other requirements that exceed federal OSHA. These requirements are typically found in the State Plan's own standards or in state workers' compensation rules. | D59: Identify the state in which this establishment is located and confirm whether the state operates under a State Plan (rather than federal OSHA). If yes, identify any state-specific requirements (e.g., California's IIPP under Title 8 CCR 3203, Washington's Accident Prevention Program, Michigan's MIOSHA requirements). Confirm those programs are documented and active. | E59: Select rating | F59: =IFERROR(ROUND(G59*VLOOKUP(E59,$M$2:$N$8,2,FALSE())/100,1),0) -> 0 | G59: 6 | J59: State/local regulations | O59: =IF(E59="Not Applicable",0,G59) -> 6

Sheet LOTO
A1: LOCKOUT / TAGOUT (LOTO) COMPLIANCE AUDIT | M1: Rating | N1: Pct
A2: 29 CFR 1910.147 — The Control of Hazardous Energy. Prepared under attorney-client privilege. | M2: Best Practice | N2: 100
M3: Verified | N3: 100
A4: SITE: | B4: ='Pre-Audit Scoping'!D5 -> Test | D4: DATE(S): | E4: ='Pre-Audit Scoping'!D10 -> July 7-9 2026 | G4: AUDITOR(S): | H4: =TRIM('Pre-Audit Scoping'!D11)&IF(TRIM('Pre-Audit Scoping'!D12)<>"",", "&TRIM('Pre-Audit Scoping'!D12),"") -> Sara Wallon, Gabriel Wallon | M4: Low | N4: 85
M5: Moderate | N5: 70
A6: SCORING SUMMARY | M6: High | N6: 30
A7: Category | B7: Score | C7: Max | D7: Percentage % | F7: Finding Rating | G7: Count | M7: Very High | N7: 0
A8: TOTAL | B8: =SUM(F18:F36) -> 0 | C8: =SUM(O18:O36) -> 142 | D8: =IF(C8<>0,B8/C8,"N/A") -> 0 | F8: Best Practice | G8: =COUNTIF(E18:E36,"Best Practice") -> 0 | M8: Not Applicable | N8: 0
F9: Verified | G9: =COUNTIF(E18:E36,"Verified") -> 0
F10: Low | G10: =COUNTIF(E18:E36,"Low") -> 0
F11: Moderate | G11: =COUNTIF(E18:E36,"Moderate") -> 0
F12: High | G12: =COUNTIF(E18:E36,"High") -> 0
F13: Very High | G13: =COUNTIF(E18:E36,"Very High") -> 0
F14: Not Applicable | G14: =COUNTIF(E18:E36,"Not Applicable") -> 0
A15: OVERALL SCORE | D15: =D8 -> 0 | F15: Rating Tier: | G15: =IF(D8="N/A","N/A",IF(D8>=0.99,"Excellence Leader",IF(D8>=0.9,"Gold",IF(D8>=0.8,"Silver",IF(D8>=0.51,"Bronze","Developing"))))) -> Developing
A17: Item # | B17: Subsection | C17: Requirement | D17: Evidence to Look For | E17: Finding Rating | F17: Score | G17: Max | H17: Observations | I17: Recommendations | J17: Citation | K17: Auditor Notes | O17: Eff. Max
A18: GENERAL REQUIREMENTS
A19: LO-1 | B19: General Requirements | C19: A written energy control program must be established and consist of three elements: (1) documented energy control procedures (ECPs) for each machine/equipment; (2) employee training specific to each role; and (3) periodic inspections of the ECPs at least annually. | D19: Request the written LOTO/energy control program document. Confirm it explicitly addresses all three required elements. Check the revision date — the program should reflect current equipment. Confirm it is readily accessible to authorized employees (not locked in a manager's office). | E19: Select rating | F19: =IFERROR(ROUND(G19*VLOOKUP(E19,$M$2:$N$8,2,FALSE())/100,1),0) -> 0 | G19: 10 | J19: 29 CFR 1910.147(c)(1)-(c)(2) | O19: =IF(E19="Not Applicable",0,G19) -> 10
A20: LO-2 | B20: General Requirements | C20: Energy Control Procedures (ECPs) must be developed, documented, and used for each machine/equipment with hazardous energy. Each ECP must address 5 required content areas per 29 CFR 1910.147(c)(4). See Evidence column checklist. | D20: Request a complete list of all machines/equipment requiring ECPs. Sample 10% (minimum 5). For each sampled ECP, verify all 5 required elements are present and evaluate against the actual machine on the floor: □ (1) Steps to shut down and de-energize the machine using the established stopping procedure □ (2) Steps for placement, removal, and transfer of lockout/tagout devices □ (3) Requirements for testing or positioning to verify isolation (the try-out test) □ (4) Type and magnitude of each energy source (electrical voltage, hydraulic PSI, pneumatic PSI, stored mechanical energy, thermal, gravity) □ (5) Methods for controlling each energy type (which valve to close, which disconnect to lock, which bleeder to open, how to block gravity-loaded parts) Walk each sampled ECP to the actual machine: confirm every isolation point listed on the procedure exists on the equipment and is accessible. Flag any generic or copy-paste ECPs shared across multiple different machine types — these require correction. | E20: Select rating | F20: =IFERROR(ROUND(G20*VLOOKUP(E20,$M$2:$N$8,2,FALSE())/100,1),0) -> 0 | G20: 10 | J20: 29 CFR 1910.147(c)(4) | O20: =IF(E20="Not Applicable",0,G20) -> 10
A21: LO-3 | B21: General Requirements | C21: When a tagout device is used on an energy-isolating device that cannot be locked out, the tagout device must be attached at the same location where a lockout device would have been attached, if it were possible to do so. | D21: Walk 10% of the facility's energy-isolating devices (minimum 3 locations) that are identified as tagout-only. Confirm tags are attached directly to the energy-isolating device itself — not to adjacent piping, nearby conduit, or the machine body. Confirm the ECP documents why lockout is infeasible for each tagout-only application. | E21: Select rating | F21: =IFERROR(ROUND(G21*VLOOKUP(E21,$M$2:$N$8,2,FALSE())/100,1),0) -> 0 | G21: 6 | J21: 29 CFR 1910.147(c)(3)(i) | O21: =IF(E21="Not Applicable",0,G21) -> 6
A22: LO-4 | B22: General Requirements | C22: Where tagout is used in lieu of lockout, the employer must demonstrate that the tagout program will provide a level of safety equivalent to lockout. Equivalency is achieved by implementing additional safety measures such as: removing an isolating circuit element; blocking a controlling switch; opening an extra disconnecting device; or removing a valve handle. | D22: For each tagout-only application (from LO-3 sample): confirm the ECP documents at least one additional safety measure beyond just affixing a tag. Ask the authorized employee performing tagout to explain and demonstrate the additional measure. Tagout alone, without these supplemental measures, does not meet the equivalency standard. | E22: Select rating | F22: =IFERROR(ROUND(G22*VLOOKUP(E22,$M$2:$N$8,2,FALSE())/100,1),0) -> 0 | G22: 6 | J22: 29 CFR 1910.147(c)(3) | O22: =IF(E22="Not Applicable",0,G22) -> 6
A23: LO-5 | B23: General Requirements | C23: The employer must provide protective materials and hardware — including locks, tags, chains, wedges, key blocks, adapter pins, self-locking fasteners, and other hardware — as necessary to isolate, secure, or block machines or equipment from energy. This equipment must be provided at no cost to the employee. | D23: Physically inspect LOTO hardware stations (there should be at least one per work area). Confirm the station is stocked with sufficient locks, tags, hasps, and hardware for the number of authorized employees on the largest shift. Ask authorized employees whether they have ever been unable to obtain a LOTO device when needed. Confirm no employee purchases their own LOTO hardware. | E23: Select rating | F23: =IFERROR(ROUND(G23*VLOOKUP(E23,$M$2:$N$8,2,FALSE())/100,1),0) -> 0 | G23: 8 | J23: 29 CFR 1910.147(c)(5) | O23: =IF(E23="Not Applicable",0,G23) -> 8
A24: LO-6 | B24: General Requirements | C24: LOTO devices must meet four criteria: (1) Durable — capable of withstanding the environment and the use for which they are intended, including exposure to corrosive chemicals; tags must be able to withstand a 50-lb pullout force. (2) Standardized — same color, shape, or size within the facility, or at least the same print and format. (3) Substantial — locks must be substantial so they cannot be removed except by excessive force. (4) Identifiable — individually identified (unique to each authorized employee) and used exclusively for LOTO purposes — not for any other use. | D24: Inspect LOTO devices at 10% of LOTO hardware stations (minimum 2 stations). For each: confirm locks are individually keyed and assigned to one authorized employee; confirm tags bear a warning legend ('Do Not Start/Open/Energize') and the authorized employee's name; confirm the same color/style is used consistently throughout the facility; physically test a tag's attachment — it should require at least 50 lbs of force to remove. Ask whether any LOTO devices are used for non-energy-control purposes (e.g., tool storage locks). | E24: Select rating | F24: =IFERROR(ROUND(G24*VLOOKUP(E24,$M$2:$N$8,2,FALSE())/100,1),0) -> 0 | G24: 8 | J24: 29 CFR 1910.147(c)(5)(ii)-(c)(5)(iii) | O24: =IF(E24="Not Applicable",0,G24) -> 8
A25: LO-7 | B25: General Requirements | C25: At least annually, an authorized employee (other than the one using the procedure) must inspect each ECP in use and certify that the inspection was conducted. For lockout procedures, the inspection must include a review with each authorized employee of their responsibilities under the procedure. For tagout procedures, the inspection must include a review of tagout limitations in addition to the procedure review. The certification must document the machine/equipment, the date of inspection, the employees involved, and the inspector's name. | D25: Request annual ECP inspection records for 100% of the current calendar year (or the most recent 12 months). Confirm: (1) every ECP in active use has been inspected within the past 12 months; (2) the inspector is an authorized employee — not the person who normally uses that procedure; (3) the certification document identifies the machine, date, employees involved, and inspector. Note any ECPs with no inspection on file — this is among the most frequently cited LOTO deficiencies. | E25: Select rating | F25: =IFERROR(ROUND(G25*VLOOKUP(E25,$M$2:$N$8,2,FALSE())/100,1),0) -> 0 | G25: 10 | J25: 29 CFR 1910.147(c)(6)(i)-(c)(6)(ii) | O25: =IF(E25="Not Applicable",0,G25) -> 10
A26: LO-8 | B26: General Requirements | C26: Training must be provided to ensure all employees understand the purpose and function of the energy control program and have the knowledge and skills required for their role. Authorized employees must be trained on: (1) recognition of applicable hazardous energy sources; (2) type and magnitude of energy in the workplace; and (3) methods and means necessary for energy isolation and control. Affected employees must be trained on: (1) the purpose and use of the energy control procedure; and (2) the prohibition on restarting or re-energizing equipment under LOTO. Other employees who work in areas where LOTO is used must be trained on the prohibition and the purpose of LOTO. | D26: Request LOTO training records for 100% of authorized employees and a 10% sample of affected employees (minimum 3). Confirm: (1) initial training was completed before the employee performed LOTO; (2) training records identify which ECP(s) the employee is authorized on; (3) training covers the specific energy types at this facility. Interview 1-2 authorized employees: ask them to explain the type and magnitude of energy on one of their assigned machines, the order of lockout steps, and what they do at shift change if their lock must stay applied. | E26: Select rating | F26: =IFERROR(ROUND(G26*VLOOKUP(E26,$M$2:$N$8,2,FALSE())/100,1),0) -> 0 | G26: 10 | J26: 29 CFR 1910.147(c)(7)(i)-(c)(7)(ii),(c)(7)(iv) | O26: =IF(E26="Not Applicable",0,G26) -> 10
A27: LO-9 | B27: General Requirements | C27: Retraining must be provided when: (1) there is reason to believe the employee does not have the required knowledge or skills (e.g., following an incident or observed deviation); (2) there is a change in job assignments; (3) there is a change in machines, equipment, or processes that presents a new hazardous energy hazard; or (4) there is a change in the energy control procedures. | D27: Ask for a list of equipment additions or process changes in the past 12 months. Confirm retraining records exist for affected authorized employees when new equipment was introduced. Review any near-miss or LOTO incident reports — confirm retraining was completed as a corrective action. Sample 10% of new equipment commissioning records (minimum 1) to trace the ECP development and employee retraining. | E27: Select rating | F27: =IFERROR(ROUND(G27*VLOOKUP(E27,$M$2:$N$8,2,FALSE())/100,1),0) -> 0 | G27: 8 | J27: 29 CFR 1910.147(c)(7)(iii) | O27: =IF(E27="Not Applicable",0,G27) -> 8
A28: LO-10 | B28: General Requirements | C28: LOTO procedures must be performed only by the authorized employees who are performing the servicing or maintenance. Affected employees (operators) must not apply or remove lockout/tagout devices. | D28: Interview 10% of production operators (minimum 3). Ask: 'If you needed to clear a jam on your machine, who would apply the lockout?' The correct answer is a trained and authorized employee — not the operator themselves, unless the operator has also been designated as an authorized employee for that specific task. Review any documented cases where an operator was observed applying or removing a lock. | E28: Select rating | F28: =IFERROR(ROUND(G28*VLOOKUP(E28,$M$2:$N$8,2,FALSE())/100,1),0) -> 0 | G28: 8 | J28: 29 CFR 1910.147(c)(8) | O28: =IF(E28="Not Applicable",0,G28) -> 8
A29: LO-11 | B29: General Requirements | C29: Affected employees must be notified by the employer or the authorized employee both: (1) before a lockout or tagout device is applied; and (2) after the device is removed and before the machine is re-started. | D29: Interview 10% of affected employees (minimum 3). Ask: 'How are you told when a lock is being put on your machine? And when it's been removed?' Confirm the ECP or written program describes a specific notification method (departmental notification, physical communication, visual signal). Review any LOTO-related incident reports for cases where communication failed. | E29: Select rating | F29: =IFERROR(ROUND(G29*VLOOKUP(E29,$M$2:$N$8,2,FALSE())/100,1),0) -> 0 | G29: 6 | J29: 29 CFR 1910.147(c)(9) | O29: =IF(E29="Not Applicable",0,G29) -> 6
A30: LO-12 | B30: General Requirements | C30: When lockout/tagout devices must be temporarily removed from an energy-isolating device to test or position the machine, the following specific sequence must be followed: (1) Clear the machine of tools and materials; (2) remove employees from the machine area; (3) remove lockout/tagout devices; (4) energize and proceed with testing/positioning; (5) de-energize all systems; (6) reapply energy control measures before continuing servicing work. | D30: Ask the maintenance supervisor whether testing or repositioning during maintenance ever requires temporary re-energization (e.g., bump tests, valve positioning checks, alignment verification). If yes, request the ECP section covering this sequence and confirm all six steps are documented. Observe or interview an authorized employee to confirm they follow this specific order. | E30: Select rating | F30: =IFERROR(ROUND(G30*VLOOKUP(E30,$M$2:$N$8,2,FALSE())/100,1),0) -> 0 | G30: 8 | J30: 29 CFR 1910.147(f)(1) | O30: =IF(E30="Not Applicable",0,G30) -> 8
... A33: LO-15 | B33: General Requirements | C33: Procedures must be in place to ensure that LOTO protection is maintained during shift or personnel changes. The minimum protection method is: the incoming authorized employee applies their lock before the outgoing employee removes theirs — so the equipment is never left unprotected during the transition. | D33: Ask the safety manager and an authorized employee how shift-change LOTO transfers are handled. Confirm the written procedure requires the incoming employee's lock to be applied before the outgoing employee's lock is removed. Also confirm there is a documented procedure for emergency lock removal when an authorized employee is unavailable (e.g., leaves sick, terminated) — this must require approval by supervision and must not simply involve cutting the lock. | E33: Select rating | F33: =IFERROR(ROUND(G33*VLOOKUP(E33,$M$2:$N$8,2,FALSE())/100,1),0) -> 0 | G33: 8 | J33: 29 CFR 1910.147(f)(4) | O33: =IF(E33="Not Applicable",0,G33) -> 8
A34: APPLICATION AND RELEASE OF ENERGY CONTROLS
A35: LO-16 | B35: Application and Release of Energy Controls | C35: All energy control applications must follow a documented 7-step sequence per 29 CFR 1910.147(d). ECPs that omit stored/residual energy steps are among the most commonly cited LOTO violations. | D35: Select 10% of active ECPs (minimum 3) that involve complex or multiple energy types. Walk each ECP to the actual machine with an authorized employee. Confirm the ECP includes all 7 steps in order: □ (1) Notify affected employees that the machine must be shut down and locked/tagged out □ (2) Identify the type and magnitude of energy and the hazards posed □ (3) Shut down and de-energize the machine using the established stopping procedure □ (4) Isolate the machine from each energy source using the energy-isolating device(s) □ (5) Apply lockout or tagout device(s) to each energy-isolating device □ (6) Release, restrain, or otherwise render safe all stored/residual energy (capacitor bleed-down; spring tension release; hydraulic/pneumatic bleed; blocking gravity-loaded parts; thermal cool-down) □ (7) Verify isolation is complete — attempt to start the machine (try-out test) or test with a meter BEFORE touching any part Grade down significantly for any ECP that addresses only electrical isolation and omits stored/residual energy steps. | E35: Select rating | F35: =IFERROR(ROUND(G35*VLOOKUP(E35,$M$2:$N$8,2,FALSE())/100,1),0) -> 0 | G35: 10 | J35: 29 CFR 1910.147(d) | O35: =IF(E35="Not Applicable",0,G35) -> 10
A36: LO-17 | B36: Application and Release of Energy Controls | C36: Before energy is restored and LOTO devices are removed, a documented 6-step sequence must be followed per 29 CFR 1910.147(e). An emergency lock removal procedure must also exist for situations where the authorized employee is unavailable. | D36: Review the energy release section of 10% of ECPs (minimum 3). Confirm the ECP includes all 6 steps in order: □ (1) Ensure work on the machine is complete □ (2) Ensure all tools, materials, and non-essential items are removed from the machine □ (3) Ensure all employees are safely positioned away from the machine □ (4) Notify affected employees that LOTO devices are being removed and energy will be restored □ (5) Remove each lockout/tagout device only by the authorized employee who applied it □ (6) Restore energy Also confirm: a written emergency lock removal procedure exists for situations where the authorized employee has left the site. Ask the supervisor: 'What do you do if an employee goes home sick and leaves their lock on equipment?' — the answer must reference a written procedure requiring supervisor authorization (never simply cutting the lock without authorization). | E36: Select rating | F36: =IFERROR(ROUND(G36*VLOOKUP(E36,$M$2:$N$8,2,FALSE())/100,1),0) -> 0 | G36: 10 | J36: 29 CFR 1910.147(e) | O36: =IF(E36="Not Applicable",0,G36) -> 10

Sheet Egress & Emergency Action
A1: EGRESS & EMERGENCY ACTION COMPLIANCE AUDIT | M1: Rating | N1: Pct
A2: 29 CFR 1910.36-39 — Exit Routes, Emergency Action Plans & Fire Prevention Plans. Prepared under attorney-client privilege. | M2: Best Practice | N2: 100
M3: Verified | N3: 100
A4: SITE: | B4: ='Pre-Audit Scoping'!D5 -> Test | D4: DATE(S): | E4: ='Pre-Audit Scoping'!D10 -> July 7-9 2026 | G4: AUDITOR(S): | H4: =TRIM('Pre-Audit Scoping'!D11)&IF(TRIM('Pre-Audit Scoping'!D12)<>"",", "&TRIM('Pre-Audit Scoping'!D12),"") -> Sara Wallon, Gabriel Wallon | M4: Low | N4: 85
M5: Moderate | N5: 70
A6: SCORING SUMMARY | M6: High | N6: 30
A7: Category | B7: Score | C7: Max | D7: Percentage % | F7: Finding Rating | G7: Count | M7: Very High | N7: 0
A8: TOTAL | B8: =SUM(F18:F40) -> 0 | C8: =SUM(O18:O40) -> 147 | D8: =IF(C8<>0,B8/C8,"N/A") -> 0 | F8: Best Practice | G8: =COUNTIF(E18:E40,"Best Practice") -> 0 | M8: Not Applicable | N8: 0
F9: Verified | G9: =COUNTIF(E18:E40,"Verified") -> 0
F10: Low | G10: =COUNTIF(E18:E40,"Low") -> 0
F11: Moderate | G11: =COUNTIF(E18:E40,"Moderate") -> 0
F12: High | G12: =COUNTIF(E18:E40,"High") -> 0
F13: Very High | G13: =COUNTIF(E18:E40,"Very High") -> 0
F14: Not Applicable | G14: =COUNTIF(E18:E40,"Not Applicable") -> 0
A15: OVERALL SCORE | D15: =D8 -> 0 | F15: Rating Tier: | G15: =IF(D8="N/A","N/A",IF(D8>=0.99,"Excellence Leader",IF(D8>=0.9,"Gold",IF(D8>=0.8,"Silver",IF(D8>=0.51,"Bronze","Developing"))))) -> Developing
A17: Item # | B17: Subsection | C17: Requirement | D17: Evidence to Look For | E17: Finding Rating | F17: Score | G17: Max | H17: Observations | I17: Recommendations | J17: Citation | K17: Auditor Notes | O17: Eff. Max
A18: EXIT ROUTE DESIGN & CONSTRUCTION
A19: EG-1 | B19: Exit Route Design & Construction | C19: Exit routes must be permanent parts of the workplace. Each exit must be a permanent structural component — not a temporary door, movable partition, or makeshift opening — and must lead directly to a safe area outside the building. | D19: Walk 10% of identified exit routes (minimum 3). Confirm each exit is a permanent structural component. Look for any exits that route through a space that could be locked, occupied, or blocked during an emergency. Note any exit that depends on a door that could be locked from the other side. | E19: Select rating | F19: =IFERROR(ROUND(G19*VLOOKUP(E19,$M$2:$N$8,2,FALSE())/100,1),0) -> 0 | G19: 8 | J19: 29 CFR 1910.36(a)(1) | O19: =IF(E19="Not Applicable",0,G19) -> 8
A20: EG-2 | B20: Exit Route Design & Construction | C20: Each exit must be separated from other areas of the building by construction materials that have the required fire resistance ratings. Openings into an exit enclosure must be limited — only those necessary for occupant use. | D20: Walk exit stairwells and corridors. Confirm enclosing walls, ceilings, and floors have appropriate fire-resistance ratings. Look for holes, penetrations, or unsealed conduit openings in exit enclosure walls. Confirm doors into the exit enclosure are self-closing fire-rated doors (not propped open). | E20: Select rating | F20: =IFERROR(ROUND(G20*VLOOKUP(E20,$M$2:$N$8,2,FALSE())/100,1),0) -> 0 | G20: 6 | J20: 29 CFR 1910.36(a)(2)-(a)(3) | O20: =IF(E20="Not Applicable",0,G20) -> 6
A21: EG-3 | B21: Exit Route Design & Construction | C21: At least two exit routes must be available to permit prompt evacuation. Exception: one exit is acceptable if the number of employees, size, occupancy, or arrangement allows all employees to evacuate safely. | D21: Confirm the number of exit routes from each major work area. For multi-story buildings or areas with large employee populations, confirm at least two exits are available and that they are separated by sufficient distance so a single event cannot block both. | E21: Select rating | F21: =IFERROR(ROUND(G21*VLOOKUP(E21,$M$2:$N$8,2,FALSE())/100,1),0) -> 0 | G21: 10 | J21: 29 CFR 1910.36(b)(1)-(b)(3) | O21: =IF(E21="Not Applicable",0,G21) -> 10
A22: EG-4 | B22: Exit Route Design & Construction | C22: Each exit discharge must lead directly to the street, walkway, refuge area, public way, or other open space with room for evacuated employees. Exit stairs that continue below the exit discharge level must have barriers to prevent employees from accidentally continuing past the exit discharge level. | D22: Walk to the exterior discharge point of each sampled exit route. Confirm the discharge location is an open, unobstructed space large enough to accommodate building occupants. For multi-story exit stairs, confirm a barrier (door, gate, or signage) at the exit discharge level prevents employees from continuing to a lower level. | E22: Select rating | F22: =IFERROR(ROUND(G22*VLOOKUP(E22,$M$2:$N$8,2,FALSE())/100,1),0) -> 0 | G22: 8 | J22: 29 CFR 1910.36(c)(1)-(c)(2); 1910.36(d) | O22: =IF(E22="Not Applicable",0,G22) -> 8
A23: EG-5 | B23: Exit Route Design & Construction | C23: Exit doors must be unlocked and able to be freely opened from the inside at all times without a key, tool, special knowledge, or effort. Delayed-egress hardware (up to 15-second delay) is permitted only in specific limited applications and only where approved by the authority having jurisdiction. | D23: Test 10% of exit doors (minimum 3) during the audit. Push open the door from the inside without any key or special device — it must open freely. Confirm no padlocks, deadbolts, or keyed locks are installed on the interior side of exit doors. If delayed-egress hardware is present, confirm it is specifically approved for the application. | E23: Select rating | F23: =IFERROR(ROUND(G23*VLOOKUP(E23,$M$2:$N$8,2,FALSE())/100,1),0) -> 0 | G23: 10 | J23: 29 CFR 1910.36(e)(1)-(e)(3) | O23: =IF(E23="Not Applicable",0,G23) -> 10
A24: EG-6 | B24: Exit Route Design & Construction | C24: Exit doors must meet design requirements: side-hinged; open in the direction of exit travel for rooms with 50 or more occupants or hazardous areas; not be a sliding, revolving, or overhead door. | D24: Walk to 10% of exit doors (minimum 3). Confirm each is a side-hinged door. For any exit door serving a hazardous area or a room with 50+ occupants, confirm the door swings in the direction of travel (outward). Note any sliding or roll-up doors installed on exit routes. | E24: Select rating | F24: =IFERROR(ROUND(G24*VLOOKUP(E24,$M$2:$N$8,2,FALSE())/100,1),0) -> 0 | G24: 6 | J24: 29 CFR 1910.36(e)(4)-(e)(6) | O24: =IF(E24="Not Applicable",0,G24) -> 6
A25: EG-7 | B25: Exit Route Design & Construction | C25: Exit routes must have adequate capacity for all occupants. Exit route height must be at least 7 feet 6 inches (2.3 m) for the entire length. Width must be sufficient for the number of occupants served, but in no case less than 28 inches (71 cm). No locked room, device, or condition may reduce capacity below required levels. | D25: Walk 10% of exit corridors and stairways (minimum 3). Measure or estimate width — confirm no pinch points below 28 inches. Look for stored materials, equipment, or other obstructions that reduce width. Measure or estimate ceiling height — confirm clearance is at least 7 feet 6 inches throughout. | E25: Select rating | F25: =IFERROR(ROUND(G25*VLOOKUP(E25,$M$2:$N$8,2,FALSE())/100,1),0) -> 0 | G25: 8 | J25: 29 CFR 1910.36(f)-(g) | O25: =IF(E25="Not Applicable",0,G25) -> 8
A26: EXIT ROUTE MAINTENANCE & MARKING
A27: EG-8 | B27: Exit Route Maintenance & Marking | C27: Exit routes must be kept free of explosive or highly flammable furnishings, decorations, or other materials. Safeguards against dangerous conditions must be maintained on exit routes. | D27: Walk all identified exit routes and observe: no flammable materials stored in corridors; no compressed gas cylinders, paint, solvents, or other hazardous materials blocking or lining the exit path; fire door closers and latches are functional. | E27: Select rating | F27: =IFERROR(ROUND(G27*VLOOKUP(E27,$M$2:$N$8,2,FALSE())/100,1),0) -> 0 | G27: 8 | J27: 29 CFR 1910.37(a)(1)-(a)(3) | O27: =IF(E27="Not Applicable",0,G27) -> 8
A28: EG-9 | B28: Exit Route Maintenance & Marking | C28: Each exit and the path of travel to it must be adequately lit so employees can see along the exit route. Lighting must be sufficient for a person to see with normal vision. | D28: Walk exit routes during normal work hours. Confirm lighting is operational throughout each route, including any stairwells. Ask whether there is emergency backup lighting that activates on power failure — if so, confirm it is tested per the manufacturer's schedule. | E28: Select rating | F28: =IFERROR(ROUND(G28*VLOOKUP(E28,$M$2:$N$8,2,FALSE())/100,1),0) -> 0 | G28: 6 | J28: 29 CFR 1910.37(b)(1) | O28: =IF(E28="Not Applicable",0,G28) -> 6
A29: EG-10 | B29: Exit Route Maintenance & Marking | C29: Each exit must be clearly marked by a visible sign with the word 'EXIT' in plainly legible letters not less than 6 inches high and 3/4 inch wide stroke. Any door, passageway, or stairway that could be mistaken for an exit must be marked 'NOT AN EXIT' or similar. Each exit route must be marked with signs posted along the route so employees always know the direction of exit travel. | D29: Walk all exit routes. Confirm: EXIT signs are posted at each exit door and at decision points along the route; signs are illuminated or self-luminescent; no burned-out exit signs; doors that could be mistaken for exits (supply rooms, storage) are clearly marked 'NOT AN EXIT.' Sample 10% of exit signs (minimum 5) and test illumination by covering the power source indicator. | E29: Select rating | F29: =IFERROR(ROUND(G29*VLOOKUP(E29,$M$2:$N$8,2,FALSE())/100,1),0) -> 0 | G29: 8 | J29: 29 CFR 1910.37(b)(2)-(b)(5) | O29: =IF(E29="Not Applicable",0,G29) -> 8
A30: EG-11 | B30: Exit Route Maintenance & Marking | C30: Exit routes must be maintained during construction, repairs, or alterations. If an exit route is temporarily unavailable, an alternate exit must be available. The fire retardant properties of paint or coatings used in exit enclosures must be maintained. | D30: Ask whether any construction or renovation is currently ongoing. If yes, confirm alternate exit routes are in place and marked. Ask about any recent painting in exit stairwells — confirm fire-retardant paint was used where required. | E30: Select rating | F30: =IFERROR(ROUND(G30*VLOOKUP(E30,$M$2:$N$8,2,FALSE())/100,1),0) -> 0 | G30: 5 | J30: 29 CFR 1910.37(c)-(d) | O30: =IF(E30="Not Applicable",0,G30) -> 5
A31: EG-12 | B31: Exit Route Maintenance & Marking | C31: An employee alarm system must be operable, audible throughout the building, and maintained. The alarm must provide enough warning time for employees to escape safely before conditions become hazardous. | D31: Ask for the most recent alarm system test record. Confirm the alarm was audible in all occupied areas (including high-noise production areas and restrooms). Confirm the alarm system is maintained per the manufacturer's schedule and NFPA 72 requirements. Walk to the farthest point in the building from an alarm device and assess audibility. | E31: Select rating | F31: =IFERROR(ROUND(G31*VLOOKUP(E31,$M$2:$N$8,2,FALSE())/100,1),0) -> 0 | G31: 8 | J31: 29 CFR 1910.37(e)(1)-(e)(3) | O31: =IF(E31="Not Applicable",0,G31) -> 8
A32: EMERGENCY ACTION PLANS
A33: EG-13 | B33: Emergency Action Plans | C33: The employer must have a written Emergency Action Plan (EAP) whenever an OSHA standard requires one or whenever the employer must have an employee alarm system. The EAP must be kept in the workplace and available for employee review. | D33: Request the written EAP. Confirm it is current (review date within the past 12 months or after any significant change to building layout, occupancy, or hazards). Confirm it is physically accessible to all employees — not solely in an electronic system that may be unavailable during an emergency. | E33: Select rating | F33: =IFERROR(ROUND(G33*VLOOKUP(E33,$M$2:$N$8,2,FALSE())/100,1),0) -> 0 | G33: 10 | J33: 29 CFR 1910.38(b)-(c) | O33: =IF(E33="Not Applicable",0,G33) -> 10
A34: EG-14 | B34: Emergency Action Plans | C34: The EAP must contain all of the following required elements: (1) Procedures for reporting a fire or other emergency (2) Procedures for emergency evacuation, including type of evacuation and exit route assignments (3) Procedures to be followed by employees who remain to operate critical plant operations before they evacuate (4) Procedures to account for all employees after evacuation (5) Procedures for employees performing rescue or medical duties (6) The name or job title of every employee who may be contacted by employees who need more information about the plan or an explanation of their duties under the plan | D34: CHECKLIST — review the EAP against all 6 required elements. Mark each: Verified (present and complete), Partial, or Absent. □ (1) Fire/emergency reporting procedures (who to call, how to activate alarm) □ (2) Evacuation procedures with exit route map or assignments by area □ (3) Procedures for critical operation employees who must stay until safe shutdown □ (4) Employee accounting procedures after evacuation (headcount, assembly point, accountability method) □ (5) Rescue and medical duty procedures and designated personnel □ (6) Employee contact for questions about the plan (name and/or job title) Pay particular attention to elements (4) and (6) — these are frequently incomplete or generic. | E34: Select rating | F34: =IFERROR(ROUND(G34*VLOOKUP(E34,$M$2:$N$8,2,FALSE())/100,1),0) -> 0 | G34: 10 | J34: 29 CFR 1910.38(c)(1)-(c)(6) | O34: =IF(E34="Not Applicable",0,G34) -> 10
A35: EG-15 | B35: Emergency Action Plans | C35: The employer must designate and train employees to assist in safe and orderly evacuation. Training must be provided at initial assignment, whenever the plan changes, and at least annually. | D35: Request training records for designated floor wardens or evacuation assistants. Confirm initial training before assignment and annual refresher. Interview a designated floor warden: ask what their responsibilities are during evacuation, how they account for employees in their area, and where the assembly point is. Confirm they know what to do if a special-needs employee requires assistance. | E35: Select rating | F35: =IFERROR(ROUND(G35*VLOOKUP(E35,$M$2:$N$8,2,FALSE())/100,1),0) -> 0 | G35: 8 | J35: 29 CFR 1910.38(d)-(e) | O35: =IF(E35="Not Applicable",0,G35) -> 8
A36: EG-16 | B36: Emergency Action Plans | C36: The employer must review the EAP with each employee at the following times: when the plan is developed or the employee is assigned initially; when the employee's responsibilities change; and when the plan changes. | D36: Request records showing EAP review with employees. Confirm the review method (drill, training session, orientation). Interview 10% of employees (minimum 5): ask where the nearest exit is from their workstation, where the assembly point is, and who their floor warden is. Gap between training content and employee knowledge is a finding. | E36: Select rating | F36: =IFERROR(ROUND(G36*VLOOKUP(E36,$M$2:$N$8,2,FALSE())/100,1),0) -> 0 | G36: 8 | J36: 29 CFR 1910.38(f) | O36: =IF(E36="Not Applicable",0,G36) -> 8
A37: FIRE PREVENTION PLANS
A38: EG-17 | B38: Fire Prevention Plans | C38: Where an OSHA standard requires a Fire Prevention Plan (FPP), it must be in writing, kept in the workplace, and available for employee review. Exception: the employer may communicate the plan orally to employees if there are 10 or fewer employees. | D38: Confirm whether a Fire Prevention Plan is required by any OSHA standard applicable to this facility (e.g., flammable liquids, spray finishing). If required, request the written FPP. Confirm it is current and accessible. | E38: Select rating | F38: =IFERROR(ROUND(G38*VLOOKUP(E38,$M$2:$N$8,2,FALSE())/100,1),0) -> 0 | G38: 6 | J38: 29 CFR 1910.39(b)-(c) | O38: =IF(E38="Not Applicable",0,G38) -> 6
A39: EG-18 | B39: Fire Prevention Plans | C39: The Fire Prevention Plan must contain: (1) a list of all major fire hazards, proper handling and storage procedures, potential ignition sources, and the type of fire protection equipment needed; (2) procedures to control accumulations of flammable and combustible waste materials; (3) procedures for regular maintenance of equipment designed to prevent or control sources of ignition or fires; (4) the name or job title of employees responsible for maintaining fire prevention equipment; (5) the name or job title of employees responsible for the control of fuel source hazards. | D39: CHECKLIST — review the FPP against all 5 required elements: □ (1) Major fire hazards list with handling/storage procedures, ignition sources, and equipment type needed □ (2) Procedures to control flammable/combustible waste accumulations □ (3) Maintenance procedures for ignition-control equipment □ (4) Named responsibility for fire prevention equipment maintenance □ (5) Named responsibility for fuel source hazard control For a gypsum manufacturing facility, the FPP should specifically address gypsum dust accumulation (combustible dust), fuel storage, and any natural gas or propane used in the drying process. | E39: Select rating | F39: =IFERROR(ROUND(G39*VLOOKUP(E39,$M$2:$N$8,2,FALSE())/100,1),0) -> 0 | G39: 8 | J39: 29 CFR 1910.39(c)(1)-(c)(5) | O39: =IF(E39="Not Applicable",0,G39) -> 8
A40: EG-19 | B40: Fire Prevention Plans | C40: The employer must inform employees of the fire hazards of the materials and processes to which they are exposed, and review with each employee those parts of the FPP necessary for self-protection. | D40: Request evidence that fire hazard information has been communicated to employees (training records, new hire orientation content, toolbox talks). Interview 10% of employees (minimum 5) in areas with fire hazards: ask what fire hazards exist in their work area, what they would do if they discovered a fire, and whether they have been trained to use a fire extinguisher. | E40: Select rating | F40: =IFERROR(ROUND(G40*VLOOKUP(E40,$M$2:$N$8,2,FALSE())/100,1),0) -> 0 | G40: 6 | J40: 29 CFR 1910.39(d) | O40: =IF(E40="Not Applicable",0,G40) -> 6

Sheet Fire Protection & Alarms
A1: FIRE PROTECTION & ALARMS COMPLIANCE AUDIT | M1: Rating | N1: Pct
A2: 29 CFR 1910.157-165 — Fire Protection, Detection & Employee Alarm Systems. Prepared under attorney-client privilege. | M2: Best Practice | N2: 100
M3: Verified | N3: 100
A4: SITE: | B4: ='Pre-Audit Scoping'!D5 -> Test | D4: DATE(S): | E4: ='Pre-Audit Scoping'!D10 -> July 7-9 2026 | G4: AUDITOR(S): | H4: =TRIM('Pre-Audit Scoping'!D11)&IF(TRIM('Pre-Audit Scoping'!D12)<>"",", "&TRIM('Pre-Audit Scoping'!D12),"") -> Sara Wallon, Gabriel Wallon | M4: Low | N4: 85
M5: Moderate | N5: 70
A6: SCORING SUMMARY | M6: High | N6: 30
A7: Category | B7: Score | C7: Max | D7: Percentage % | F7: Finding Rating | G7: Count | M7: Very High | N7: 0
A8: TOTAL | B8: =SUM(F18:F40) -> 0 | C8: =SUM(O18:O40) -> 124 | D8: =IF(C8<>0,B8/C8,"N/A") -> 0 | F8: Best Practice | G8: =COUNTIF(E18:E40,"Best Practice") -> 0 | M8: Not Applicable | N8: 0
F9: Verified | G9: =COUNTIF(E18:E40,"Verified") -> 0
F10: Low | G10: =COUNTIF(E18:E40,"Low") -> 0
F11: Moderate | G11: =COUNTIF(E18:E40,"Moderate") -> 0
F12: High | G12: =COUNTIF(E18:E40,"High") -> 0
F13: Very High | G13: =COUNTIF(E18:E40,"Very High") -> 0
F14: Not Applicable | G14: =COUNTIF(E18:E40,"Not Applicable") -> 0
A15: OVERALL SCORE | D15: =D8 -> 0 | F15: Rating Tier: | G15: =IF(D8="N/A","N/A",IF(D8>=0.99,"Excellence Leader",IF(D8>=0.9,"Gold",IF(D8>=0.8,"Silver",IF(D8>=0.51,"Bronze","Developing"))))) -> Developing
A17: Item # | B17: Subsection | C17: Requirement | D17: Evidence to Look For | E17: Finding Rating | F17: Score | G17: Max | H17: Observations | I17: Recommendations | J17: Citation | K17: Auditor Notes | O17: Eff. Max
A18: PORTABLE FIRE EXTINGUISHERS
A19: FP-1 | B19: Portable Fire Extinguishers | C19: Only approved portable fire extinguishers are permitted. Extinguishers must be mounted, located, and identified so they are readily accessible to employees without subjecting them to injury. Extinguishers must not be obstructed or obscured from view. | D19: Walk 10% of fire extinguisher locations (minimum 10). For each: confirm the extinguisher is mounted in its designated location (not sitting on the floor); the mounting location is clearly marked; there are no obstructions blocking access; the unit is visible without needing to move materials. Note any locations where the extinguisher has been removed or the location is unoccupied. | E19: Select rating | F19: =IFERROR(ROUND(G19*VLOOKUP(E19,$M$2:$N$8,2,FALSE())/100,1),0) -> 0 | G19: 8 | J19: 29 CFR 1910.157(c)(1) | O19: =IF(E19="Not Applicable",0,G19) -> 8
A20: FP-2 | B20: Portable Fire Extinguishers | C20: Portable fire extinguishers must be maintained in a fully charged, operable condition and kept in their designated locations. Monthly visual inspections and annual maintenance checks by a licensed service provider are required. | D20: Inspect 10% of extinguishers (minimum 10). Confirm: the monthly inspection tag has been initialed within the last 30 days; the pressure gauge needle is in the green zone; the pull pin is intact with the tamper seal; there is no visible physical damage, corrosion, or nozzle clogging; the annual service tag shows service within the past 12 months. Ask to see the extinguisher service records for the past 12 months. | E20: Select rating | F20: =IFERROR(ROUND(G20*VLOOKUP(E20,$M$2:$N$8,2,FALSE())/100,1),0) -> 0 | G20: 10 | J20: 29 CFR 1910.157(e)(1)-(e)(4) | O20: =IF(E20="Not Applicable",0,G20) -> 10
